Workbook

Sheet Pipeline Summary
A1: WAIFF India Edition — Outreach Pipeline Summary
A2: Live dashboard, pulled from Targets / Gmail Tracker / LinkedIn Tracker. Update the two blue input cells; everything else recalculates.
A4: SENDING RAMP
A5: Campaign start date | B5: 46265
A6: Days into campaign (today) | B6: =IF($B$5="","",TODAY()-$B$5+1)
A7: Today's daily send target | B7: =IF($B$5="","",IF((TODAY()-$B$5+1)<=3,25,IF((TODAY()-$B$5+1)<=7,60,IF((TODAY()-$B$5+1)<=14,75,100))))
A8: Note (3 Sep 2026): ramp started mid-sequence — Aditya was already sending from his own Gmail, so days 1-3 were skipped. Days 4-7 bumped to 60/day (from the brief's default 50). Days 8-14 and 15+ continue on the original 75 / 100 schedule.
A9: Ramp reference (brief section 8)
A10: Days | B10: Sends/day
A11: Days 1-3 | B11: 25
A12: Days 4-7 | B12: 60
A13: Days 8-14 | B13: 75
A14: Days 15+ | B14: 100
A16: PIPELINE COUNTS (from Targets tab)
A17: Total companies logged | B17: =COUNTA(Targets!$A$5:$A$2000)
A18: Excluded (section 4) | B18: =COUNTIF(Targets!$O$5:$O$2000,"Excluded")
A19: Not started | B19: =COUNTIF(Targets!$O$5:$O$2000,"Not started")
A20: Researching | B20: =COUNTIF(Targets!$O$5:$O$2000,"Researching")
A21: Ready to send | B21: =COUNTIF(Targets!$O$5:$O$2000,"Ready to send")
A22: Sent | B22: =COUNTIF(Targets!$O$5:$O$2000,"Sent")
A23: Replied | B23: =COUNTIF(Targets!$O$5:$O$2000,"Replied")
A24: Meeting booked | B24: =COUNTIF(Targets!$O$5:$O$2000,"Meeting booked")
A25: Dormant (past day 25, no response) | B25: =COUNTIF(Targets!$O$5:$O$2000,"Dormant")
A27: EMAIL / FORM ACTIVITY (from Gmail Tracker tab)
A28: Total companies sent (email + form) | B28: =COUNTA('Gmail Tracker'!$A$5:$A$2000)
A29: Bounces | B29: =COUNTIF('Gmail Tracker'!$G$5:$G$2000,"Y")
A30: Bounce rate | B30: =IFERROR(B29/B28,"")
A31: Replies | B31: =COUNTIF('Gmail Tracker'!$H$5:$H$2000,"Y")
A32: Reply rate | B32: =IFERROR(B31/B28,"")
A33: Meetings booked | B33: =COUNTIF('Gmail Tracker'!$M$5:$M$2000,"Y")
A35: LINKEDIN ACTIVITY (from LinkedIn Tracker tab)
A36: Profiles logged (all batches) | B36: =COUNTA('LinkedIn Tracker'!$C$5:$C$2000)
A37: Connections sent | B37: =COUNTA('LinkedIn Tracker'!$H$5:$H$2000)
A38: Connections accepted | B38: =COUNTIF('LinkedIn Tracker'!$I$5:$I$2000,"Accepted")
A39: Accept rate | B39: =IFERROR(B38/B37,"")
A40: Messages sent | B40: =COUNTA('LinkedIn Tracker'!$J$5:$J$2000)
A41: Replies | B41: =COUNTIF('LinkedIn Tracker'!$K$5:$K$2000,"Y")
A43: 48-HOUR REVIEW (fill in manually every 2 days — brief section 10c)
A44: Date of review
A45: Best-performing segment
A46: Worst-performing segment
A47: Subject lines working
A48: Follow-up stage working best
A49: One change recommended

Sheet Targets
A1: WAIFF India — Targets (master company list, one row per company)
A2: One-pass rule: each company gets exactly one row. Check for duplicates and section-4 exclusions here before adding. Row 4 is an example only — real rows start at row 5.
A3: Company | B3: Priority Bucket | C3: HQ / Region | D3: Relevance (why qualified) | E3: Capacity check (Y/N/Unknown) | F3: Reachability - named contact found (Y/N) | G3: Excluded? (Y/N) | H3: Exclusion reason | I3: Role target (Sponsor/Organizer/Either) | J3: Best email address | K3: Other addresses (BCC) | L3: Enquiry form URL | M3: Channel chosen | N3: LinkedIn profiles logged? (Y/N) | O3: Status | P3: Date added | Q3: Date first contacted | R3: Follow-up Day 4 done (Y/N) | S3: Follow-up Day 11 done (Y/N) | T3: Follow-up Day 25 done (Y/N) | U3: Notes
A4: Runway AI, Inc. | B4: Venture-funded AI tool company | C4: New York, USA | D4: Makes AI video-generation tools used by filmmakers — direct category fit | E4: Y | F4: Y | G4: N | I4: Sponsor | J4: partnerships@runwayml.com | K4: press@runwayml.com | L4: https://runwayml.com/contact | M4: Email | N4: Y | O4: Researching | P4: 2026-09-03 | R4: N | S4: N | T4: N | U4: EXAMPLE ROW — edit or delete, do not count as real data
A5: Radisson Blu | D5: Already contacted directly by Aditya | E5: Unknown | F5: Unknown | G5: N | I5: Sponsor | J5: communication@radissonhotels.com | M5: Email | N5: N | O5: Replied | P5: 2026-09-01 | Q5: 2026-09-01 | R5: N | S5: N | T5: N | U5: Backfilled 3 Sep 2026 — sent directly by Aditya before this tracker existed. Anuj Kumar asked 3 questions before a call; replied 3 Sep 2026 with company/date/value framing, no deck link sent. Awaiting reply.
A6: EPAM Systems | D6: Already contacted directly by Aditya | E6: Unknown | F6: Unknown | G6: N | I6: Sponsor | K6: sameena.mohdali@gmail.com; sameena_ali@epam.com; nandini_bhatnagar@epam.com; nandinib2007@gmail.com; nandinibhatnagar@epam.it | M6: Email | N6: N | O6: Replied | P6: 2026-09-01 | Q6: 2026-09-01 | R6: N | S6: N | T6: N | U6: Backfilled 3 Sep 2026 — sent directly by Aditya before this tracker existed. Nandini Bhatnagar wants to talk after Sept 9; replied 3 Sep 2026 confirming availability. Awaiting her scheduling reply.
A7: Adani Digital Labs | D7: Already contacted directly by Aditya | E7: Unknown | F7: Unknown | G7: N | I7: Sponsor | K7: digitallabs@adani.com; media@adani.com; hrishik.jethi@adani.com; cgarg@adanidigitallabs.com; manishsingh.payal@adani.com; jaladhi.shukla@adani.com; support@adanione.com; cbccyber1@adani.com | M7: Email | N7: N | O7: Sent | P7: 2026-09-02 | Q7: 2026-09-02 | R7: N | S7: N | T7: N | U7: Backfilled 3 Sep 2026 — sent directly by Aditya before this tracker existed. BOUNCE: 4 of 8 BCC addresses bounced (cgarg@adanidigitallabs.com, hrishik.jethi@adani.com, manishsingh.payal@adani.com, digitallabs@adani.com)
A8: Adani AI Labs | D8: Already contacted directly by Aditya | E8: Unknown | F8: Unknown | G8: N | I8: Sponsor | J8: Shalini.singh@adani.com | K8: roy.paul@adani.com; jeet.adani@adani.com; tanushyam.chattopadhyay@adani.com; investor.ael@adani.com | M8: Email | N8: N | O8: Sent | P8: 2026-09-02 | Q8: 2026-09-02 | R8: N | S8: N | T8: N | U8: Backfilled 3 Sep 2026 — sent directly by Aditya before this tracker existed. BOUNCE: 1 of 4 BCC addresses bounced (tanushyam.chattopadhyay@adani.com); also sent separately to Shalini Singh direct
A9: Freshworks | D9: Already contacted directly by Aditya | E9: Unknown | F9: Unknown | G9: N | I9: Sponsor | K9: sales@freshworks.com; pr@freshworks.com; dpo@freshworks.com; ir@freshworks.com | M9: Email | N9: N | O9: Sent | P9: 2026-09-02 | Q9: 2026-09-02 | R9: N | S9: N | T9: N | U9: Backfilled 3 Sep 2026 — sent directly by Aditya before this tracker existed. Automated support-ticket confirmation only — not a personal reply, no action needed yet
A10: Zoho | D10: Already contacted directly by Aditya | E10: Unknown | F10: Unknown | G10: N | I10: Sponsor | K10: sales@zohocorp.com; partner-operations@zohocorp.com; press@zohocorp.com | M10: Email | N10: N | O10: Sent | P10: 2026-09-02 | Q10: 2026-09-02 | R10: N | S10: N | T10: N | U10: Backfilled 3 Sep 2026 — sent directly by Aditya before this tracker existed. Automated partner-ticket confirmation + generic sales-team reply — not personalized, no action needed yet
A11: Myntra | D11: Already contacted directly by Aditya | E11: Unknown | F11: Unknown | G11: N | I11: Sponsor | J11: communications@myntra.com | M11: Email | N11: N | O11: Bounced | P11: 2026-09-02 | Q11: 2026-09-02 | R11: N | S11: N | T11: N | U11: Backfilled 3 Sep 2026 — sent directly by Aditya before this tracker existed. BOUNCE: Address not found (bounced) — only address used, no BCC alternates
A12: Tech Mahindra | D12: Already contacted directly by Aditya | E12: Unknown | F12: Unknown | G12: N | I12: Sponsor | K12: alliances@techmahindra.com; socialmedia@techmahindra.com; mktg@techmahindra.com; media.relations@techmahindra.com | M12: Email | N12: N | O12: Sent | P12: 2026-09-02 | Q12: 2026-09-02 | R12: N | S12: N | T12: N | U12: Backfilled 3 Sep 2026 — sent directly by Aditya before this tracker existed.
A13: BenQ India | D13: Already contacted directly by Aditya | E13: Unknown | F13: Unknown | G13: N | I13: Sponsor | K13: ruchika.singh@benq.com; ankita.karwa@benq.com; rajeev.singh@benq.com (+3 personal-looking gmail addresses also BCC'd) | M13: Email | N13: N | O13: Sent | P13: 2026-09-02 | Q13: 2026-09-02 | R13: N | S13: N | T13: N | U13: Backfilled 3 Sep 2026 — sent directly by Aditya before this tracker existed.
A14: Sennheiser | D14: Already contacted directly by Aditya | E14: Unknown | F14: Unknown | G14: N | I14: Sponsor | K14: sponsoring@sennheiser.com; sarah.talaat@sennheiser.com; felix.teufel@sennheiser.com (+17 more BCC'd, incl. Sonova/Neumann/agency addresses) | M14: Email | N14: N | O14: Sent | P14: 2026-09-02 | Q14: 2026-09-02 | R14: N | S14: N | T14: N | U14: Backfilled 3 Sep 2026 — sent directly by Aditya before this tracker existed.
A15: Runway | B15: Venture-funded AI tool company | C15: San Francisco, US | D15: Gen-4.5 launch + Lionsgate equity partnership for AI-generated franchise content | E15: Y | F15: Y | G15: N | I15: Sponsor | J15: partnerships@runwayml.com | K15: press@runwayml.com | M15: Email | N15: N | O15: Sent | P15: 2026-09-03 | Q15: 2026-09-03 | R15: N | S15: N | T15: N | U15: Sent 3 Sep 2026 — Batch 1 (60), Target Batch 2 research.
A16: Genmo | B16: Venture-funded AI tool company | C16: San Francisco, US | D16: Mochi 1 open text-to-video model, still updated a year on | E16: Y | F16: Y | G16: N | I16: Sponsor | J16: hi@genmo.ai | M16: Email | N16: N | O16: Sent | P16: 2026-09-03 | Q16: 2026-09-03 | R16: N | S16: N | T16: N | U16: Sent 3 Sep 2026 — Batch 1 (60), Target Batch 2 research.
A17: Shengshu Technology (Vidu) | B17: Venture-funded AI tool company | C17: Beijing, China | D17: Alibaba Cloud $290M round backing Vidu world-model ambitions | E17: Y | F17: Y | G17: N | I17: Sponsor | J17: support@vidu.com | M17: Email | N17: N | O17: Sent | P17: 2026-09-03 | Q17: 2026-09-03 | R17: N | S17: N | T17: N | U17: Sent 3 Sep 2026 — Batch 1 (60), Target Batch 2 research.
A18: ElevenLabs | B18: Venture-funded AI tool company | C18: London, UK | D18: New CRO, Canada launch, CLI v1 release | E18: Y | F18: Y | G18: N | I18: Sponsor | J18: press@elevenlabs.io | M18: Email | N18: N | O18: Sent | P18: 2026-09-03 | Q18: 2026-09-03 | R18: N | S18: Y - 2026-09-14 | T18: N | U18: Sent 3 Sep 2026 — Batch 1 (60), Target Batch 2 research. || Day 11 follow-up sent 2026-09-14: new-fact angle (Cannes 2027 flagship now fixed 6-7 Apr 2027 at Palais des Festivals, Road to Cannes selection model, 2026 jury names). Sponsor variant for sponsor track, organizer variant naming edition ownership and retained sponsorship revenue for organizer track.
A19: Murf AI | B19: Venture-funded AI tool company | C19: Bangalore, India | D19: 300+ Forbes 2000 clients, 6M+ users, 20+ languages | E19: Y | F19: Y | G19: N | I19: Sponsor | J19: alliances@murf.ai | K19: enterprise@murf.ai; support@murf.ai | M19: Email | N19: N | O19: Sent | P19: 2026-09-03 | Q19: 2026-09-03 | R19: N | S19: N | T19: N | U19: Sent 3 Sep 2026 — Batch 1 (60), Target Batch 2 research.
A20: NeuralGarage | B20: Venture-funded AI tool company | C20: Mumbai, India | D20: VisualDub — SXSW 2025 winner, lip-sync tech used in Rajinikanth's Coolie | E20: Y | F20: Y | G20: N | I20: Sponsor | J20: info@neuralgarage.com | M20: Email | N20: N | O20: Sent | P20: 2026-09-03 | Q20: 2026-09-03 | R20: N | S20: Y - 2026-09-14 | T20: N | U20: Sent 3 Sep 2026 — Batch 1 (60), Target Batch 2 research. || Day 11 follow-up sent 2026-09-14: new-fact angle (Cannes 2027 flagship now fixed 6-7 Apr 2027 at Palais des Festivals, Road to Cannes selection model, 2026 jury names). Sponsor variant for sponsor track, organizer variant naming edition ownership and retained sponsorship revenue for organizer track.
A21: Synthesia | B21: Venture-funded AI tool company | C21: London, UK | D21: Signed EU Article 50 AI Act code of practice; interactive AI press-officer avatar | E21: Y | F21: Y | G21: N | I21: Sponsor | J21: press@synthesia.io | M21: Email | N21: N | O21: Sent | P21: 2026-09-03 | Q21: 2026-09-03 | R21: N | S21: Y - 2026-09-14 | T21: N | U21: Sent 3 Sep 2026 — Batch 1 (60), Target Batch 2 research. || Day 11 follow-up sent 2026-09-14: new-fact angle (Cannes 2027 flagship now fixed 6-7 Apr 2027 at Palais des Festivals, Road to Cannes selection model, 2026 jury names). Sponsor variant for sponsor track, organizer variant naming edition ownership and retained sponsorship revenue for organizer track.
A22: OpusClip (Opus.pro) | B22: Venture-funded AI tool company | C22: San Francisco, US | D22: SoftBank Vision Fund 2 $20M investment in AI video editing platform | E22: Y | F22: Y | G22: N | I22: Sponsor | J22: contact@opus.pro | M22: Email | N22: N | O22: Sent | P22: 2026-09-03 | Q22: 2026-09-03 | R22: N | S22: Y - 2026-09-14 | T22: N | U22: Sent 3 Sep 2026 — Batch 1 (60), Target Batch 2 research. || Day 11 follow-up sent 2026-09-14: new-fact angle (Cannes 2027 flagship now fixed 6-7 Apr 2027 at Palais des Festivals, Road to Cannes selection model, 2026 jury names). Sponsor variant for sponsor track, organizer variant naming edition ownership and retained sponsorship revenue for organizer track.
A23: Captions (Mirage) | B23: Venture-funded AI tool company | C23: New York, US | D23: $75M raise from General Catalyst Customer Value Fund for Asia expansion | E23: Y | F23: Y | G23: N | I23: Sponsor | J23: press@mirage.app | K23: info@mirage.app | M23: Email | N23: N | O23: Sent | P23: 2026-09-03 | Q23: 2026-09-03 | R23: N | S23: Y - 2026-09-14 | T23: N | U23: Sent 3 Sep 2026 — Batch 1 (60), Target Batch 2 research. || Day 11 follow-up sent 2026-09-14: new-fact angle (Cannes 2027 flagship now fixed 6-7 Apr 2027 at Palais des Festivals, Road to Cannes selection model, 2026 jury names). Sponsor variant for sponsor track, organizer variant naming edition ownership and retained sponsorship revenue for organizer track.
A24: Topaz Labs | B24: Venture-funded AI tool company | C24: Dallas, US | D24: Largest single AI model release in company history; NeuroStream cuts VRAM 95% | E24: Y | F24: Y | G24: N | I24: Sponsor | J24: Press@topazlabs.com | M24: Email | N24: N | O24: Sent | P24: 2026-09-03 | Q24: 2026-09-03 | R24: N | S24: Y - 2026-09-14 | T24: N | U24: Sent 3 Sep 2026 — Batch 1 (60), Target Batch 2 research. || Day 11 follow-up sent 2026-09-14: new-fact angle (Cannes 2027 flagship now fixed 6-7 Apr 2027 at Palais des Festivals, Road to Cannes selection model, 2026 jury names). Sponsor variant for sponsor track, organizer variant naming edition ownership and retained sponsorship revenue for organizer track.
A25: Black Forest Labs | B25: Venture-funded AI tool company | C25: Freiburg, Germany | D25: Martin Scorsese joined as advisor to shape FLUX use in filmmaking pre-production | E25: Y | F25: Y | G25: N | I25: Sponsor | J25: info@blackforestlabs.ai | M25: Email | N25: N | O25: Sent | P25: 2026-09-03 | Q25: 2026-09-03 | R25: N | S25: Y - 2026-09-14 | T25: N | U25: Sent 3 Sep 2026 — Batch 1 (60), Target Batch 2 research. || Day 11 follow-up sent 2026-09-14: new-fact angle (Cannes 2027 flagship now fixed 6-7 Apr 2027 at Palais des Festivals, Road to Cannes selection model, 2026 jury names). Sponsor variant for sponsor track, organizer variant naming edition ownership and retained sponsorship revenue for organizer track.
A26: Stability AI | B26: Venture-funded AI tool company | C26: London, UK | D26: $76M Series B backed by EA/Sony Music/UMG/WMG/AMD Ventures + new WPP partnership | E26: Y | F26: Y | G26: N | I26: Sponsor | J26: partners@stability.ai | K26: press@stability.ai | M26: Email | N26: N | O26: Sent | P26: 2026-09-03 | Q26: 2026-09-03 | R26: N | S26: N | T26: N | U26: Sent 3 Sep 2026 — Batch 1 (60), Target Batch 2 research.
A27: NVIDIA | B27: India-operating hardware & consumer brand | C27: Santa Clara, US (India: Bengaluru/Gurugram) | D27: Cosmos 3 Edge world model + Synthetic Video Detector NIM announced at SIGGRAPH 2026 | E27: Y | F27: Y | G27: N | I27: Sponsor | J27: india-pr@nvidia.com | M27: Email | N27: N | O27: Sent | P27: 2026-09-03 | Q27: 2026-09-03 | R27: N | S27: N | T27: N | U27: Sent 3 Sep 2026 — Batch 1 (60), Target Batch 2 research.
A28: Qualcomm | B28: India-operating hardware & consumer brand | C28: San Diego, US (India offices) | D28: "Snapdragon For India 2026" launch of Snapdragon 6 Gen 5 / 4 Gen 5 | E28: Y | F28: Y | G28: N | I28: Sponsor | J28: corpcomm@qualcomm.com | M28: Email | N28: N | O28: Sent | P28: 2026-09-03 | Q28: 2026-09-03 | R28: N | S28: Y - 2026-09-14 | T28: N | U28: Sent 3 Sep 2026 — Batch 1 (60), Target Batch 2 research. || Day 11 follow-up sent 2026-09-14: new-fact angle (Cannes 2027 flagship now fixed 6-7 Apr 2027 at Palais des Festivals, Road to Cannes selection model, 2026 jury names). Sponsor variant for sponsor track, organizer variant naming edition ownership and retained sponsorship revenue for organizer track.
A29: Sony India | B29: India-operating hardware & consumer brand | C29: Tokyo, Japan (India subsidiary) | D29: ILCE-7V launch with AI-powered Auto Framing and 7K-oversampled 4K/60p video | E29: Y | F29: Y | G29: N | I29: Sponsor | J29: press.india@sony.com | M29: Email | N29: N | O29: Sent | P29: 2026-09-03 | Q29: 2026-09-03 | R29: N | S29: Y - 2026-09-14 | T29: N | U29: Sent 3 Sep 2026 — Batch 1 (60), Target Batch 2 research. || Day 11 follow-up sent 2026-09-14: new-fact angle (Cannes 2027 flagship now fixed 6-7 Apr 2027 at Palais des Festivals, Road to Cannes selection model, 2026 jury names). Sponsor variant for sponsor track, organizer variant naming edition ownership and retained sponsorship revenue for organizer track.
A30: Harman International (JBL) | B30: India-operating hardware & consumer brand | C30: Stamford, US (India office; Samsung-owned) | D30: JBL 80th anniversary; Summit Everest / Summit K2 loudspeaker launch | E30: Y | F30: Y | G30: N | I30: Sponsor | J30: indiaprosales@harman.com | K30: indiaprocare@harman.com; david.glaubke@harman.com | M30: Email | N30: N | O30: Sent | P30: 2026-09-03 | Q30: 2026-09-03 | R30: N | S30: Y - 2026-09-14 | T30: N | U30: Sent 3 Sep 2026 — Batch 1 (60), Target Batch 2 research. || Day 11 follow-up sent 2026-09-14: new-fact angle (Cannes 2027 flagship now fixed 6-7 Apr 2027 at Palais des Festivals, Road to Cannes selection model, 2026 jury names). Sponsor variant for sponsor track, organizer variant naming edition ownership and retained sponsorship revenue for organizer track.
A31: Zebronics | B31: India-operating hardware & consumer brand | C31: Chennai, India | D31: Zeb-PixaPlay 72 Plus — 120-inch, 4000-lumen smart projector | E31: Y | F31: Y | G31: N | I31: Sponsor | J31: enquiry@zebronics.com | M31: Email | N31: N | O31: Sent | P31: 2026-09-03 | Q31: 2026-09-03 | R31: N | S31: Y - 2026-09-14 | T31: N | U31: Sent 3 Sep 2026 — Batch 1 (60), Target Batch 2 research. || Day 11 follow-up sent 2026-09-14: new-fact angle (Cannes 2027 flagship now fixed 6-7 Apr 2027 at Palais des Festivals, Road to Cannes selection model, 2026 jury names). Sponsor variant for sponsor track, organizer variant naming edition ownership and retained sponsorship revenue for organizer track.
A32: Dell Technologies India | B32: India-operating hardware & consumer brand | C32: Round Rock, US (India: Bengaluru/Hyderabad) | D32: Alienware 16X Aurora "Back to School" campaign with Jemimah Rodrigues and Yashraj Mukhate | E32: Y | F32: Y | G32: N | I32: Sponsor | J32: media.relations@dell.com | M32: Email | N32: N | O32: Sent | P32: 2026-09-03 | Q32: 2026-09-03 | R32: N | S32: Y - 2026-09-14 | T32: N | U32: Sent 3 Sep 2026 — Batch 1 (60), Target Batch 2 research. || Day 11 follow-up sent 2026-09-14: new-fact angle (Cannes 2027 flagship now fixed 6-7 Apr 2027 at Palais des Festivals, Road to Cannes selection model, 2026 jury names). Sponsor variant for sponsor track, organizer variant naming edition ownership and retained sponsorship revenue for organizer track.
A33: ASUS India | B33: India-operating hardware & consumer brand | C33: Taipei, Taiwan (India subsidiary) | D33: ROG Flow Z13 Kojima Productions Edition collab (Death Stranding universe) | E33: Y | F33: Y | G33: N | I33: Sponsor | J33: Media@asus.com | M33: Email | N33: N | O33: Sent | P33: 2026-09-03 | Q33: 2026-09-03 | R33: N | S33: Y - 2026-09-14 | T33: N | U33: Sent 3 Sep 2026 — Batch 1 (60), Target Batch 2 research. || Day 11 follow-up sent 2026-09-14: new-fact angle (Cannes 2027 flagship now fixed 6-7 Apr 2027 at Palais des Festivals, Road to Cannes selection model, 2026 jury names). Sponsor variant for sponsor track, organizer variant naming edition ownership and retained sponsorship revenue for organizer track.
A34: Lenovo India | B34: India-operating hardware & consumer brand | C34: Beijing/Morrisville (India subsidiary) | D34: Creator/influencer partnerships program (Grace Gabel, Sabrina Mohan) | E34: Y | F34: Y | G34: N | I34: Sponsor | J34: grace.gabel@lenovo.com | K34: sabrina.mohan@lenovo.com; stephanie.yu@lenovo.com | M34: Email | N34: N | O34: Sent | P34: 2026-09-03 | Q34: 2026-09-03 | R34: N | S34: Y - 2026-09-14 | T34: N | U34: Sent 3 Sep 2026 — Batch 1 (60), Target Batch 2 research. || Day 11 follow-up sent 2026-09-14: new-fact angle (Cannes 2027 flagship now fixed 6-7 Apr 2027 at Palais des Festivals, Road to Cannes selection model, 2026 jury names). Sponsor variant for sponsor track, organizer variant naming edition ownership and retained sponsorship revenue for organizer track.
A35: Western Digital (SanDisk Professional) | B35: India-operating hardware & consumer brand | C35: San Jose, US (India operations) | D35: SanDisk Creator Series launch in India for 4K-6K creators, bundled Adobe CC trial | E35: Y | F35: Y | G35: N | I35: Sponsor | J35: WD.Mediainquiries@wdc.com | M35: Email | N35: N | O35: Sent | P35: 2026-09-03 | Q35: 2026-09-03 | R35: N | S35: Y - 2026-09-14 | T35: N | U35: Sent 3 Sep 2026 — Batch 1 (60), Target Batch 2 research. || Day 11 follow-up sent 2026-09-14: new-fact angle (Cannes 2027 flagship now fixed 6-7 Apr 2027 at Palais des Festivals, Road to Cannes selection model, 2026 jury names). Sponsor variant for sponsor track, organizer variant naming edition ownership and retained sponsorship revenue for organizer track.
A36: Samsung India | B36: India-operating hardware & consumer brand | C36: Suwon, South Korea (India subsidiary) | D36: Brut India partnership covering 2026 Cannes red carpet via Galaxy S26 Ultra creator storytelling | E36: Y | F36: Y | G36: N | I36: Sponsor | J36: corpcommindia@samsung.com | M36: Email | N36: N | O36: Sent | P36: 2026-09-03 | Q36: 2026-09-03 | R36: N | S36: Y - 2026-09-14 | T36: N | U36: Sent 3 Sep 2026 — Batch 1 (60), Target Batch 2 research. || Day 11 follow-up sent 2026-09-14: new-fact angle (Cannes 2027 flagship now fixed 6-7 Apr 2027 at Palais des Festivals, Road to Cannes selection model, 2026 jury names). Sponsor variant for sponsor track, organizer variant naming edition ownership and retained sponsorship revenue for organizer track.
A37: Krutrim AI (Ola Krutrim) | B37: Indian AI infrastructure | C37: Bengaluru, India | D37: First annual net profit; revenue nearly tripled; 25+ enterprise clients | E37: Y | F37: Y | G37: N | I37: Sponsor | J37: sales@olakrutrim.com | K37: cloudsupport@olakrutrim.com | M37: Email | N37: N | O37: Sent | P37: 2026-09-03 | Q37: 2026-09-03 | R37: N | S37: Y - 2026-09-14 | T37: N | U37: Sent 3 Sep 2026 — Batch 1 (60), Target Batch 2 research. || Day 11 follow-up sent 2026-09-14: new-fact angle (Cannes 2027 flagship now fixed 6-7 Apr 2027 at Palais des Festivals, Road to Cannes selection model, 2026 jury names). Sponsor variant for sponsor track, organizer variant naming edition ownership and retained sponsorship revenue for organizer track.
A38: Yotta Data Services | B38: Indian AI infrastructure | C38: Navi Mumbai, India | D38: Frost & Sullivan 2026 Indian Company of the Year for Sovereign AI Infrastructure | E38: Y | F38: Y | G38: N | I38: Sponsor | J38: marketing@yotta.com | K38: info@yotta.com | M38: Email | N38: N | O38: Sent | P38: 2026-09-03 | Q38: 2026-09-03 | R38: N | S38: N | T38: N | U38: Sent 3 Sep 2026 — Batch 1 (60), Target Batch 2 research.
A39: E2E Networks | B39: Indian AI infrastructure | C39: New Delhi, India | D39: ₹1,000 crore Blackwell GPU order + new NVIDIA B200 cluster on TIR platform | E39: Y | F39: Y | G39: N | I39: Sponsor | J39: sales@e2enetworks.com | M39: Email | N39: N | O39: Sent | P39: 2026-09-03 | Q39: 2026-09-03 | R39: N | S39: Y - 2026-09-14 | T39: N | U39: Sent 3 Sep 2026 — Batch 1 (60), Target Batch 2 research. || Day 11 follow-up sent 2026-09-14: new-fact angle (Cannes 2027 flagship now fixed 6-7 Apr 2027 at Palais des Festivals, Road to Cannes selection model, 2026 jury names). Sponsor variant for sponsor track, organizer variant naming edition ownership and retained sponsorship revenue for organizer track.
A40: Netweb Technologies | B40: Indian AI infrastructure | C40: Faridabad, India | D40: Launched Tyrone ParallelStor Velox unified data platform for AI/HPC | E40: Y | F40: Y | G40: N | I40: Sponsor | J40: mktkol@netwebindia.com | K40: info@netwebindia.com; hydsales@netwebindia.com | M40: Email | N40: N | O40: Sent | P40: 2026-09-03 | Q40: 2026-09-03 | R40: N | S40: Y - 2026-09-14 | T40: N | U40: Sent 3 Sep 2026 — Batch 1 (60), Target Batch 2 research. || Day 11 follow-up sent 2026-09-14: new-fact angle (Cannes 2027 flagship now fixed 6-7 Apr 2027 at Palais des Festivals, Road to Cannes selection model, 2026 jury names). Sponsor variant for sponsor track, organizer variant naming edition ownership and retained sponsorship revenue for organizer track.
A41: CtrlS Datacenters | B41: Indian AI infrastructure | C41: Hyderabad, India | D41: ₹7,000 crore CPP Investments commitment to scale India datacenter infrastructure | E41: Y | F41: Y | G41: N | I41: Sponsor | J41: marketing@ctrls.in | M41: Email | N41: N | O41: Sent | P41: 2026-09-03 | Q41: 2026-09-03 | R41: N | S41: Y - 2026-09-14 | T41: N | U41: Sent 3 Sep 2026 — Batch 1 (60), Target Batch 2 research. || Day 11 follow-up sent 2026-09-14: new-fact angle (Cannes 2027 flagship now fixed 6-7 Apr 2027 at Palais des Festivals, Road to Cannes selection model, 2026 jury names). Sponsor variant for sponsor track, organizer variant naming edition ownership and retained sponsorship revenue for organizer track.
A42: Nikon India / RED Digital Cinema | B42: India-operating hardware & consumer brand | C42: Tokyo, Japan (India subsidiary; RED acquired 2024) | D42: Nikon ZR — first Nikon cinema camera, born from RED Digital Cinema acquisition | E42: Y | F42: Y | G42: N | I42: Sponsor | J42: NindSupport@nikon.com | M42: Email | N42: N | O42: Sent | P42: 2026-09-03 | Q42: 2026-09-03 | R42: N | S42: Y - 2026-09-14 | T42: N | U42: Sent 3 Sep 2026 — Batch 1 (60), Target Batch 2 research. || Day 11 follow-up sent 2026-09-14: new-fact angle (Cannes 2027 flagship now fixed 6-7 Apr 2027 at Palais des Festivals, Road to Cannes selection model, 2026 jury names). Sponsor variant for sponsor track, organizer variant naming edition ownership and retained sponsorship revenue for organizer track.
A43: Panasonic (Lumix) India | B43: India-operating hardware & consumer brand | C43: Osaka, Japan (India subsidiary) | D43: LUMIX L² Technology autofocus collaboration with DJI for cinema/mirrorless cameras | E43: Y | F43: Y | G43: N | I43: Sponsor | J43: helpline@in.Panasonic.com | M43: Email | N43: N | O43: Sent | P43: 2026-09-03 | Q43: 2026-09-03 | R43: N | S43: Y - 2026-09-14 | T43: N | U43: Sent 3 Sep 2026 — Batch 1 (60), Target Batch 2 research. || Day 11 follow-up sent 2026-09-14: new-fact angle (Cannes 2027 flagship now fixed 6-7 Apr 2027 at Palais des Festivals, Road to Cannes selection model, 2026 jury names). Sponsor variant for sponsor track, organizer variant naming edition ownership and retained sponsorship revenue for organizer track.
A44: Fractal Analytics | B44: Media, VFX and exhibition | C44: Mumbai, India | D44: IPO Feb 2026, India's first AI-focused public offering | E44: Y | F44: Y | G44: N | I44: Sponsor | L44: https://fractal.ai/contact-us/ | M44: Form | N44: N | O44: Form submitted | P44: 2026-09-03 | Q44: 2026-09-03 | R44: N | S44: N | T44: N | U44: Business Opportunity form submitted 3 Sep 2026, reply-to adiup394@gmail.com. Note: message field had a stray phone-number prefix due to a form-fill glitch, rest of message intact.
A45: AMD | B45: India-operating hardware & consumer brand | C45: Santa Clara, US (India: Bengaluru) | D45: AMD x S8UL/Revenant Esports creator-ecosystem partnership | E45: Y | F45: Y | G45: N | I45: Sponsor | L45: https://www.amd.com/en/forms/solutions-inquiry/media-and-entertainment.html | M45: Form | N45: N | O45: Draft ready - needs manual CAPTCHA | P45: 2026-09-03 | R45: N | S45: N | T45: N | U45: Form filled but blocked by reCAPTCHA - needs Aditya to submit manually. LinkedIn contacts (Vinay Sinha, Mukesh Bajpai) logged separately.
A46: DNEG India | B46: Media, VFX and exhibition | C46: India | D46: 2025 Oscar for Visual Effects, Dune: Part Two | E46: Y | F46: Y | G46: N | I46: Organizer | J46: info@dneg.com | K46: pr@dneg.com | M46: Email | N46: N | O46: Sent | P46: 2026-09-03 | Q46: 2026-09-03 | R46: N | S46: Y - 2026-09-14 | T46: N | U46: Sent 3 Sep 2026 — Organizer track batch (media/VFX/exhibition pool). || Day 11 follow-up sent 2026-09-14: new-fact angle (Cannes 2027 flagship now fixed 6-7 Apr 2027 at Palais des Festivals, Road to Cannes selection model, 2026 jury names). Sponsor variant for sponsor track, organizer variant naming edition ownership and retained sponsorship revenue for organizer track.
A47: Red Chillies Entertainment (Redchillies.vfx) | B47: Media, VFX and exhibition | C47: India | D47: Best VFX, FICCI-BAF Awards 2024, for Dunki | E47: Y | F47: Y | G47: N | I47: Organizer | J47: business@redchillies.com | K47: press@redchillies.com | M47: Email | N47: N | O47: Sent | P47: 2026-09-03 | Q47: 2026-09-03 | R47: N | S47: Y - 2026-09-14 | T47: N | U47: Sent 3 Sep 2026 — Organizer track batch (media/VFX/exhibition pool). || Day 11 follow-up sent 2026-09-14: new-fact angle (Cannes 2027 flagship now fixed 6-7 Apr 2027 at Palais des Festivals, Road to Cannes selection model, 2026 jury names). Sponsor variant for sponsor track, organizer variant naming edition ownership and retained sponsorship revenue for organizer track.
A48: Applause Entertainment | B48: Media, VFX and exhibition | C48: India | D48: Story TV microdrama partnership, Mar 2026 | E48: Y | F48: Y | G48: N | I48: Organizer | J48: prasoon.garg@applause.adityabirla.com | K48: marketing@applause.adityabirla.com | M48: Email | N48: N | O48: Sent | P48: 2026-09-03 | Q48: 2026-09-03 | R48: N | S48: Y - 2026-09-14 | T48: N | U48: Sent 3 Sep 2026 — Organizer track batch (media/VFX/exhibition pool). || Day 11 follow-up sent 2026-09-14: new-fact angle (Cannes 2027 flagship now fixed 6-7 Apr 2027 at Palais des Festivals, Road to Cannes selection model, 2026 jury names). Sponsor variant for sponsor track, organizer variant naming edition ownership and retained sponsorship revenue for organizer track.
A49: Mythri Movie Makers | B49: Media, VFX and exhibition | C49: India | D49: 45+ film slate over 5 years announced Aug 2025 | E49: Y | F49: Y | G49: N | I49: Organizer | J49: info@mythrimoviemakers.com | M49: Email | N49: N | O49: Sent | P49: 2026-09-03 | Q49: 2026-09-03 | R49: N | S49: Y - 2026-09-14 | T49: N | U49: Sent 3 Sep 2026 — Organizer track batch (media/VFX/exhibition pool). || Day 11 follow-up sent 2026-09-14: new-fact angle (Cannes 2027 flagship now fixed 6-7 Apr 2027 at Palais des Festivals, Road to Cannes selection model, 2026 jury names). Sponsor variant for sponsor track, organizer variant naming edition ownership and retained sponsorship revenue for organizer track.
A50: Wizcraft International Entertainment | B50: Media, VFX and exhibition | C50: India | D50: IIFA Awards organizer; launched Wizfilm production venture Feb 2024 | E50: Y | F50: Y | G50: N | I50: Organizer | J50: info@wizcraft.co | M50: Email | N50: N | O50: Sent | P50: 2026-09-03 | Q50: 2026-09-03 | R50: N | S50: Y - 2026-09-14 | T50: N | U50: Sent 3 Sep 2026 — Organizer track batch (media/VFX/exhibition pool). || Day 11 follow-up sent 2026-09-14: new-fact angle (Cannes 2027 flagship now fixed 6-7 Apr 2027 at Palais des Festivals, Road to Cannes selection model, 2026 jury names). Sponsor variant for sponsor track, organizer variant naming edition ownership and retained sponsorship revenue for organizer track.
A51: Ramoji Film City | B51: Media, VFX and exhibition | C51: India | D51: Hosted Ramoji Excellence Awards 2025, Nov 2025 | E51: Y | F51: Y | G51: N | I51: Organizer | J51: info@ramojifilmcity.com | K51: avrao@ramojifilmcity.com | M51: Email | N51: N | O51: Sent | P51: 2026-09-03 | Q51: 2026-09-03 | R51: N | S51: Y - 2026-09-14 | T51: N | U51: Sent 3 Sep 2026 — Organizer track batch (media/VFX/exhibition pool). || Day 11 follow-up sent 2026-09-14: new-fact angle (Cannes 2027 flagship now fixed 6-7 Apr 2027 at Palais des Festivals, Road to Cannes selection model, 2026 jury names). Sponsor variant for sponsor track, organizer variant naming edition ownership and retained sponsorship revenue for organizer track.
A52: Lyca Productions | B52: Media, VFX and exhibition | C52: India | D52: WAVES 2025 JV with Mahaveer Jain Films, 9 films over 3 years | E52: Y | F52: Y | G52: N | I52: Organizer | J52: info@lycaproductions.in | M52: Email | N52: N | O52: Sent | P52: 2026-09-03 | Q52: 2026-09-03 | R52: N | S52: Y - 2026-09-14 | T52: N | U52: Sent 3 Sep 2026 — Organizer track batch (media/VFX/exhibition pool). || Day 11 follow-up sent 2026-09-14: new-fact angle (Cannes 2027 flagship now fixed 6-7 Apr 2027 at Palais des Festivals, Road to Cannes selection model, 2026 jury names). Sponsor variant for sponsor track, organizer variant naming edition ownership and retained sponsorship revenue for organizer track.
A53: Prime Focus Technologies | B53: Media, VFX and exhibition | C53: India | D53: STAGE OTT partnership, May 2025 (CLEAR AI media platform) | E53: Y | F53: Y | G53: N | I53: Organizer | J53: tshobhana@primefocustechnologies.com | M53: Email | N53: N | O53: Sent | P53: 2026-09-03 | Q53: 2026-09-03 | R53: N | S53: Y - 2026-09-14 | T53: N | U53: Sent 3 Sep 2026 — Organizer track batch (media/VFX/exhibition pool). || Day 11 follow-up sent 2026-09-14: new-fact angle (Cannes 2027 flagship now fixed 6-7 Apr 2027 at Palais des Festivals, Road to Cannes selection model, 2026 jury names). Sponsor variant for sponsor track, organizer variant naming edition ownership and retained sponsorship revenue for organizer track.
A54: NY VFXWAALA | B54: Media, VFX and exhibition | C54: India | D54: Goodbye Kansas Studios stake acquisition, Mar 2024 | E54: Y | F54: Y | G54: N | I54: Organizer | J54: info@nyvfxwaala.com | M54: Email | N54: N | O54: Sent | P54: 2026-09-03 | Q54: 2026-09-03 | R54: N | S54: Y - 2026-09-14 | T54: N | U54: Sent 3 Sep 2026 — Organizer track batch (media/VFX/exhibition pool). || Day 11 follow-up sent 2026-09-14: new-fact angle (Cannes 2027 flagship now fixed 6-7 Apr 2027 at Palais des Festivals, Road to Cannes selection model, 2026 jury names). Sponsor variant for sponsor track, organizer variant naming edition ownership and retained sponsorship revenue for organizer track.
A55: Qube Cinema Technologies | B55: Media, VFX and exhibition | C55: India | D55: Arts Alliance Media acquisition, Feb 2026 | E55: Y | F55: Y | G55: N | I55: Organizer | J55: sales@qubecinema.com | M55: Email | N55: N | O55: Sent | P55: 2026-09-03 | Q55: 2026-09-03 | R55: N | S55: Y - 2026-09-14 | T55: N | U55: Sent 3 Sep 2026 — Organizer track batch (media/VFX/exhibition pool). || Day 11 follow-up sent 2026-09-14: new-fact angle (Cannes 2027 flagship now fixed 6-7 Apr 2027 at Palais des Festivals, Road to Cannes selection model, 2026 jury names). Sponsor variant for sponsor track, organizer variant naming edition ownership and retained sponsorship revenue for organizer track.
A56: Yash Raj Films | B56: Media, VFX and exhibition | C56: India | D56: Netflix classics deal Nov 2025; Hemant Kundnani elevated to Head of Marketing Sep 2026 | E56: Y | F56: Y | G56: N | I56: Organizer | J56: helpdesk@yashrajfilms.com | L56: yashrajfilms.com/about-us/contactyrf/business-queries | M56: Email | N56: N | O56: Contacted | P56: 2026-09-03 | Q56: 2026-09-13 | R56: N/A | S56: N/A | T56: N/A | U56: Real email supplied by Aditya 13 Sep, used instead of the CAPTCHA-blocked contact form. Organizer-track email sent.
A57: Avid Technology | B57: Global enterprise | C57: Global | D57: Google Cloud agentic-AI editing partnership, Apr 2026 | E57: Y | F57: Y | G57: N | I57: Sponsor | J57: partners@avid.com | M57: Email | N57: N | O57: Sent | P57: 2026-09-03 | Q57: 2026-09-03 | R57: N | S57: Y - 2026-09-14 | T57: N | U57: Sent 3 Sep 2026. || Day 11 follow-up sent 2026-09-14: new-fact angle (Cannes 2027 flagship now fixed 6-7 Apr 2027 at Palais des Festivals, Road to Cannes selection model, 2026 jury names). Sponsor variant for sponsor track, organizer variant naming edition ownership and retained sponsorship revenue for organizer track.
A58: Foundry | B58: Global enterprise | C58: Global | D58: Griptape Enterprise launch + Chief AI Officer hire, Jul 2026 | E58: Y | F58: Y | G58: N | I58: Sponsor | J58: info@foundry.com | M58: Email | N58: N | O58: Sent | P58: 2026-09-03 | Q58: 2026-09-03 | R58: N | S58: Y - 2026-09-14 | T58: N | U58: Sent 3 Sep 2026. || Day 11 follow-up sent 2026-09-14: new-fact angle (Cannes 2027 flagship now fixed 6-7 Apr 2027 at Palais des Festivals, Road to Cannes selection model, 2026 jury names). Sponsor variant for sponsor track, organizer variant naming edition ownership and retained sponsorship revenue for organizer track.
A59: Insta360 | B59: Global enterprise | C59: Global | D59: X6 camera on-device AI editing launch, Aug 2025 | E59: Y | F59: Y | G59: N | I59: Sponsor | J59: enterprise@insta360.com | M59: Email | N59: N | O59: Sent | P59: 2026-09-03 | Q59: 2026-09-03 | R59: N | S59: Y - 2026-09-14 | T59: N | U59: Sent 3 Sep 2026. || Day 11 follow-up sent 2026-09-14: new-fact angle (Cannes 2027 flagship now fixed 6-7 Apr 2027 at Palais des Festivals, Road to Cannes selection model, 2026 jury names). Sponsor variant for sponsor track, organizer variant naming edition ownership and retained sponsorship revenue for organizer track.
A60: Envato | B60: Global creative/stock content platform | C60: Melbourne, Australia | D60: Stock content + AI creative-tools platform (Firefly-style AI features) used by filmmakers/editors — direct category fit for sponsorship/brand association | E60: Y | F60: Y | G60: N | I60: Sponsor | J60: business@envato.com | M60: Email | N60: N | O60: Sent | P60: 2026-09-03 | Q60: 2026-09-03 | R60: N | S60: Y - 2026-09-14 | T60: N | U60: Sent to business@envato.com (general business inquiries — no named partnerships contact found). || Day 11 follow-up sent 2026-09-14: new-fact angle (Cannes 2027 flagship now fixed 6-7 Apr 2027 at Palais des Festivals, Road to Cannes selection model, 2026 jury names). Sponsor variant for sponsor track, organizer variant naming edition ownership and retained sponsorship revenue for organizer track.
A61: Moonvalley AI | B61: Venture-funded AI video-generation company | C61: Los Angeles / Toronto | D61: Builds commercially-safe, licensed-data generative video model (Marey); backed by CAA and Comcast Ventures (~$84M round, Jul 2025) — strong category + values fit | E61: Y | F61: Y | G61: N | I61: Sponsor | L61: https://moonvalley.com/partner-with-us | M61: Form | N61: N | O61: Form submitted | P61: 2026-09-03 | Q61: 2026-09-03 | R61: N | S61: N | T61: N | U61: Genuine "Partner with us" form (studios/directors/filmmakers/agencies/advertisers/brands with taste) — filled and submitted successfully.
A62: GoPro | B62: Global consumer hardware / action camera | C62: San Mateo, USA | D62: Official Action Camera Partner of MotoGP and MXGP FIM Motocross World Championship — proven event-sponsorship spender, direct category fit for capturing filmmaking/POV content | E62: Y | F62: Y | G62: N | I62: Sponsor | J62: Sponsor@gopro.com | M62: Email | N62: N | O62: Bounced | P62: 2026-09-03 | Q62: 2026-09-03 | R62: N | S62: N | T62: N | U62: Address is GoPro's confirmed sponsorship inbox but skews toward individual athlete/creator requests — flagged as a lower-confidence fit despite being a genuine channel. UPDATE 3 Sep: bounced — address defunct despite being GoPro's own confirmed sponsorship inbox.
A63: Christie Digital | B63: Cinema projection technology | C63: Cypress, USA / Kitchener, Canada | D63: Major cinema projector manufacturer (Disney digital cinema supply deal, widespread festival/theatrical exhibition use) — directly relevant to a film festival's exhibition side | E63: Y | F63: Y | G63: N | I63: Sponsor | J63: pr@christiedigital.com | M63: Email | N63: N | O63: Sent | P63: 2026-09-03 | Q63: 2026-09-03 | R63: N | S63: Y - 2026-09-14 | T63: N | U63: Own site explicitly types this address for "Public Relations or sponsorship" — qualifies as a real sponsorship channel, not just press. || Day 11 follow-up sent 2026-09-14: new-fact angle (Cannes 2027 flagship now fixed 6-7 Apr 2027 at Palais des Festivals, Road to Cannes selection model, 2026 jury names). Sponsor variant for sponsor track, organizer variant naming edition ownership and retained sponsorship revenue for organizer track.
A64: D-ID | B64: Venture-funded AI / Indian AI / Media conglomerate | C64: Israel | D64: Visual AI Agents / avatar tech, direct category fit | E64: Y | F64: Y | G64: N | I64: Sponsor | J64: sarah.schloss@headline.media | M64: Email | O64: Sent | P64: 2026-09-04 | Q64: 2026-09-04
A65: Krea AI | B65: Venture-funded AI / Indian AI / Media conglomerate | C65: USA | D65: GenAI creative suite, $83M Series B, $500M valuation | E65: Y | F65: Y | G65: N | I65: Sponsor | J65: press@krea.ai | M65: Email | O65: Bounced | P65: 2026-09-04 | Q65: 2026-09-04
A66: Character.AI | B66: Venture-funded AI / Indian AI / Media conglomerate | C66: USA | D66: AI-native interactive storytelling ((c.ai) series) | E66: Y | F66: Y | G66: N | I66: Sponsor | J66: press@character.ai | M66: Email | O66: Sent | P66: 2026-09-04 | Q66: 2026-09-04
A67: CoRover | B67: Venture-funded AI / Indian AI / Media conglomerate | C67: India | D67: Indian AI success story, sovereign AI lab for Indian Army | E67: Y | F67: Y | G67: N | I67: Sponsor | J67: chat@CoRover.ai | M67: Email | O67: Sent | P67: 2026-09-04 | Q67: 2026-09-04
A68: Haptik (Jio Haptik) | B68: Venture-funded AI / Indian AI / Media conglomerate | C68: India | D68: Conversational AI, Reliance/Jio ecosystem reach | E68: Y | F68: Y | G68: N | I68: Sponsor | J68: enterprise@haptik.ai | M68: Email | O68: Sent | P68: 2026-09-04 | Q68: 2026-09-04
A69: FICCI (Media & Entertainment / FRAMES) | B69: Venture-funded AI / Indian AI / Media conglomerate | C69: India | D69: India's flagship M&E industry body, FICCI FRAMES 2026 is AI-themed | E69: Y | F69: Y | G69: N | I69: Sponsor | J69: Garima.singh@ficci.com | M69: Email | O69: Sent | P69: 2026-09-04 | Q69: 2026-09-04
A70: JioStar (Jio Studios/Reliance Entertainment) | B70: Indian media/production house | C70: India | D70: Largest Indian media conglomerate post Reliance-Disney merger, already producing AI content | E70: Y | F70: Y | G70: N | I70: Organizer | J70: hello@jiostar.com | M70: Email | O70: Sent | P70: 2026-09-04 | Q70: 2026-09-04
A71: Zee Entertainment Enterprises | B71: Indian media/production house | C71: India | D71: Major Indian media conglomerate, expanding Zee Studios slate | E71: Y | F71: Y | G71: N | I71: Organizer | J71: media@zee.com | M71: Email | O71: Sent | P71: 2026-09-04 | Q71: 2026-09-04
A72: Dharma Productions | B72: Indian media/production house | C72: India | D72: Major Bollywood production house, launching new distribution arm | E72: Y | F72: Y | G72: N | I72: Organizer | J72: marketing@dharma-production.com | M72: Email | O72: Sent | P72: 2026-09-04 | Q72: 2026-09-04
A73: IIFA (International Indian Film Academy) | B73: Indian media/production house | C73: India | D73: India's premier film awards/industry body, Partnerships desk explicitly covers sponsorship & brand collaboration | E73: Y | F73: Y | G73: N | I73: Organizer | J73: iifa.com/contact/ | M73: Form | O73: Form submitted | P73: 2026-09-04 | Q73: 2026-09-04
A74: NFDC (National Film Development Corporation) / WAVES Film Bazaar | B74: Government/Institutional body | C74: India | D74: Government/Institutional — India's official film co-production & market facilitation body | E74: Y | F74: Y | G74: N | I74: Sponsor | J74: coproduction@nfdcindia.com | M74: Email | O74: Sent | P74: 2026-09-04 | Q74: 2026-09-04
A75: Maharashtra Film, Stage & Cultural Development Corporation (Film City Mumbai) | B75: Government/Institutional body | C75: India | D75: Government/Institutional — Maharashtra state film body, potential venue partner in Mumbai | E75: Y | F75: Y | G75: N | I75: Sponsor | J75: contact.filmcell@maharashtra.gov.in | M75: Email | O75: Sent | P75: 2026-09-04 | Q75: 2026-09-04
A76: Four Seasons Hotel Mumbai | B76: Sponsor candidate — 5 Sep research batch | C76: Mumbai, India | D76: Premium venue with a luxury-events sales lead named directly on the hotel's own press page | E76: Y | F76: Y | G76: N | I76: Sponsor | J76: agatha.gomes@fourseasons.com | M76: Email | N76: N | O76: Sent | P76: 2026-09-05 | Q76: 2026-09-05 | R76: N | S76: N | T76: N | U76: 5 Sep research batch. Premium venue with a luxury-events sales lead named directly on the hotel's own press page
A77: Taj Hotels (IHCL) | B77: Sponsor candidate — 5 Sep research batch | C77: Mumbai, India | D77: India's most recognized hospitality brand, dedicated events inbox | E77: Y | F77: N | G77: N | I77: Sponsor | J77: meetings@ihcltata.com | M77: Email | N77: N | O77: Sent | P77: 2026-09-05 | Q77: 2026-09-05 | R77: N | S77: N | T77: N | U77: 5 Sep research batch. India's most recognized hospitality brand, dedicated events inbox
A78: ITC Hotels | B78: Sponsor candidate — 5 Sep research batch | C78: Mumbai, India | D78: Major Indian hospitality group with dedicated event infrastructure | E78: Y | F78: N | G78: N | I78: Sponsor | J78: reservations@itchotels.com | M78: Email | N78: N | O78: Sent | P78: 2026-09-05 | Q78: 2026-09-05 | R78: N | S78: N | T78: N | U78: 5 Sep research batch. Major Indian hospitality group with dedicated event infrastructure
A79: Grand Hyatt Mumbai | B79: Sponsor candidate — 5 Sep research batch | C79: Mumbai, India | D79: Premium Mumbai venue with two dedicated sales/events addresses | E79: Y | F79: Y | G79: N | I79: Sponsor | J79: sales.ghmumbai@hyatt.com | K79: mumgh.snm@hyatt.com | M79: Email | N79: N | O79: Sent | P79: 2026-09-05 | Q79: 2026-09-05 | R79: N | S79: N | T79: N | U79: 5 Sep research batch. Premium Mumbai venue with two dedicated sales/events addresses
A80: JW Marriott Mumbai Sahar | B80: Sponsor candidate — 5 Sep research batch | C80: Mumbai, India | D80: Major Marriott property near the airport, active events business | E80: Y | F80: N | G80: Y | H80: Already contacted by Aditya's other partner (confirmed 6 Sep) | I80: Sponsor | L80: https://www.marriott.com/en-us/hotels/bomsa-jw-marriott-mumbai-sahar/events/ | M80: Form | N80: N | O80: Excluded - already contacted by partner | P80: 2026-09-05 | R80: N | S80: N | T80: N | U80: 5 Sep research batch. Major Marriott property near the airport, active events business
A81: Dabur India | B81: Sponsor candidate — 5 Sep research batch | C81: India | D81: One of India's largest FMCG houses with a long history of cultural sponsorships | E81: Y | F81: N | G81: N | I81: Sponsor | J81: corpcomm@dabur.com | M81: Email | N81: N | O81: Sent | P81: 2026-09-05 | Q81: 2026-09-05 | R81: N | S81: N | T81: N | U81: 5 Sep research batch. One of India's largest FMCG houses with a long history of cultural sponsorships
A82: Paper Boat (Hector Beverages) | B82: Sponsor candidate — 5 Sep research batch | C82: India | D82: Experiential-marketing-native beverage brand, natural fit for a festival activation | E82: Y | F82: Y | G82: N | I82: Sponsor | J82: paperboat@hectorbeverages.com | M82: Email | N82: N | O82: Sent | P82: 2026-09-05 | Q82: 2026-09-05 | R82: N | S82: N | T82: N | U82: 5 Sep research batch. Experiential-marketing-native beverage brand, natural fit for a festival activation
A83: PhonePe | B83: Sponsor candidate — 5 Sep research batch | C83: India | D83: India's largest UPI player, strong brand-visibility appetite | E83: Y | F83: Y | G83: N | I83: Sponsor | J83: pr@phonepe.com | M83: Email | N83: N | O83: Sent | P83: 2026-09-05 | Q83: 2026-09-05 | R83: N | S83: N | T83: N | U83: 5 Sep research batch. India's largest UPI player, strong brand-visibility appetite
A84: SonyLIV (Culver Max Entertainment) | B84: Organizer candidate — 5 Sep research batch | C84: India | D84: Major Indian OTT platform, natural distribution/organizer angle | E84: Y | F84: N | G84: N | I84: Organizer | L84: https://advertisewithus.sonyliv.com/ | M84: Form | N84: N | O84: Ready to send | P84: 2026-09-05 | R84: N | S84: N | T84: N | U84: 5 Sep research batch. Major Indian OTT platform, natural distribution/organizer angle
A85: hoichoi | B85: Organizer candidate — 5 Sep research batch | C85: India | D85: Fast-growing regional OTT platform with a named partnerships routing | E85: Y | F85: N | G85: N | I85: Organizer | J85: support@hoichoi.tv | M85: Email | N85: N | O85: Sent | P85: 2026-09-05 | Q85: 2026-09-05 | R85: N | S85: N | T85: N | U85: 5 Sep research batch. Fast-growing regional OTT platform with a named partnerships routing
A86: IndiaAI Mission (MeitY) | B86: Sponsor candidate — 5 Sep research batch | C86: India — Government | D86: India's flagship government AI initiative — direct institutional-partner analog for an AI film festival | E86: Y | F86: Y | G86: N | I86: Sponsor | J86: impactsummit-events@indiaai.gov.in | K86: impactsummit-comms@indiaai.gov.in | M86: Email | N86: N | O86: Sent | P86: 2026-09-05 | Q86: 2026-09-05 | R86: N | S86: N | T86: N | U86: 5 Sep research batch. India's flagship government AI initiative — direct institutional-partner analog for an AI film festival
A87: CBFC (Central Board of Film Certification) | B87: Sponsor candidate — 5 Sep research batch | C87: Mumbai, India — Government | D87: India's film certification authority — institutional legitimacy for an AI-generated-film festival | E87: Y | F87: Y | G87: N | I87: Sponsor | J87: romum.cbfc@nic.in | K87: chairperson.cbfc@nic.in,ceo.cbfc@nic.in | M87: Email | N87: N | O87: Sent | P87: 2026-09-05 | Q87: 2026-09-05 | R87: N | S87: N | T87: N | U87: 5 Sep research batch. India's film certification authority — institutional legitimacy for an AI-generated-film festival
A88: FTII (Film and Television Institute of India) | B88: Organizer candidate — 5 Sep research batch | C88: Pune, India — Government | D88: India's premier film school — a natural jury/masterclass/academic-partner pipeline | E88: Y | F88: Y | G88: N | I88: Organizer | J88: registrar@ftii.ac.in | K88: vc@ftii.ac.in | M88: Email | N88: N | O88: Sent | P88: 2026-09-05 | Q88: 2026-09-05 | R88: N | S88: N | T88: N | U88: 5 Sep research batch. India's premier film school — a natural jury/masterclass/academic-partner pipeline
A89: SRFTI (Satyajit Ray Film and Television Institute) | B89: Organizer candidate — 5 Sep research batch | C89: Kolkata, India — Government | D89: Leading Indian film institute with a digital-media specialization closest to AI filmmaking | E89: Y | F89: N | G89: N | I89: Organizer | J89: contact@srfti.ac.in | K89: dean.edm@srfti.ac.in | M89: Email | N89: N | O89: Sent | P89: 2026-09-05 | Q89: 2026-09-05 | R89: N | S89: N | T89: N | U89: 5 Sep research batch. Leading Indian film institute with a digital-media specialization closest to AI filmmaking
A90: Startup Mahakumbh (FICCI / DPIIT) | B90: Sponsor candidate — 5 Sep research batch | C90: India — Government-linked | D90: Government-linked flagship startup platform, real named contact | E90: Y | F90: Y | G90: N | I90: Sponsor | J90: akshay.jain@ficci.com | M90: Email | N90: N | O90: Sent | P90: 2026-09-05 | Q90: 2026-09-05 | R90: N | S90: N | T90: N | U90: 5 Sep research batch. Government-linked flagship startup platform, real named contact
A91: Maharashtra Directorate of Tourism | B91: Sponsor candidate — 5 Sep research batch | C91: Mumbai, India — Government | D91: State-government culture/tourism channel for an India-launch story based in Mumbai | E91: Y | F91: Y | G91: N | I91: Sponsor | J91: diot@maharashtratourism.gov.in | M91: Email | N91: N | O91: Sent | P91: 2026-09-05 | Q91: 2026-09-05 | R91: N | S91: N | T91: N | U91: 5 Sep research batch. State-government culture/tourism channel for an India-launch story based in Mumbai
A92: Anthropic | B92: Sponsor candidate — 5 Sep research batch | C92: USA | D92: Leading AI lab, natural thought-leadership fit for an AI film festival | E92: Y | F92: N | G92: N | I92: Sponsor | J92: press@anthropic.com | M92: Email | N92: N | O92: Sent | P92: 2026-09-05 | Q92: 2026-09-05 | R92: N | S92: N | T92: N | U92: 5 Sep research batch. Leading AI lab, natural thought-leadership fit for an AI film festival
A93: Mistral AI | B93: Sponsor candidate — 5 Sep research batch | C93: France | D93: Major European AI lab with an events-scoped contact channel | E93: Y | F93: N | G93: N | I93: Sponsor | J93: press@mistral.ai | M93: Email | N93: N | O93: Sent | P93: 2026-09-05 | Q93: 2026-09-05 | R93: N | S93: N | T93: N | U93: 5 Sep research batch. Major European AI lab with an events-scoped contact channel
A94: Hugging Face | B94: Sponsor candidate — 5 Sep research batch | C94: USA | D94: The hub many AI filmmaking tools are built on top of | E94: Y | F94: N | G94: N | I94: Sponsor | J94: press@huggingface.co | M94: Email | N94: N | O94: Sent | P94: 2026-09-05 | Q94: 2026-09-05 | R94: N | S94: N | T94: N | U94: 5 Sep research batch. The hub many AI filmmaking tools are built on top of
A95: Magnific AI (Freepik) | B95: Sponsor candidate — 5 Sep research batch | C95: Spain | D95: AI upscaling/creative tool with a formal, named partner program — the strongest-typed match in this batch | E95: Y | F95: Y | G95: N | I95: Sponsor | J95: pr@magnific.com | M95: Email | N95: N | O95: Sent | P95: 2026-09-05 | Q95: 2026-09-05 | R95: N | S95: N | T95: N | U95: 5 Sep research batch. AI upscaling/creative tool with a formal, named partner program — the strongest-typed match in this batch
A96: Deepgram | B96: Sponsor candidate — 5 Sep research batch | C96: USA | D96: Voice-AI infra vendor relevant to AI film sound/dubbing | E96: Y | F96: N | G96: N | I96: Sponsor | L96: https://deepgram.com/partners | M96: Form | N96: N | O96: Ready to send | P96: 2026-09-05 | R96: N | S96: N | T96: N | U96: 5 Sep research batch. Voice-AI infra vendor relevant to AI film sound/dubbing
A97: AssemblyAI | B97: Sponsor candidate — 5 Sep research batch | C97: USA | D97: Speech recognition/AI infra relevant to AI film production pipelines | E97: Y | F97: N | G97: N | I97: Sponsor | L97: https://www.assemblyai.com/contact/sales | M97: Form | N97: N | O97: Closed - company declined | P97: 2026-09-05 | R97: N | S97: N | T97: N | U97: 5 Sep research batch. Speech recognition/AI infra relevant to AI film production pipelines
A98: Replicate | B98: Sponsor candidate — 5 Sep research batch | C98: USA | D98: Infrastructure layer for AI creative tooling | E98: Y | F98: N | G98: N | I98: Sponsor | L98: https://replicate.com/enterprise | M98: Form | N98: N | O98: Ready to send | P98: 2026-09-05 | R98: N | S98: N | T98: N | U98: 5 Sep research batch. Infrastructure layer for AI creative tooling
A99: Leonardo AI | B99: Sponsor candidate — 5 Sep research batch | C99: Australia | D99: AI creative tool with growing enterprise reach | E99: Y | F99: N | G99: N | I99: Sponsor | L99: https://leonardo.ai/contact-us | M99: Form | N99: N | O99: Ready to send | P99: 2026-09-05 | R99: N | S99: N | T99: N | U99: 5 Sep research batch. AI creative tool with growing enterprise reach
A100: Krikey AI | B100: Sponsor candidate — 5 Sep research batch | C100: USA | D100: AI animation/mocap tool, direct filmmaking-adjacent fit | E100: Y | F100: N | G100: N | I100: Sponsor | J100: support@krikey.com | M100: Email | N100: N | O100: Sent | P100: 2026-09-05 | Q100: 2026-09-05 | R100: N | S100: N | T100: N | U100: 5 Sep research batch. AI animation/mocap tool, direct filmmaking-adjacent fit
...

Sheet LinkedIn Tracker
A1: WAIFF India — LinkedIn Tracker (80 profiles/week, one dated batch at a time)
A2: Source only from companies already in the email batch — no separate LinkedIn universe. No repeats, ever. Row 4 is an example only.
A3: Batch # | B3: Batch date | C3: Name | D3: Title | E3: Company | F3: Profile URL | G3: Sourced from an email-batch company? (Y/N) | H3: Connection sent date | I3: Connection status | J3: Message sent date | K3: Reply? (Y/N) | L3: Reply date | M3: Follow-up date | N3: Notes
A4: 1 | B4: 2026-09-03 | C4: Jane Doe | D4: Head of Partnerships | E4: Runway AI, Inc. | F4: https://www.linkedin.com/in/example-profile | G4: Y | I4: Pending | K4: N | N4: EXAMPLE ROW — edit or delete, do not count as real data
A5: 1 | B5: 2026-09-03 | C5: Michelle Kwon | D5: Head of Operations and Partnerships | E5: Runway | F5: https://www.linkedin.com/in/michelleskwon/ | G5: Y | I5: Pending | K5: N | N5: Connection note: Hi Michelle, following Runway's Gen-4.5 and the Lionsgate deal closely. I'm building the founding sponsor group for WAiFF's India edition, launching December 2026. Would love to connect.
A6: 1 | B6: 2026-09-03 | C6: Tony Pu | D6: Community & Partnerships | E6: Kuaishou / Kling AI | F6: https://www.linkedin.com/in/tpu0817/ | G6: Y | I6: Pending | K6: N | N6: Connection note: Hi Tony, Kling AI's growth this year has been remarkable. I'm the India Ambassador for WAiFF, the AI film festival held at Cannes, building our India sponsor group. Would love to connect.
A7: 1 | B7: 2026-09-03 | C7: Paras Jain | D7: Genmo (title unconfirmed) | E7: Genmo | F7: https://www.linkedin.com/in/jain-paras/ | G7: Y | I7: Pending | K7: N | N7: Connection note: Hi Paras, Mochi 1's open approach to text-to-video stood out to me. I'm building the founding sponsor group for WAiFF India, launching December 2026. Would love to connect.
A8: 1 | B8: 2026-09-03 | C8: Franz-Josef Schrepf | D8: Revenue & Partnerships | E8: OpusClip | F8: https://www.linkedin.com/in/franz-josef-schrepf/ | G8: Y | I8: Pending | K8: N | N8: Connection note: Hi Franz-Josef, congrats on the SoftBank Vision Fund 2 investment. I'm the India Ambassador for WAiFF, the AI film festival at Cannes, building our India sponsor group. Would love to connect.
A9: 1 | B9: 2026-09-03 | C9: Callie Costello | D9: Product & Brand Marketing | E9: Mirage (Captions) | F9: https://www.linkedin.com/in/calliegcostello/ | G9: Y | I9: Pending | K9: N | N9: Connection note: Hi Callie, congrats on the $75M raise and the Asia expansion. I'm building the founding sponsor group for WAiFF's India edition, launching December 2026. Would love to connect.
A10: 1 | B10: 2026-09-03 | C10: Ross Shain | D10: Principal Creative Technologist | E10: Topaz Labs | F10: https://www.linkedin.com/in/rshain/ | G10: Y | I10: Pending | K10: N | N10: Connection note: Hi Ross, the Next-Gen model launch and NeuroStream tech are impressive. I'm the India Ambassador for WAiFF, the AI film festival at Cannes, building our India sponsor group. Would love to connect.
A11: 1 | B11: 2026-09-03 | C11: Michelle Belcic | D11: VP Sales & Partnerships | E11: Photoroom | F11: https://fr.linkedin.com/in/michellebelcic | G11: Y | I11: Pending | K11: N | N11: Connection note: Hi Michelle, Photoroom's H1 2026 product recap was impressive. I'm building the founding sponsor group for WAiFF's India edition, launching December 2026. Would love to connect.
A12: 1 | B12: 2026-09-03 | C12: Anthony Ganjou | D12: Co-Founder | E12: Move AI | F12: https://www.linkedin.com/in/anthonyganjou/ | G12: Y | I12: Pending | K12: N | N12: Connection note: Hi Anthony, Move AI's marker-less mocap work with studios like Disney and Paramount is exactly the kind of tool WAiFF's filmmakers need. Building our India sponsor group. Would love to connect.
A13: 1 | B13: 2026-09-03 | C13: Sofía Goble | D13: Operations (unconfirmed current role) | E13: Cuebric | F13: https://www.linkedin.com/in/sof%C3%ADa-goble-17a56a1a3/ | G13: Y | I13: Pending | K13: N | N13: Connection note: Hi Sofía, Cuebric's virtual-production work with Disguise caught my eye. I'm building the founding sponsor group for WAiFF's India edition, launching December 2026. Would love to connect.
A14: 1 | B14: 2026-09-03 | C14: Parthajit Sar | D14: Marketing programs | E14: NVIDIA | F14: https://in.linkedin.com/in/parthajit-sar | G14: Y | I14: Pending | K14: N | N14: Connection note: Hi Parthajit, NVIDIA's Cosmos 3 Edge announcement at SIGGRAPH was a big one for AI filmmaking. I'm building WAiFF's India sponsor group, launching December 2026. Would love to connect.
A15: 1 | B15: 2026-09-03 | C15: Vishal Dhupar | D15: Managing Director, Asia South | E15: NVIDIA | F15: https://in.linkedin.com/in/vishaldhupar | G15: Y | I15: Pending | K15: N | N15: Connection note: Hi Vishal, I'm the India Ambassador for WAiFF, the AI film festival held at Cannes, building our founding India sponsor group launching December 2026. Would love to connect.
... A135: 4 | B135: 2026-09-03 | C135: Colan Sewell | D135: VP, Chief Revenue Officer, Reality Labs | E135: Meta | F135: https://www.linkedin.com/in/colansewell/ | G135: Y | I135: Pending | K135: N | N135: Most senior revenue/partnerships executive in Reality Labs.

Sheet Gmail Tracker
A1: WAIFF India — Gmail Tracker (one send per company)
A2: One body per company: best address in To:, other addresses at that same company in BCC. Never BCC across different companies. Row 4 is an example only.
A3: Date sent | B3: Company | C3: Channel | D3: To address | E3: BCC addresses | F3: Subject line | G3: Bounced? (Y/N) | H3: Reply received? (Y/N) | I3: Reply date | J3: Follow-up Day 4 sent (Y/N) | K3: Follow-up Day 11 sent (Y/N) | L3: Follow-up Day 25 sent (Y/N) | M3: Meeting booked? (Y/N) | N3: Meeting date | O3: Status | P3: Notes
A4: 2026-09-01 | B4: Radisson Blu | C4: Email | D4: communication@radissonhotels.com | F4: Partnership Opportunity with WAIFF India — Radisson Blu x World AI Film Festival | G4: N | H4: Y | I4: 2026-09-02 | J4: N | K4: N | L4: N | M4: N | O4: Replied | P4: Sent before this tracker existed — backfilled from Gmail search 3 Sep 2026. Anuj Kumar (Marketing Manager, South Asia) asked 3 specific questions before a call. Replied 3 Sep 2026: covered India edition (Dec 2026, Mumbai), JW Marriott Cannes as existing global sponsor, what Radisson gets (network-wide visibility, access, association) and what WAiFF needs (VIP accommodation/hosting, brand partner role, not just venue). No Canva/deck link sent per standing rule. Asked for a call after 2 PM IST. Awaiting reply.
A5: 2026-09-01 | B5: EPAM Systems | C5: Email | D5: (BCC only — see BCC column) | E5: sameena.mohdali@gmail.com; sameena_ali@epam.com; nandini_bhatnagar@epam.com; nandinib2007@gmail.com; nandinibhatnagar@epam.it | F5: Partnership Opportunity with WAIFF India — EPAM Systems x World AI Film Festival | G5: N | H5: Y | I5: 2026-09-02 | J5: N | K5: N | L5: N | M5: N | O5: Replied | P5: Sent before this tracker existed — backfilled from Gmail search 3 Sep 2026. Nandini Bhatnagar (Sr Director Marketing) wants to talk after Sept 9. Replied 3 Sep 2026 confirming availability anytime after 12:00 PM IST, around 4:00 PM IST or later. Awaiting her scheduling reply.
A6: 2026-09-02 | B6: Adani Digital Labs | C6: Email | D6: (BCC only — see BCC column) | E6: digitallabs@adani.com; media@adani.com; hrishik.jethi@adani.com; cgarg@adanidigitallabs.com; manishsingh.payal@adani.com; jaladhi.shukla@adani.com; support@adanione.com; cbccyber1@adani.com | F6: Partnership Opportunity with WAIFF India — Adani Digital Labs x World AI Film Festival | G6: Y | H6: N | J6: N | K6: N | L6: N | M6: N | O6: Bounced | P6: Sent before this tracker existed — backfilled from Gmail search 3 Sep 2026. BOUNCE: 4 of 8 BCC addresses bounced (cgarg@adanidigitallabs.com, hrishik.jethi@adani.com, manishsingh.payal@adani.com, digitallabs@adani.com)
A7: 2026-09-02 | B7: Adani AI Labs | C7: Email | D7: Shalini.singh@adani.com | E7: roy.paul@adani.com; jeet.adani@adani.com; tanushyam.chattopadhyay@adani.com; investor.ael@adani.com | F7: Partnership Opportunity with WAIFF India — Adani AI Labs x World AI Film Festival | G7: Y | H7: N | J7: N | K7: N | L7: N | M7: N | O7: Bounced | P7: Sent before this tracker existed — backfilled from Gmail search 3 Sep 2026. BOUNCE: 1 of 4 BCC addresses bounced (tanushyam.chattopadhyay@adani.com); also sent separately to Shalini Singh direct
A8: 2026-09-02 | B8: Freshworks | C8: Email | D8: (BCC only — see BCC column) | E8: sales@freshworks.com; pr@freshworks.com; dpo@freshworks.com; ir@freshworks.com | F8: Partnership Opportunity with WAIFF India — Freshworks x World AI Film Festival | G8: N | H8: Y | I8: 2026-09-02 | J8: N | K8: N | L8: N | M8: N | O8: Sent | P8: Sent before this tracker existed — backfilled from Gmail search 3 Sep 2026. Automated support-ticket confirmation only — not a personal reply, no action needed yet
A9: 2026-09-02 | B9: Zoho | C9: Email | D9: (BCC only — see BCC column) | E9: sales@zohocorp.com; partner-operations@zohocorp.com; press@zohocorp.com | F9: Partnership Opportunity with WAIFF India — Zoho x World AI Film Festival | G9: N | H9: Y | I9: 2026-09-02 | J9: N | K9: N | L9: N | M9: N | O9: Sent | P9: Sent before this tracker existed — backfilled from Gmail search 3 Sep 2026. Automated partner-ticket confirmation + generic sales-team reply — not personalized, no action needed yet
A10: 2026-09-02 | B10: Myntra | C10: Email | D10: communications@myntra.com | F10: Partnership Opportunity with WAIFF India — Myntra x World AI Film Festival | G10: Y | H10: N | J10: N | K10: N | L10: N | M10: N | O10: Bounced | P10: Sent before this tracker existed — backfilled from Gmail search 3 Sep 2026. BOUNCE: Address not found (bounced) — only address used, no BCC alternates
A11: 2026-09-02 | B11: Tech Mahindra | C11: Email | D11: (BCC only — see BCC column) | E11: alliances@techmahindra.com; socialmedia@techmahindra.com; mktg@techmahindra.com; media.relations@techmahindra.com | F11: Partnership Opportunity with WAIFF India — Tech Mahindra x World AI Film Festival | G11: N | H11: N | J11: N | K11: Y | L11: N | M11: N | O11: Sent | P11: Sent before this tracker existed — backfilled from Gmail search 3 Sep 2026.
A12: 2026-09-02 | B12: BenQ India | C12: Email | D12: (BCC only — see BCC column) | E12: ruchika.singh@benq.com; ankita.karwa@benq.com; rajeev.singh@benq.com (+3 personal-looking gmail addresses also BCC'd) | F12: Partnership Opportunity with WAIFF India — BenQ India x World AI Film Festival | G12: N | H12: N | J12: N | K12: Y | L12: N | M12: N | O12: Sent | P12: Sent before this tracker existed — backfilled from Gmail search 3 Sep 2026.
A13: 2026-09-02 | B13: Sennheiser | C13: Email | D13: (BCC only — see BCC column) | E13: sponsoring@sennheiser.com; sarah.talaat@sennheiser.com; felix.teufel@sennheiser.com (+17 more BCC'd, incl. Sonova/Neumann/agency addresses) | F13: Partnership Opportunity with WAIFF India — Sennheiser x World AI Film Festival | G13: N | H13: N | J13: N | K13: Y | L13: N | M13: N | O13: Sent | P13: Sent before this tracker existed — backfilled from Gmail search 3 Sep 2026.
A14: 2026-09-03 | B14: Runway AI, Inc. | C14: Email | D14: partnerships@runwayml.com | E14: press@runwayml.com | F14: Partnering with WAiFF India — Runway x World AI Film Festival | G14: N | H14: N | J14: Y - 2026-09-07 | K14: Y - 2026-09-14 | L14: N | M14: N | O14: Sent | P14: Real send, confirmed via Gmail — landed clean, no bounce, no reply yet. | DAY-4 FOLLOW-UP SENT 7 Sep. Carried genuinely new information: the verified sponsor roster (CapCut/ByteDance, MiniMax, JW Marriott Cannes, LOTTE, Morphic, Skolae) and the official tier benefits, both extracted from the WAiFF deck on 7 Sep. Several were also reframed from sponsor pitch to organizer/jury/masterclass conversation where that fit the company better. || Day 11 follow-up sent 2026-09-14: new-fact angle (Cannes 2027 flagship now fixed 6-7 Apr 2027 at Palais des Festivals, Road to Cannes selection model, 2026 jury names). Sponsor variant for sponsor track, organizer variant naming edition ownership and retained sponsorship revenue for organizer track.
A15: 2026-09-03 | B15: Runway | C15: Email | D15: partnerships@runwayml.com | E15: press@runwayml.com | F15: WAIFF India x Runway — AI Cinema Partnership | G15: N | H15: N | J15: Y - 2026-09-07 | K15: Y - 2026-09-22 (skipped, see note) | L15: N | M15: N | O15: Sent | P15: Sent 3 Sep 2026 — Batch 1 (60), Target Batch 2 research. | DAY-4 FOLLOW-UP SENT 7 Sep. Carried genuinely new information: the verified sponsor roster (CapCut/ByteDance, MiniMax, JW Marriott Cannes, LOTTE, Morphic, Skolae) and the official tier benefits, both extracted from the WAiFF deck on 7 Sep. Several were also reframed from sponsor pitch to organizer/jury/masterclass conversation where that fit the company better. || 2026-09-22: Runway got an unplanned 3rd touch on 9/14 (new Cannes 2027 dates) only 8 days ago - skipped today's Day11 to avoid a 4th message this close. Next touch not before ~9/28.
A16: 2026-09-03 | B16: Genmo | C16: Email | D16: hi@genmo.ai | F16: WAIFF India x Genmo — AI Cinema Partnership | G16: N | H16: N | J16: Y - 2026-09-07 | K16: Y - 2026-09-22 (skipped, see note) | L16: N | M16: N | O16: Sent | P16: Sent 3 Sep 2026 — Batch 1 (60), Target Batch 2 research. | DAY-4 FOLLOW-UP SENT 7 Sep. Carried genuinely new information: the verified sponsor roster (CapCut/ByteDance, MiniMax, JW Marriott Cannes, LOTTE, Morphic, Skolae) and the official tier benefits, both extracted from the WAiFF deck on 7 Sep. Several were also reframed from sponsor pitch to organizer/jury/masterclass conversation where that fit the company better. || 2026-09-22: Genmo got a DUPLICATE fresh cold email on 9/13 (new thread, not a real follow-up) on top of the proper 9/7 Day4 follow-up - skipped today's Day11, already touched 9 days ago. Flag: duplicate-contact bug from a past batch, not a real Day11.
A17: 2026-09-03 | B17: Shengshu Technology (Vidu) | C17: Email | D17: support@vidu.com | F17: WAIFF India x Shengshu Technology (Vidu) — AI Cinema Partnership | G17: N | H17: Y | I17: 2026-09-08 | J17: Y - 2026-09-07 | K17: Y - 2026-09-19 (live conversation, covered via direct reply not generic followup) | L17: N | M17: N | O17: Replied - engaged conversation | P17: Sent 3 Sep 2026 — Batch 1 (60), Target Batch 2 research. | DAY-4 FOLLOW-UP SENT 7 Sep. Carried genuinely new information: the verified sponsor roster (CapCut/ByteDance, MiniMax, JW Marriott Cannes, LOTTE, Morphic, Skolae) and the official tier benefits, both extracted from the WAiFF deck on 7 Sep. Several were also reframed from sponsor pitch to organizer/jury/masterclass conversation where that fit the company better. || CORRECTION 2026-09-22: this IS actively engaged. Han (Runjie Han, Head of Operations, shengshu.ai) replied 9/8 asking to learn more, Aditya answered same day, sent detailed opportunity outline 9/10, and sent a further concrete follow-up 9/19 (3 days ago). This is a live conversation, not a cold lead. Do NOT send a generic Day11 follow-up here. Separately a duplicate cold email went to support@vidu.com again on 9/13 under a different subject line, unrelated to the live Han thread — flagged as a duplicate-contact cleanup item, no action needed now.
A18: 2026-09-03 | B18: ElevenLabs | C18: Email | D18: press@elevenlabs.io | F18: WAIFF India x ElevenLabs — AI Cinema Partnership | G18: N | H18: N | J18: Y - 2026-09-07 | K18: Y | L18: N | M18: N | O18: Sent | P18: Sent 3 Sep 2026 — Batch 1 (60), Target Batch 2 research. | DAY-4 FOLLOW-UP SENT 7 Sep. Carried genuinely new information: the verified sponsor roster (CapCut/ByteDance, MiniMax, JW Marriott Cannes, LOTTE, Morphic, Skolae) and the official tier benefits, both extracted from the WAiFF deck on 7 Sep. Several were also reframed from sponsor pitch to organizer/jury/masterclass conversation where that fit the company better. || Day 11 follow-up sent 2026-09-14: new-fact angle (Cannes 2027 flagship now fixed 6-7 Apr 2027 at Palais des Festivals, Road to Cannes selection model, 2026 jury names). Sponsor variant for sponsor track, organizer variant naming edition ownership and retained sponsorship revenue for organizer track. | Day-11 follow-up sent 2026-09-23, msgid 1a0cdce1a73bd6c5. Updated with Cannes 6-7 Apr 2027 + 2027 jury (Agnès Jaoui President).
A19: 2026-09-03 | B19: Murf AI | C19: Email | D19: alliances@murf.ai | E19: enterprise@murf.ai; support@murf.ai | F19: WAIFF India x Murf AI — AI Cinema Partnership | G19: N | H19: N | J19: Y - 2026-09-07 | K19: Y - 2026-09-22 (skipped, see note) | L19: N | M19: N | O19: Sent | P19: Sent 3 Sep 2026 — Batch 1 (60), Target Batch 2 research. | DAY-4 FOLLOW-UP SENT 7 Sep. Carried genuinely new information: the verified sponsor roster (CapCut/ByteDance, MiniMax, JW Marriott Cannes, LOTTE, Morphic, Skolae) and the official tier benefits, both extracted from the WAiFF deck on 7 Sep. Several were also reframed from sponsor pitch to organizer/jury/masterclass conversation where that fit the company better. || 2026-09-22: Murf AI got a DUPLICATE fresh cold email on 9/13 (new thread) on top of the proper 9/7 Day4 follow-up - skipped today's Day11, already touched 9 days ago. Same duplicate-contact bug as Genmo/Stability.
A20: 2026-09-03 | B20: NeuralGarage | C20: Email | D20: info@neuralgarage.com | F20: WAIFF India x NeuralGarage — AI Cinema Partnership | G20: N | H20: N | J20: Y - 2026-09-07 | K20: Y | L20: N | M20: N | O20: Sent | P20: Sent 3 Sep 2026 — Batch 1 (60), Target Batch 2 research. | DAY-4 FOLLOW-UP SENT 7 Sep. Carried genuinely new information: the verified sponsor roster (CapCut/ByteDance, MiniMax, JW Marriott Cannes, LOTTE, Morphic, Skolae) and the official tier benefits, both extracted from the WAiFF deck on 7 Sep. Several were also reframed from sponsor pitch to organizer/jury/masterclass conversation where that fit the company better. || Day 11 follow-up sent 2026-09-14: new-fact angle (Cannes 2027 flagship now fixed 6-7 Apr 2027 at Palais des Festivals, Road to Cannes selection model, 2026 jury names). Sponsor variant for sponsor track, organizer variant naming edition ownership and retained sponsorship revenue for organizer track. | Day-11 follow-up sent 2026-09-23, msgid 1a0cdce2582fee41. Updated with Cannes 6-7 Apr 2027 + 2027 jury (Agnès Jaoui President).
A21: 2026-09-03 | B21: Synthesia | C21: Email | D21: press@synthesia.io | F21: WAIFF India x Synthesia — AI Cinema Partnership | G21: N | H21: N | J21: Y - 2026-09-07 | K21: Y | L21: N | M21: N | O21: Sent | P21: Sent 3 Sep 2026 — Batch 1 (60), Target Batch 2 research. | DAY-4 FOLLOW-UP SENT 7 Sep. Carried genuinely new information: the verified sponsor roster (CapCut/ByteDance, MiniMax, JW Marriott Cannes, LOTTE, Morphic, Skolae) and the official tier benefits, both extracted from the WAiFF deck on 7 Sep. Several were also reframed from sponsor pitch to organizer/jury/masterclass conversation where that fit the company better. || Day 11 follow-up sent 2026-09-14: new-fact angle (Cannes 2027 flagship now fixed 6-7 Apr 2027 at Palais des Festivals, Road to Cannes selection model, 2026 jury names). Sponsor variant for sponsor track, organizer variant naming edition ownership and retained sponsorship revenue for organizer track. | Day-11 follow-up sent 2026-09-23, msgid 1a0cdce2b2574fe5. Updated with Cannes 6-7 Apr 2027 + 2027 jury (Agnès Jaoui President).
A22: 2026-09-03 | B22: OpusClip (Opus.pro) | C22: Email | D22: contact@opus.pro | F22: WAIFF India x OpusClip (Opus.pro) — AI Cinema Partnership | G22: N | H22: N | J22: Y - 2026-09-07 | K22: Y | L22: N | M22: N | O22: Sent | P22: Sent 3 Sep 2026 — Batch 1 (60), Target Batch 2 research. | DAY-4 FOLLOW-UP SENT 7 Sep. Carried genuinely new information: the verified sponsor roster (CapCut/ByteDance, MiniMax, JW Marriott Cannes, LOTTE, Morphic, Skolae) and the official tier benefits, both extracted from the WAiFF deck on 7 Sep. Several were also reframed from sponsor pitch to organizer/jury/masterclass conversation where that fit the company better. || Day 11 follow-up sent 2026-09-14: new-fact angle (Cannes 2027 flagship now fixed 6-7 Apr 2027 at Palais des Festivals, Road to Cannes selection model, 2026 jury names). Sponsor variant for sponsor track, organizer variant naming edition ownership and retained sponsorship revenue for organizer track. | Day-11 follow-up sent 2026-09-23, msgid 1a0cdce31e8a75ce. Updated with Cannes 6-7 Apr 2027 + 2027 jury (Agnès Jaoui President).
A23: 2026-09-03 | B23: Captions (Mirage) | C23: Email | D23: press@mirage.app | E23: info@mirage.app | F23: WAIFF India x Captions (Mirage) — AI Cinema Partnership | G23: N | H23: N | J23: Y - 2026-09-07 | K23: Y | L23: N | M23: N | O23: Sent | P23: Sent 3 Sep 2026 — Batch 1 (60), Target Batch 2 research. | DAY-4 FOLLOW-UP SENT 7 Sep. Carried genuinely new information: the verified sponsor roster (CapCut/ByteDance, MiniMax, JW Marriott Cannes, LOTTE, Morphic, Skolae) and the official tier benefits, both extracted from the WAiFF deck on 7 Sep. Several were also reframed from sponsor pitch to organizer/jury/masterclass conversation where that fit the company better. || Day 11 follow-up sent 2026-09-14: new-fact angle (Cannes 2027 flagship now fixed 6-7 Apr 2027 at Palais des Festivals, Road to Cannes selection model, 2026 jury names). Sponsor variant for sponsor track, organizer variant naming edition ownership and retained sponsorship revenue for organizer track. | Day-11 follow-up sent 2026-09-23, msgid 1a0cdce38cb88fae. Updated with Cannes 6-7 Apr 2027 + 2027 jury (Agnès Jaoui President).
A24: 2026-09-03 | B24: Topaz Labs | C24: Email | D24: Press@topazlabs.com | F24: WAIFF India x Topaz Labs — AI Cinema Partnership | G24: N | H24: N | J24: Y - 2026-09-07 | K24: Y | L24: N | M24: N | O24: Sent | P24: Sent 3 Sep 2026 — Batch 1 (60), Target Batch 2 research. | DAY-4 FOLLOW-UP SENT 7 Sep. Carried genuinely new information: the verified sponsor roster (CapCut/ByteDance, MiniMax, JW Marriott Cannes, LOTTE, Morphic, Skolae) and the official tier benefits, both extracted from the WAiFF deck on 7 Sep. Several were also reframed from sponsor pitch to organizer/jury/masterclass conversation where that fit the company better. || Day 11 follow-up sent 2026-09-14: new-fact angle (Cannes 2027 flagship now fixed 6-7 Apr 2027 at Palais des Festivals, Road to Cannes selection model, 2026 jury names). Sponsor variant for sponsor track, organizer variant naming edition ownership and retained sponsorship revenue for organizer track. | Day-11 follow-up sent 2026-09-23, msgid 1a0cdce41c4aeb4a. Updated with Cannes 6-7 Apr 2027 + 2027 jury (Agnès Jaoui President).
A25: 2026-09-03 | B25: Black Forest Labs | C25: Email | D25: info@blackforestlabs.ai | F25: WAIFF India x Black Forest Labs — AI Cinema Partnership | G25: N | H25: N | J25: Y - 2026-09-07 | K25: Y | L25: N | M25: N | O25: Sent | P25: Sent 3 Sep 2026 — Batch 1 (60), Target Batch 2 research. | DAY-4 FOLLOW-UP SENT 7 Sep. Carried genuinely new information: the verified sponsor roster (CapCut/ByteDance, MiniMax, JW Marriott Cannes, LOTTE, Morphic, Skolae) and the official tier benefits, both extracted from the WAiFF deck on 7 Sep. Several were also reframed from sponsor pitch to organizer/jury/masterclass conversation where that fit the company better. || Day 11 follow-up sent 2026-09-14: new-fact angle (Cannes 2027 flagship now fixed 6-7 Apr 2027 at Palais des Festivals, Road to Cannes selection model, 2026 jury names). Sponsor variant for sponsor track, organizer variant naming edition ownership and retained sponsorship revenue for organizer track. | Day-11 follow-up sent 2026-09-23, msgid 1a0cdce483f4a18d. Updated with Cannes 6-7 Apr 2027 + 2027 jury (Agnès Jaoui President).
A26: 2026-09-03 | B26: Stability AI | C26: Email | D26: partners@stability.ai | E26: press@stability.ai | F26: WAIFF India x Stability AI — AI Cinema Partnership | G26: N | H26: N | J26: Y - 2026-09-07 | K26: Y - 2026-09-22 (skipped, see note) | L26: N | M26: N | O26: Sent | P26: Sent 3 Sep 2026 — Batch 1 (60), Target Batch 2 research. | DAY-4 FOLLOW-UP SENT 7 Sep. Carried genuinely new information: the verified sponsor roster (CapCut/ByteDance, MiniMax, JW Marriott Cannes, LOTTE, Morphic, Skolae) and the official tier benefits, both extracted from the WAiFF deck on 7 Sep. Several were also reframed from sponsor pitch to organizer/jury/masterclass conversation where that fit the company better. || 2026-09-22: Stability AI got a DUPLICATE fresh cold email on 9/13 (new thread) on top of the proper 9/7 Day4 follow-up - skipped today's Day11, already touched 9 days ago. Same duplicate-contact bug as Genmo/Murf.
A27: 2026-09-03 | B27: NVIDIA | C27: Email | D27: india-pr@nvidia.com | F27: WAIFF India x NVIDIA — AI Cinema Partnership | G27: N | H27: N | J27: Y - 2026-09-19 | K27: Y | L27: N | M27: N | O27: Sent | P27: Sent 3 Sep 2026 — Batch 1 (60), Target Batch 2 research. || 2026-09-19: check-in sent to Kavita Aroor (karoor@nvidia.com, cc Shristi Mahnot) on the live thread after her 2-week review window, MsgID 1a0b9366e4eee7f9. Note: Aditya also sent a separate cold email to 7 NVIDIA employees (BCC) on 2026-09-17. || CORRECTION 2026-09-22: the india-pr@nvidia.com address (this row) never replied directly. The real live NVIDIA relationship is with Kavita Aroor (karoor@nvidia.com) on a separate thread — she replied 9/3 ("will review internally, revert in a couple weeks"), Aditya sent a check-in 9/19 (3 days ago), still awaiting her response. Do NOT send another follow-up to NVIDIA today, the 9/19 check-in already covers it. Also found: a 7-person BCC blast to NVIDIA on 9/3 (separate from this row) got only a boilerplate Inception-program redirect, no real reply. NVIDIA has 3-4 disconnected threads under one company name — needs manual consolidation, flagged to Aditya. | Day-11 follow-up sent 2026-09-23, msgid 1a0cdce4e1d1f8a5. Updated with Cannes 6-7 Apr 2027 + 2027 jury (Agnès Jaoui President).
A28: 2026-09-03 | B28: Qualcomm | C28: Email | D28: corpcomm@qualcomm.com | F28: WAIFF India x Qualcomm — AI Cinema Partnership | G28: N | H28: N | J28: Y - 2026-09-07 | K28: Y | L28: N | M28: N | O28: Sent | P28: Sent 3 Sep 2026 — Batch 1 (60), Target Batch 2 research. | DAY-4 FOLLOW-UP SENT 7 Sep. Carried genuinely new information: the verified sponsor roster (CapCut/ByteDance, MiniMax, JW Marriott Cannes, LOTTE, Morphic, Skolae) and the official tier benefits, both extracted from the WAiFF deck on 7 Sep. Several were also reframed from sponsor pitch to organizer/jury/masterclass conversation where that fit the company better. || Day 11 follow-up sent 2026-09-14: new-fact angle (Cannes 2027 flagship now fixed 6-7 Apr 2027 at Palais des Festivals, Road to Cannes selection model, 2026 jury names). Sponsor variant for sponsor track, organizer variant naming edition ownership and retained sponsorship revenue for organizer track. | Day-11 follow-up sent 2026-09-23, msgid 1a0cdce57d742093. Updated with Cannes 6-7 Apr 2027 + 2027 jury (Agnès Jaoui President).
A29: 2026-09-03 | B29: Sony India | C29: Email | D29: press.india@sony.com | F29: WAIFF India x Sony India — AI Cinema Partnership | G29: N | H29: N | J29: Y - 2026-09-07 | K29: Y | L29: N | M29: N | O29: Sent | P29: Sent 3 Sep 2026 — Batch 1 (60), Target Batch 2 research. | DAY-4 FOLLOW-UP SENT 7 Sep. Carried genuinely new information: the verified sponsor roster (CapCut/ByteDance, MiniMax, JW Marriott Cannes, LOTTE, Morphic, Skolae) and the official tier benefits, both extracted from the WAiFF deck on 7 Sep. Several were also reframed from sponsor pitch to organizer/jury/masterclass conversation where that fit the company better. || Day 11 follow-up sent 2026-09-14: new-fact angle (Cannes 2027 flagship now fixed 6-7 Apr 2027 at Palais des Festivals, Road to Cannes selection model, 2026 jury names). Sponsor variant for sponsor track, organizer variant naming edition ownership and retained sponsorship revenue for organizer track. | Day-11 follow-up sent 2026-09-23, msgid 1a0cdce5dfb2beba. Updated with Cannes 6-7 Apr 2027 + 2027 jury (Agnès Jaoui President).
A30: 2026-09-03 | B30: Harman International (JBL) | C30: Email | D30: indiaprosales@harman.com | E30: indiaprocare@harman.com; david.glaubke@harman.com | F30: WAIFF India x Harman International (JBL) — AI Cinema Partnership | G30: N | H30: N | J30: Y - 2026-09-07 | K30: Y | L30: N | M30: N | O30: Sent | P30: Sent 3 Sep 2026 — Batch 1 (60), Target Batch 2 research. | DAY-4 FOLLOW-UP SENT 7 Sep. Carried genuinely new information: the verified sponsor roster (CapCut/ByteDance, MiniMax, JW Marriott Cannes, LOTTE, Morphic, Skolae) and the official tier benefits, both extracted from the WAiFF deck on 7 Sep. Several were also reframed from sponsor pitch to organizer/jury/masterclass conversation where that fit the company better. || Day 11 follow-up sent 2026-09-14: new-fact angle (Cannes 2027 flagship now fixed 6-7 Apr 2027 at Palais des Festivals, Road to Cannes selection model, 2026 jury names). Sponsor variant for sponsor track, organizer variant naming edition ownership and retained sponsorship revenue for organizer track. | Day-11 follow-up sent 2026-09-23, msgid 1a0cdce64b54c428. Updated with Cannes 6-7 Apr 2027 + 2027 jury (Agnès Jaoui President).
A31: 2026-09-03 | B31: Zebronics | C31: Email | D31: enquiry@zebronics.com | F31: WAIFF India x Zebronics — AI Cinema Partnership | G31: N | H31: N | J31: Y - 2026-09-07 | K31: Y | L31: N | M31: N | O31: Sent | P31: Sent 3 Sep 2026 — Batch 1 (60), Target Batch 2 research. | DAY-4 FOLLOW-UP SENT 7 Sep. Carried genuinely new information: the verified sponsor roster (CapCut/ByteDance, MiniMax, JW Marriott Cannes, LOTTE, Morphic, Skolae) and the official tier benefits, both extracted from the WAiFF deck on 7 Sep. Several were also reframed from sponsor pitch to organizer/jury/masterclass conversation where that fit the company better. || Day 11 follow-up sent 2026-09-14: new-fact angle (Cannes 2027 flagship now fixed 6-7 Apr 2027 at Palais des Festivals, Road to Cannes selection model, 2026 jury names). Sponsor variant for sponsor track, organizer variant naming edition ownership and retained sponsorship revenue for organizer track. | Day-11 follow-up sent 2026-09-23, msgid 1a0cdce6bbe1caa9. Updated with Cannes 6-7 Apr 2027 + 2027 jury (Agnès Jaoui President).
A32: 2026-09-03 | B32: Dell Technologies India | C32: Email | D32: media.relations@dell.com | F32: WAIFF India x Dell Technologies India — AI Cinema Partnership | G32: N | H32: Y | J32: Y - 2026-09-07 | K32: Y - 2026-09-14 | L32: N | M32: N | O32: Replied - Declined | P32: Sent 3 Sep 2026 — Batch 1 (60), Target Batch 2 research. | DAY-4 FOLLOW-UP SENT 7 Sep. Carried genuinely new information: the verified sponsor roster (CapCut/ByteDance, MiniMax, JW Marriott Cannes, LOTTE, Morphic, Skolae) and the official tier benefits, both extracted from the WAiFF deck on 7 Sep. Several were also reframed from sponsor pitch to organizer/jury/masterclass conversation where that fit the company better. || Day 11 follow-up sent 2026-09-14: new-fact angle (Cannes 2027 flagship now fixed 6-7 Apr 2027 at Palais des Festivals, Road to Cannes selection model, 2026 jury names). Sponsor variant for sponsor track, organizer variant naming edition ownership and retained sponsorship revenue for organizer track. || REPLY 2026-09-14: Dell Media Relations declined, won't explore a collaboration at this time.
A33: 2026-09-03 | B33: ASUS India | C33: Email | D33: Media@asus.com | F33: WAIFF India x ASUS India — AI Cinema Partnership | G33: N | H33: N | J33: Y - 2026-09-07 | K33: Y | L33: N | M33: N | O33: Sent | P33: Sent 3 Sep 2026 — Batch 1 (60), Target Batch 2 research. | DAY-4 FOLLOW-UP SENT 7 Sep. Carried genuinely new information: the verified sponsor roster (CapCut/ByteDance, MiniMax, JW Marriott Cannes, LOTTE, Morphic, Skolae) and the official tier benefits, both extracted from the WAiFF deck on 7 Sep. Several were also reframed from sponsor pitch to organizer/jury/masterclass conversation where that fit the company better. || Day 11 follow-up sent 2026-09-14: new-fact angle (Cannes 2027 flagship now fixed 6-7 Apr 2027 at Palais des Festivals, Road to Cannes selection model, 2026 jury names). Sponsor variant for sponsor track, organizer variant naming edition ownership and retained sponsorship revenue for organizer track. | Day-11 follow-up sent 2026-09-23, msgid 1a0cdce72ee3cd67. Updated with Cannes 6-7 Apr 2027 + 2027 jury (Agnès Jaoui President).
A34: 2026-09-03 | B34: Lenovo India | C34: Email | D34: grace.gabel@lenovo.com | E34: sabrina.mohan@lenovo.com; stephanie.yu@lenovo.com | F34: WAIFF India x Lenovo India — AI Cinema Partnership | G34: N | H34: N | J34: Y - 2026-09-07 | K34: Y | L34: N | M34: N | O34: Sent | P34: Sent 3 Sep 2026 — Batch 1 (60), Target Batch 2 research. | DAY-4 FOLLOW-UP SENT 7 Sep. Carried genuinely new information: the verified sponsor roster (CapCut/ByteDance, MiniMax, JW Marriott Cannes, LOTTE, Morphic, Skolae) and the official tier benefits, both extracted from the WAiFF deck on 7 Sep. Several were also reframed from sponsor pitch to organizer/jury/masterclass conversation where that fit the company better. || Day 11 follow-up sent 2026-09-14: new-fact angle (Cannes 2027 flagship now fixed 6-7 Apr 2027 at Palais des Festivals, Road to Cannes selection model, 2026 jury names). Sponsor variant for sponsor track, organizer variant naming edition ownership and retained sponsorship revenue for organizer track. | Day-11 follow-up sent 2026-09-23, msgid 1a0cdce7d5058af6. Updated with Cannes 6-7 Apr 2027 + 2027 jury (Agnès Jaoui President).
A35: 2026-09-03 | B35: Western Digital (SanDisk Professional) | C35: Email | D35: WD.Mediainquiries@wdc.com | F35: WAIFF India x Western Digital (SanDisk Professional) — AI Cinema Partnership | G35: N | H35: N | J35: Y - 2026-09-07 | K35: Y | L35: N | M35: N | O35: Sent | P35: Sent 3 Sep 2026 — Batch 1 (60), Target Batch 2 research. | DAY-4 FOLLOW-UP SENT 7 Sep. Carried genuinely new information: the verified sponsor roster (CapCut/ByteDance, MiniMax, JW Marriott Cannes, LOTTE, Morphic, Skolae) and the official tier benefits, both extracted from the WAiFF deck on 7 Sep. Several were also reframed from sponsor pitch to organizer/jury/masterclass conversation where that fit the company better. || Day 11 follow-up sent 2026-09-14: new-fact angle (Cannes 2027 flagship now fixed 6-7 Apr 2027 at Palais des Festivals, Road to Cannes selection model, 2026 jury names). Sponsor variant for sponsor track, organizer variant naming edition ownership and retained sponsorship revenue for organizer track. | Day-11 follow-up sent 2026-09-23, msgid 1a0cdce804ab916a. Updated with Cannes 6-7 Apr 2027 + 2027 jury (Agnès Jaoui President).
A36: 2026-09-03 | B36: Samsung India | C36: Email | D36: corpcommindia@samsung.com | F36: WAIFF India x Samsung India — AI Cinema Partnership | G36: N | H36: N | J36: Y - 2026-09-07 | K36: Y | L36: N | M36: N | O36: Sent | P36: Sent 3 Sep 2026 — Batch 1 (60), Target Batch 2 research. | DAY-4 FOLLOW-UP SENT 7 Sep. Carried genuinely new information: the verified sponsor roster (CapCut/ByteDance, MiniMax, JW Marriott Cannes, LOTTE, Morphic, Skolae) and the official tier benefits, both extracted from the WAiFF deck on 7 Sep. Several were also reframed from sponsor pitch to organizer/jury/masterclass conversation where that fit the company better. || Day 11 follow-up sent 2026-09-14: new-fact angle (Cannes 2027 flagship now fixed 6-7 Apr 2027 at Palais des Festivals, Road to Cannes selection model, 2026 jury names). Sponsor variant for sponsor track, organizer variant naming edition ownership and retained sponsorship revenue for organizer track. | Day-11 follow-up sent 2026-09-23: sponsor-track template, updated Cannes facts (Apr 6-7 2027 Palais des Festivals; Agnes Jaoui jury president, Roger Avary, Elsa Zylberstein; Gong Li dropped from 2027 jury claim per Section 23 correction). Follow-up msgid 1a0cdd664d4ab074.
A37: 2026-09-03 | B37: Krutrim AI (Ola Krutrim) | C37: Email | D37: sales@olakrutrim.com | E37: cloudsupport@olakrutrim.com | F37: WAIFF India x Krutrim AI (Ola Krutrim) — AI Cinema Partnership | G37: N | H37: N | J37: Y - 2026-09-07 | K37: Y | L37: N | M37: N | O37: Sent | P37: Sent 3 Sep 2026 — Batch 1 (60), Target Batch 2 research. | DAY-4 FOLLOW-UP SENT 7 Sep. Carried genuinely new information: the verified sponsor roster (CapCut/ByteDance, MiniMax, JW Marriott Cannes, LOTTE, Morphic, Skolae) and the official tier benefits, both extracted from the WAiFF deck on 7 Sep. Several were also reframed from sponsor pitch to organizer/jury/masterclass conversation where that fit the company better. || Day 11 follow-up sent 2026-09-14: new-fact angle (Cannes 2027 flagship now fixed 6-7 Apr 2027 at Palais des Festivals, Road to Cannes selection model, 2026 jury names). Sponsor variant for sponsor track, organizer variant naming edition ownership and retained sponsorship revenue for organizer track. | Day-11 follow-up sent 2026-09-23: sponsor-track template, updated Cannes facts (Apr 6-7 2027 Palais des Festivals; Agnes Jaoui jury president, Roger Avary, Elsa Zylberstein; Gong Li dropped from 2027 jury claim per Section 23 correction). Follow-up msgid 1a0cdd67512a41db.
A38: 2026-09-03 | B38: Yotta Data Services | C38: Email | D38: marketing@yotta.com | E38: info@yotta.com | F38: WAIFF India x Yotta Data Services — AI Cinema Partnership | G38: N | H38: N | J38: Y - 2026-09-07 | K38: Y | L38: N | M38: N | O38: Sent | P38: Sent 3 Sep 2026 — Batch 1 (60), Target Batch 2 research. | DAY-4 FOLLOW-UP SENT 7 Sep. Carried genuinely new information: the verified sponsor roster (CapCut/ByteDance, MiniMax, JW Marriott Cannes, LOTTE, Morphic, Skolae) and the official tier benefits, both extracted from the WAiFF deck on 7 Sep. Several were also reframed from sponsor pitch to organizer/jury/masterclass conversation where that fit the company better. || DAY-11 FOLLOWUP sent 2026-09-22: new fact (Buenos Aires + Montreal/Vancouver Oct 2026 editions confirmed), in-thread reply. | Day-11 follow-up sent 2026-09-23: sponsor-track template, updated Cannes facts (Apr 6-7 2027 Palais des Festivals; Agnes Jaoui jury president, Roger Avary, Elsa Zylberstein; Gong Li dropped from 2027 jury claim per Section 23 correction). Follow-up msgid 1a0cdd685998ae61.
A39: 2026-09-03 | B39: E2E Networks | C39: Email | D39: sales@e2enetworks.com | F39: WAIFF India x E2E Networks — AI Cinema Partnership | G39: N | H39: N | J39: Y - 2026-09-07 | K39: Y | L39: N | M39: N | O39: Sent | P39: Sent 3 Sep 2026 — Batch 1 (60), Target Batch 2 research. | DAY-4 FOLLOW-UP SENT 7 Sep. Carried genuinely new information: the verified sponsor roster (CapCut/ByteDance, MiniMax, JW Marriott Cannes, LOTTE, Morphic, Skolae) and the official tier benefits, both extracted from the WAiFF deck on 7 Sep. Several were also reframed from sponsor pitch to organizer/jury/masterclass conversation where that fit the company better. || Day 11 follow-up sent 2026-09-14: new-fact angle (Cannes 2027 flagship now fixed 6-7 Apr 2027 at Palais des Festivals, Road to Cannes selection model, 2026 jury names). Sponsor variant for sponsor track, organizer variant naming edition ownership and retained sponsorship revenue for organizer track. | Day-11 follow-up sent 2026-09-23: sponsor-track template, updated Cannes facts (Apr 6-7 2027 Palais des Festivals; Agnes Jaoui jury president, Roger Avary, Elsa Zylberstein; Gong Li dropped from 2027 jury claim per Section 23 correction). Follow-up msgid 1a0cdd6972599936.
A40: 2026-09-03 | B40: Netweb Technologies | C40: Email | D40: mktkol@netwebindia.com | E40: info@netwebindia.com; hydsales@netwebindia.com | F40: WAIFF India x Netweb Technologies — AI Cinema Partnership | G40: N | H40: N | J40: Y - 2026-09-07 | K40: Y | L40: N | M40: N | O40: Sent | P40: Sent 3 Sep 2026 — Batch 1 (60), Target Batch 2 research. | DAY-4 FOLLOW-UP SENT 7 Sep. Carried genuinely new information: the verified sponsor roster (CapCut/ByteDance, MiniMax, JW Marriott Cannes, LOTTE, Morphic, Skolae) and the official tier benefits, both extracted from the WAiFF deck on 7 Sep. Several were also reframed from sponsor pitch to organizer/jury/masterclass conversation where that fit the company better. || Day 11 follow-up sent 2026-09-14: new-fact angle (Cannes 2027 flagship now fixed 6-7 Apr 2027 at Palais des Festivals, Road to Cannes selection model, 2026 jury names). Sponsor variant for sponsor track, organizer variant naming edition ownership and retained sponsorship revenue for organizer track. | Day-11 follow-up sent 2026-09-23: sponsor-track template, updated Cannes facts (Apr 6-7 2027 Palais des Festivals; Agnes Jaoui jury president, Roger Avary, Elsa Zylberstein; Gong Li dropped from 2027 jury claim per Section 23 correction). Follow-up msgid 1a0cdd6a66a2edfe.
A41: 2026-09-03 | B41: CtrlS Datacenters | C41: Email | D41: marketing@ctrls.in | F41: WAIFF India x CtrlS Datacenters — AI Cinema Partnership | G41: N | H41: N | J41: Y - 2026-09-07 | K41: Y | L41: N | M41: N | O41: Sent | P41: Sent 3 Sep 2026 — Batch 1 (60), Target Batch 2 research. | DAY-4 FOLLOW-UP SENT 7 Sep. Carried genuinely new information: the verified sponsor roster (CapCut/ByteDance, MiniMax, JW Marriott Cannes, LOTTE, Morphic, Skolae) and the official tier benefits, both extracted from the WAiFF deck on 7 Sep. Several were also reframed from sponsor pitch to organizer/jury/masterclass conversation where that fit the company better. || Day 11 follow-up sent 2026-09-14: new-fact angle (Cannes 2027 flagship now fixed 6-7 Apr 2027 at Palais des Festivals, Road to Cannes selection model, 2026 jury names). Sponsor variant for sponsor track, organizer variant naming edition ownership and retained sponsorship revenue for organizer track. | Day-11 follow-up sent 2026-09-23: sponsor-track template, updated Cannes facts (Apr 6-7 2027 Palais des Festivals; Agnes Jaoui jury president, Roger Avary, Elsa Zylberstein; Gong Li dropped from 2027 jury claim per Section 23 correction). Follow-up msgid 1a0cdd6b76421472.
A42: 2026-09-03 | B42: Nikon India / RED Digital Cinema | C42: Email | D42: NindSupport@nikon.com | F42: WAIFF India x Nikon India / RED Digital Cinema — AI Cinema Partnership | G42: N | H42: N | J42: Y - 2026-09-07 | K42: Y | L42: N | M42: N | O42: Sent | P42: Sent 3 Sep 2026 — Batch 1 (60), Target Batch 2 research. | DAY-4 FOLLOW-UP SENT 7 Sep. Carried genuinely new information: the verified sponsor roster (CapCut/ByteDance, MiniMax, JW Marriott Cannes, LOTTE, Morphic, Skolae) and the official tier benefits, both extracted from the WAiFF deck on 7 Sep. Several were also reframed from sponsor pitch to organizer/jury/masterclass conversation where that fit the company better. || Day 11 follow-up sent 2026-09-14: new-fact angle (Cannes 2027 flagship now fixed 6-7 Apr 2027 at Palais des Festivals, Road to Cannes selection model, 2026 jury names). Sponsor variant for sponsor track, organizer variant naming edition ownership and retained sponsorship revenue for organizer track. | Day-11 follow-up sent 2026-09-23: sponsor-track template, updated Cannes facts (Apr 6-7 2027 Palais des Festivals; Agnes Jaoui jury president, Roger Avary, Elsa Zylberstein; Gong Li dropped from 2027 jury claim per Section 23 correction). Follow-up msgid 1a0cdd6c868010c1.
A43: 2026-09-03 | B43: Panasonic (Lumix) India | C43: Email | D43: helpline@in.Panasonic.com | F43: WAIFF India x Panasonic (Lumix) India — AI Cinema Partnership | G43: N | H43: N | J43: Y - 2026-09-07 | K43: Y | L43: N | M43: N | O43: Sent | P43: Sent 3 Sep 2026 — Batch 1 (60), Target Batch 2 research. | DAY-4 FOLLOW-UP SENT 7 Sep. Carried genuinely new information: the verified sponsor roster (CapCut/ByteDance, MiniMax, JW Marriott Cannes, LOTTE, Morphic, Skolae) and the official tier benefits, both extracted from the WAiFF deck on 7 Sep. Several were also reframed from sponsor pitch to organizer/jury/masterclass conversation where that fit the company better. || Day 11 follow-up sent 2026-09-14: new-fact angle (Cannes 2027 flagship now fixed 6-7 Apr 2027 at Palais des Festivals, Road to Cannes selection model, 2026 jury names). Sponsor variant for sponsor track, organizer variant naming edition ownership and retained sponsorship revenue for organizer track. | Day-11 follow-up sent 2026-09-23: sponsor-track template, updated Cannes facts (Apr 6-7 2027 Palais des Festivals; Agnes Jaoui jury president, Roger Avary, Elsa Zylberstein; Gong Li dropped from 2027 jury claim per Section 23 correction). Follow-up msgid 1a0cdd6d89a0684b.
A44: 2026-09-03 | B44: Fractal Analytics | C44: Form | D44: https://fractal.ai/contact-us/ | F44: WAIFF India x Fractal Analytics — AI Cinema Partnership | G44: N | H44: N | J44: N | K44: N | L44: N | M44: N | O44: Form submitted | P44: Business Opportunity form submitted 3 Sep 2026, reply-to adiup394@gmail.com. Note: message field had a stray phone-number prefix due to a form-fill glitch, rest of message intact. | Status normalised 6 Sep: this is a FORM row that read "Sent". Form was submitted 3 Sep. Do not re-fill.
A45: 2026-09-03 | B45: AMD | C45: Form | D45: https://www.amd.com/en/forms/solutions-inquiry/media-and-entertainment.html | F45: AMD Media & Entertainment Solutions Inquiry | G45: N | H45: N | J45: N | K45: N | L45: N | M45: N | O45: Draft ready - needs manual CAPTCHA | P45: All fields filled (name/title/company/email/phone/message) 3 Sep 2026 but the form has a reCAPTCHA gate - Claude does not complete CAPTCHAs. Aditya needs to open the form, check the box, and click Submit himself. | MULTI-CHANNEL, not a duplicate: this is the AMD media-and-entertainment enquiry FORM (3 Sep, still needs manual CAPTCHA). The AMD EMAIL send is logged separately at row 102 (6 Sep). Count AMD once when reporting company totals.
A46: 2026-09-03 | B46: DNEG India | C46: Email | D46: info@dneg.com | E46: pr@dneg.com | F46: WAIFF India — an opportunity to organize and own the India edition | G46: N | H46: N | J46: Y - 2026-09-07 | K46: Y | L46: N | M46: N | O46: Sent | P46: Sent 3 Sep 2026 — Organizer track batch (media/VFX/exhibition pool). | DAY-4 FOLLOW-UP SENT 7 Sep. Carried genuinely new information: the verified sponsor roster (CapCut/ByteDance, MiniMax, JW Marriott Cannes, LOTTE, Morphic, Skolae) and the official tier benefits, both extracted from the WAiFF deck on 7 Sep. Several were also reframed from sponsor pitch to organizer/jury/masterclass conversation where that fit the company better. || Day 11 follow-up sent 2026-09-14: new-fact angle (Cannes 2027 flagship now fixed 6-7 Apr 2027 at Palais des Festivals, Road to Cannes selection model, 2026 jury names). Sponsor variant for sponsor track, organizer variant naming edition ownership and retained sponsorship revenue for organizer track. | Day-11 follow-up sent 2026-09-23: organizer-track template, updated Cannes facts (Apr 6-7 2027 Palais des Festivals; Agnes Jaoui jury president, Roger Avary, Elsa Zylberstein; Gong Li dropped from 2027 jury claim per Section 23 correction) + organizer license figures (EUR 50k fee / EUR 400k Global Partner upgrade). Follow-up msgid 1a0cdd6ee523dea3.
A47: 2026-09-03 | B47: Red Chillies Entertainment (Redchillies.vfx) | C47: Email | D47: business@redchillies.com | E47: press@redchillies.com | F47: WAIFF India — an opportunity to organize and own the India edition | G47: N | H47: N | J47: Y - 2026-09-07 | K47: Y | L47: N | M47: N | O47: Sent | P47: Sent 3 Sep 2026 — Organizer track batch (media/VFX/exhibition pool). | DAY-4 FOLLOW-UP SENT 7 Sep. Carried genuinely new information: the verified sponsor roster (CapCut/ByteDance, MiniMax, JW Marriott Cannes, LOTTE, Morphic, Skolae) and the official tier benefits, both extracted from the WAiFF deck on 7 Sep. Several were also reframed from sponsor pitch to organizer/jury/masterclass conversation where that fit the company better. || Day 11 follow-up sent 2026-09-14: new-fact angle (Cannes 2027 flagship now fixed 6-7 Apr 2027 at Palais des Festivals, Road to Cannes selection model, 2026 jury names). Sponsor variant for sponsor track, organizer variant naming edition ownership and retained sponsorship revenue for organizer track. | Day-11 follow-up sent 2026-09-23: organizer-track template, updated Cannes facts (Apr 6-7 2027 Palais des Festivals; Agnes Jaoui jury president, Roger Avary, Elsa Zylberstein; Gong Li dropped from 2027 jury claim per Section 23 correction) + organizer license figures (EUR 50k fee / EUR 400k Global Partner upgrade). Follow-up msgid 1a0cdd700604eec7.
A48: 2026-09-03 | B48: Applause Entertainment | C48: Email | D48: prasoon.garg@applause.adityabirla.com | E48: marketing@applause.adityabirla.com | F48: WAIFF India — an opportunity to organize and own the India edition | G48: N | H48: N | J48: Y - 2026-09-07 | K48: Y | L48: N | M48: N | O48: Sent | P48: Sent 3 Sep 2026 — Organizer track batch (media/VFX/exhibition pool). | DAY-4 FOLLOW-UP SENT 7 Sep. Carried genuinely new information: the verified sponsor roster (CapCut/ByteDance, MiniMax, JW Marriott Cannes, LOTTE, Morphic, Skolae) and the official tier benefits, both extracted from the WAiFF deck on 7 Sep. Several were also reframed from sponsor pitch to organizer/jury/masterclass conversation where that fit the company better. || Day 11 follow-up sent 2026-09-14: new-fact angle (Cannes 2027 flagship now fixed 6-7 Apr 2027 at Palais des Festivals, Road to Cannes selection model, 2026 jury names). Sponsor variant for sponsor track, organizer variant naming edition ownership and retained sponsorship revenue for organizer track. | Day-11 follow-up sent 2026-09-23: organizer-track template, updated Cannes facts (Apr 6-7 2027 Palais des Festivals; Agnes Jaoui jury president, Roger Avary, Elsa Zylberstein; Gong Li dropped from 2027 jury claim per Section 23 correction) + organizer license figures (EUR 50k fee / EUR 400k Global Partner upgrade). Follow-up msgid 1a0cdd7156ccd3ae.
A49: 2026-09-03 | B49: Mythri Movie Makers | C49: Email | D49: info@mythrimoviemakers.com | F49: WAIFF India — an opportunity to organize and own the India edition | G49: N | H49: N | J49: Y - 2026-09-07 | K49: Y | L49: N | M49: N | O49: Sent | P49: Sent 3 Sep 2026 — Organizer track batch (media/VFX/exhibition pool). | DAY-4 FOLLOW-UP SENT 7 Sep. Carried genuinely new information: the verified sponsor roster (CapCut/ByteDance, MiniMax, JW Marriott Cannes, LOTTE, Morphic, Skolae) and the official tier benefits, both extracted from the WAiFF deck on 7 Sep. Several were also reframed from sponsor pitch to organizer/jury/masterclass conversation where that fit the company better. || Day 11 follow-up sent 2026-09-14: new-fact angle (Cannes 2027 flagship now fixed 6-7 Apr 2027 at Palais des Festivals, Road to Cannes selection model, 2026 jury names). Sponsor variant for sponsor track, organizer variant naming edition ownership and retained sponsorship revenue for organizer track. | Day-11 follow-up sent 2026-09-23: organizer-track template, updated Cannes facts (Apr 6-7 2027 Palais des Festivals; Agnes Jaoui jury president, Roger Avary, Elsa Zylberstein; Gong Li dropped from 2027 jury claim per Section 23 correction) + organizer license figures (EUR 50k fee / EUR 400k Global Partner upgrade). Follow-up msgid 1a0cdd728334c502.
A50: 2026-09-03 | B50: Wizcraft International Entertainment | C50: Email | D50: info@wizcraft.co | F50: WAIFF India — an opportunity to organize and own the India edition | G50: N | H50: N | J50: Y - 2026-09-07 | K50: Y - 2026-09-14 | L50: N | M50: N | O50: Sent | P50: Sent 3 Sep 2026 — Organizer track batch (media/VFX/exhibition pool). | DAY-4 FOLLOW-UP SENT 7 Sep. Carried genuinely new information: the verified sponsor roster (CapCut/ByteDance, MiniMax, JW Marriott Cannes, LOTTE, Morphic, Skolae) and the official tier benefits, both extracted from the WAiFF deck on 7 Sep. Several were also reframed from sponsor pitch to organizer/jury/masterclass conversation where that fit the company better. || Day 11 follow-up sent 2026-09-14: new-fact angle (Cannes 2027 flagship now fixed 6-7 Apr 2027 at Palais des Festivals, Road to Cannes selection model, 2026 jury names). Sponsor variant for sponsor track, organizer variant naming edition ownership and retained sponsorship revenue for organizer track.
A51: 2026-09-03 | B51: Ramoji Film City | C51: Email | D51: info@ramojifilmcity.com | E51: avrao@ramojifilmcity.com | F51: WAIFF India — an opportunity to organize and own the India edition | G51: N | H51: N | J51: Y - 2026-09-07 | K51: Y - 2026-09-14 | L51: N | M51: N | O51: Sent | P51: Sent 3 Sep 2026 — Organizer track batch (media/VFX/exhibition pool). | DAY-4 FOLLOW-UP SENT 7 Sep. Carried genuinely new information: the verified sponsor roster (CapCut/ByteDance, MiniMax, JW Marriott Cannes, LOTTE, Morphic, Skolae) and the official tier benefits, both extracted from the WAiFF deck on 7 Sep. Several were also reframed from sponsor pitch to organizer/jury/masterclass conversation where that fit the company better. || Day 11 follow-up sent 2026-09-14: new-fact angle (Cannes 2027 flagship now fixed 6-7 Apr 2027 at Palais des Festivals, Road to Cannes selection model, 2026 jury names). Sponsor variant for sponsor track, organizer variant naming edition ownership and retained sponsorship revenue for organizer track.
A52: 2026-09-03 | B52: Lyca Productions | C52: Email | D52: info@lycaproductions.in | F52: WAIFF India — an opportunity to organize and own the India edition | G52: N | H52: N | J52: Y - 2026-09-07 | K52: Y - 2026-09-14 | L52: N | M52: N | O52: Sent | P52: Sent 3 Sep 2026 — Organizer track batch (media/VFX/exhibition pool). | DAY-4 FOLLOW-UP SENT 7 Sep. Carried genuinely new information: the verified sponsor roster (CapCut/ByteDance, MiniMax, JW Marriott Cannes, LOTTE, Morphic, Skolae) and the official tier benefits, both extracted from the WAiFF deck on 7 Sep. Several were also reframed from sponsor pitch to organizer/jury/masterclass conversation where that fit the company better. || Day 11 follow-up sent 2026-09-14: new-fact angle (Cannes 2027 flagship now fixed 6-7 Apr 2027 at Palais des Festivals, Road to Cannes selection model, 2026 jury names). Sponsor variant for sponsor track, organizer variant naming edition ownership and retained sponsorship revenue for organizer track.
A53: 2026-09-03 | B53: Prime Focus Technologies | C53: Email | D53: tshobhana@primefocustechnologies.com | F53: WAIFF India — an opportunity to organize and own the India edition | G53: N | H53: N | J53: Y - 2026-09-07 | K53: Y - 2026-09-14 | L53: N | M53: N | O53: Sent | P53: Sent 3 Sep 2026 — Organizer track batch (media/VFX/exhibition pool). | DAY-4 FOLLOW-UP SENT 7 Sep. Carried genuinely new information: the verified sponsor roster (CapCut/ByteDance, MiniMax, JW Marriott Cannes, LOTTE, Morphic, Skolae) and the official tier benefits, both extracted from the WAiFF deck on 7 Sep. Several were also reframed from sponsor pitch to organizer/jury/masterclass conversation where that fit the company better. || Day 11 follow-up sent 2026-09-14: new-fact angle (Cannes 2027 flagship now fixed 6-7 Apr 2027 at Palais des Festivals, Road to Cannes selection model, 2026 jury names). Sponsor variant for sponsor track, organizer variant naming edition ownership and retained sponsorship revenue for organizer track.
A54: 2026-09-03 | B54: NY VFXWAALA | C54: Email | D54: info@nyvfxwaala.com | F54: WAIFF India — an opportunity to organize and own the India edition | G54: N | H54: N | J54: Y - 2026-09-07 | K54: Y - 2026-09-14 | L54: N | M54: N | O54: Sent | P54: Sent 3 Sep 2026 — Organizer track batch (media/VFX/exhibition pool). | DAY-4 FOLLOW-UP SENT 7 Sep. Carried genuinely new information: the verified sponsor roster (CapCut/ByteDance, MiniMax, JW Marriott Cannes, LOTTE, Morphic, Skolae) and the official tier benefits, both extracted from the WAiFF deck on 7 Sep. Several were also reframed from sponsor pitch to organizer/jury/masterclass conversation where that fit the company better. || Day 11 follow-up sent 2026-09-14: new-fact angle (Cannes 2027 flagship now fixed 6-7 Apr 2027 at Palais des Festivals, Road to Cannes selection model, 2026 jury names). Sponsor variant for sponsor track, organizer variant naming edition ownership and retained sponsorship revenue for organizer track.
A55: 2026-09-03 | B55: Qube Cinema Technologies | C55: Email | D55: sales@qubecinema.com | F55: WAIFF India — an opportunity to organize and own the India edition | G55: N | H55: N | J55: Y - 2026-09-07 | K55: Y - 2026-09-14 | L55: N | M55: N | O55: Sent | P55: Sent 3 Sep 2026 — Organizer track batch (media/VFX/exhibition pool). | DAY-4 FOLLOW-UP SENT 7 Sep. Carried genuinely new information: the verified sponsor roster (CapCut/ByteDance, MiniMax, JW Marriott Cannes, LOTTE, Morphic, Skolae) and the official tier benefits, both extracted from the WAiFF deck on 7 Sep. Several were also reframed from sponsor pitch to organizer/jury/masterclass conversation where that fit the company better. || Day 11 follow-up sent 2026-09-14: new-fact angle (Cannes 2027 flagship now fixed 6-7 Apr 2027 at Palais des Festivals, Road to Cannes selection model, 2026 jury names). Sponsor variant for sponsor track, organizer variant naming edition ownership and retained sponsorship revenue for organizer track.
A56: 2026-09-13 | B56: Yash Raj Films | C56: Email (organizer track, V2 template) | D56: helpdesk@yashrajfilms.com | F56: Yash Raj Films x World AI Film Festival — India Organizer Opportunity | G56: N | H56: N | J56: Y - 2026-09-22 | M56: N | O56: Sent | P56: Aditya supplied real email (helpdesk@yashrajfilms.com) 13 Sep, superseding the earlier CAPTCHA-blocked form draft. Organizer-track pitch (€50k license / €400k Global Partner upgrade named per brief's organizer exception). MsgID 1a09be02faedf988 || DAY-4 FOLLOWUP sent 2026-09-22: two-line nudge, no new pitch, in-thread reply.
A57: 2026-09-03 | B57: Avid Technology | C57: Email | D57: partners@avid.com | F57: WAIFF India x Avid Technology — AI Cinema Partnership | G57: N | H57: N | J57: Y - 2026-09-07 | K57: Y - 2026-09-14 | L57: N | M57: N | O57: Sent | P57: Sent 3 Sep 2026 - Global enterprise/fresh candidate batch, sponsor track. | DAY-4 FOLLOW-UP SENT 7 Sep. Carried genuinely new information: the verified sponsor roster (CapCut/ByteDance, MiniMax, JW Marriott Cannes, LOTTE, Morphic, Skolae) and the official tier benefits, both extracted from the WAiFF deck on 7 Sep. Several were also reframed from sponsor pitch to organizer/jury/masterclass conversation where that fit the company better. || Day 11 follow-up sent 2026-09-14: new-fact angle (Cannes 2027 flagship now fixed 6-7 Apr 2027 at Palais des Festivals, Road to Cannes selection model, 2026 jury names). Sponsor variant for sponsor track, organizer variant naming edition ownership and retained sponsorship revenue for organizer track.
A58: 2026-09-03 | B58: Foundry | C58: Email | D58: info@foundry.com | F58: WAIFF India x Foundry — AI Cinema Partnership | G58: N | H58: N | J58: Y - 2026-09-07 | K58: Y - 2026-09-14 | L58: N | M58: N | O58: Sent | P58: Sent 3 Sep 2026 - Global enterprise/fresh candidate batch, sponsor track. | DAY-4 FOLLOW-UP SENT 7 Sep. Carried genuinely new information: the verified sponsor roster (CapCut/ByteDance, MiniMax, JW Marriott Cannes, LOTTE, Morphic, Skolae) and the official tier benefits, both extracted from the WAiFF deck on 7 Sep. Several were also reframed from sponsor pitch to organizer/jury/masterclass conversation where that fit the company better. || Day 11 follow-up sent 2026-09-14: new-fact angle (Cannes 2027 flagship now fixed 6-7 Apr 2027 at Palais des Festivals, Road to Cannes selection model, 2026 jury names). Sponsor variant for sponsor track, organizer variant naming edition ownership and retained sponsorship revenue for organizer track.
A59: 2026-09-03 | B59: Insta360 | C59: Email | D59: enterprise@insta360.com | F59: WAIFF India x Insta360 — AI Cinema Partnership | G59: N | H59: N | J59: Y - 2026-09-07 | K59: Y - 2026-09-14 | L59: N | M59: N | O59: Sent | P59: Sent 3 Sep 2026 - Global enterprise/fresh candidate batch, sponsor track. | DAY-4 FOLLOW-UP SENT 7 Sep. Carried genuinely new information: the verified sponsor roster (CapCut/ByteDance, MiniMax, JW Marriott Cannes, LOTTE, Morphic, Skolae) and the official tier benefits, both extracted from the WAiFF deck on 7 Sep. Several were also reframed from sponsor pitch to organizer/jury/masterclass conversation where that fit the company better. || Day 11 follow-up sent 2026-09-14: new-fact angle (Cannes 2027 flagship now fixed 6-7 Apr 2027 at Palais des Festivals, Road to Cannes selection model, 2026 jury names). Sponsor variant for sponsor track, organizer variant naming edition ownership and retained sponsorship revenue for organizer track.
A60: 2026-09-03 | B60: Envato | C60: Email | D60: business@envato.com | F60: Partnering with WAiFF India — Envato x World AI Film Festival | G60: N | H60: N | J60: Y - 2026-09-07 | K60: Y - 2026-09-14 | L60: N | M60: N | O60: Sent | P60: Elements/stock-content + AI creative tools company. Sent to business@envato.com (business inquiries address). Gmail id 1a0689153454235e. | DAY-4 FOLLOW-UP SENT 7 Sep. Carried genuinely new information: the verified sponsor roster (CapCut/ByteDance, MiniMax, JW Marriott Cannes, LOTTE, Morphic, Skolae) and the official tier benefits, both extracted from the WAiFF deck on 7 Sep. Several were also reframed from sponsor pitch to organizer/jury/masterclass conversation where that fit the company better. || Day 11 follow-up sent 2026-09-14: new-fact angle (Cannes 2027 flagship now fixed 6-7 Apr 2027 at Palais des Festivals, Road to Cannes selection model, 2026 jury names). Sponsor variant for sponsor track, organizer variant naming edition ownership and retained sponsorship revenue for organizer track.
A61: 2026-09-03 | B61: Moonvalley AI | C61: Form | D61: https://moonvalley.com/partner-with-us | F61: N/A — web form | G61: N | H61: N | J61: N | K61: N | L61: N | M61: N | O61: Form submitted | P61: Genuine "Partner with us" form (studios/directors/filmmakers/agencies/advertisers/brands). Filled Name, Email, Organization, and message covering WAiFF scale + Moonvalley's licensed-data Marey model + CAA/Comcast Ventures funding. Confirmed "Thank you! You have successfully submitted." 3 Sep 2026. | Status normalised 6 Sep: this is a FORM row that read "Sent". Form was submitted 3 Sep. Do not re-fill.
A62: 2026-09-03 | B62: GoPro | C62: Email | D62: Sponsor@gopro.com | F62: Partnering with WAiFF India — GoPro x World AI Film Festival | G62: Y | H62: N | J62: N | K62: N | L62: N | M62: N | O62: Bounced | P62: Sponsor@gopro.com bounced 3 Sep — "address couldn't be found." The address was real (verified via GoPro's own X/Twitter reply) but appears defunct now. Not counted as a landed send. Needs a fresh channel if pursued again.
A63: 2026-09-03 | B63: Christie Digital | C63: Email | D63: pr@christiedigital.com | F63: Partnering with WAiFF India — Christie x World AI Film Festival | G63: N | H63: N | J63: Y - 2026-09-07 | K63: Y - 2026-09-14 | L63: N | M63: N | O63: Sent | P63: Christie's own site explicitly labels this "Public Relations or sponsorship" contact — qualifies as sponsorship-typed. Cinema projection technology company, directly relevant to festival exhibition. Gmail id 1a068a58e2898876. | DAY-4 FOLLOW-UP SENT 7 Sep. Carried genuinely new information: the verified sponsor roster (CapCut/ByteDance, MiniMax, JW Marriott Cannes, LOTTE, Morphic, Skolae) and the official tier benefits, both extracted from the WAiFF deck on 7 Sep. Several were also reframed from sponsor pitch to organizer/jury/masterclass conversation where that fit the company better. || Day 11 follow-up sent 2026-09-14: new-fact angle (Cannes 2027 flagship now fixed 6-7 Apr 2027 at Palais des Festivals, Road to Cannes selection model, 2026 jury names). Sponsor variant for sponsor track, organizer variant naming edition ownership and retained sponsorship revenue for organizer track.
A64: 2026-09-04 | B64: D-ID | C64: Email | D64: sarah.schloss@headline.media | F64: Partnership Opportunity with WAIFF India — D-ID x World AI Film Festival | G64: N | H64: N | J64: Y | K64: Y - 2026-09-22 | L64: N | M64: N | O64: Sent | P64: || DAY-11 FOLLOWUP sent 2026-09-22: new fact (Buenos Aires + Montreal/Vancouver Oct 2026 editions confirmed), in-thread reply.
A65: 2026-09-04 | B65: Krea AI | C65: Email | D65: press@krea.ai | F65: Partnership Opportunity with WAIFF India — Krea AI x World AI Film Festival | G65: Y | H65: N | J65: N | K65: N | L65: N | M65: N | O65: Bounced | P65: press@krea.ai bounced despite being decoded from official press page — Cloudflare-obfuscated address decode may have been imperfect, or inbox retired.
A66: 2026-09-04 | B66: Character.AI | C66: Email | D66: press@character.ai | F66: Partnership Opportunity with WAIFF India — Character.AI x World AI Film Festival | G66: N | H66: N | J66: Y | K66: Y - 2026-09-22 | L66: N | M66: N | O66: Sent | P66: || DAY-11 FOLLOWUP sent 2026-09-22: new fact (Buenos Aires + Montreal/Vancouver Oct 2026 editions confirmed), in-thread reply.
A67: 2026-09-04 | B67: CoRover | C67: Email | D67: chat@CoRover.ai | F67: Partnership Opportunity with WAIFF India — CoRover x World AI Film Festival | G67: N | H67: N | J67: Y | K67: Y - 2026-09-22 | L67: N | M67: N | O67: Sent | P67: || DAY-11 FOLLOWUP sent 2026-09-22: new fact (Buenos Aires + Montreal/Vancouver Oct 2026 editions confirmed), in-thread reply.
A68: 2026-09-04 | B68: Haptik (Jio Haptik) | C68: Email | D68: enterprise@haptik.ai | F68: Partnership Opportunity with WAIFF India — Haptik x World AI Film Festival | G68: N | H68: N | J68: Y | K68: Y - 2026-09-22 | L68: N | M68: N | O68: Sent | P68: || DAY-11 FOLLOWUP sent 2026-09-22: new fact (Buenos Aires + Montreal/Vancouver Oct 2026 editions confirmed), in-thread reply.
A69: 2026-09-04 | B69: FICCI (Media & Entertainment / FRAMES) | C69: Email | D69: Garima.singh@ficci.com | F69: WAIFF India x FICCI FRAMES — an AI cinema collaboration for the September edition | G69: N | H69: N | J69: Y | K69: N | L69: N | M69: N | O69: Sent
A70: 2026-09-04 | B70: JioStar (Jio Studios/Reliance Entertainment) | C70: Email | D70: hello@jiostar.com | F70: WAIFF India — an opportunity to organize and own the India edition | G70: N | H70: N | J70: Y | K70: N | L70: N | M70: N | O70: Sent
A71: 2026-09-04 | B71: Zee Entertainment Enterprises | C71: Email | D71: media@zee.com | F71: WAIFF India — partnership query for Zee Studios / Zee Entertainment | G71: N | H71: N | J71: Y | K71: Y - 2026-09-22 | L71: N | M71: N | O71: Sent | P71: || 2026-09-22: Day-11 follow-up attempted but BLOCKED by platform safety filter before send (reason: "Real-World Transactions" - likely an automatic caution given ZEE5 is on the do-not-contact list and Zee Entertainment is its parent company). NOT sent. Aditya should decide personally whether to contact Zee Entertainment directly given the ZEE5 exclusion, and send this follow-up himself if he wants to proceed. || 2026-09-22: Day-11 follow-up sent (retried after Aditya explicitly confirmed to proceed despite the earlier platform block). New fact: Buenos Aires + Montreal/Vancouver Oct 2026 editions.
A72: 2026-09-04 | B72: Dharma Productions | C72: Email | D72: marketing@dharma-production.com | F72: WAIFF India — an opportunity to organize and own the India edition | G72: N | H72: N | J72: Y | K72: Y - 2026-09-22 | L72: N | M72: N | O72: Sent | P72: || DAY-11 FOLLOWUP sent 2026-09-22: new fact (Buenos Aires + Montreal/Vancouver Oct 2026 editions confirmed), in-thread reply.
A73: 2026-09-04 | B73: IIFA (International Indian Film Academy) | C73: Form | D73: iifa.com/contact/ (Partnerships desk — Brand Collaboration) | F73: N/A — form submission, not email | G73: N | H73: N | J73: N/A - form channel, no email to follow up | K73: N | L73: N | M73: N | O73: Form submitted | P73: Confirmed: "Thank you. Your enquiry has been sent to the IIFA team." | Status normalised 6 Sep: this is a FORM row that read "Sent". Submission confirmed 4 Sep with an on-screen acknowledgement from the IIFA team. Do not re-fill.
A74: 2026-09-04 | B74: NFDC (National Film Development Corporation) / WAVES Film Bazaar | C74: Email | D74: coproduction@nfdcindia.com | F74: WAIFF India Edition — a possible collaboration with NFDC | G74: N | H74: N | J74: Y | K74: Y - 2026-09-22 | L74: N | M74: N | O74: Sent | P74: Government/Institutional track || DAY-11 FOLLOWUP sent 2026-09-22: new fact (Buenos Aires + Montreal/Vancouver Oct 2026 editions confirmed), in-thread reply.
A75: 2026-09-04 | B75: Maharashtra Film, Stage & Cultural Development Corporation (Film City Mumbai) | C75: Email | D75: contact.filmcell@maharashtra.gov.in | F75: WAIFF India Edition, Mumbai (Dec 2026) — exploring Maharashtra Film City as a venue partner | G75: N | H75: N | J75: Y | K75: Y - 2026-09-22 | L75: N | M75: N | O75: Sent | P75: Government/Institutional track || DAY-11 FOLLOWUP sent 2026-09-22: new fact (Buenos Aires + Montreal/Vancouver Oct 2026 editions confirmed), in-thread reply.
A76: 2026-09-06 | B76: Four Seasons Hotel Mumbai | C76: Email | D76: agatha.gomes@fourseasons.com | F76: WAiFF x Four Seasons Hotel Mumbai — India, this December | G76: N | H76: N | J76: Y | K76: Y | L76: N | M76: N | O76: Sent | P76: Relevance: Premium venue with a luxury-events sales lead named directly on the hotel's own press page | Day-11 follow-up sent 2026-09-23: sponsor-track template, updated Cannes facts (Apr 6-7 2027 Palais des Festivals; Agnes Jaoui jury president, Roger Avary, Elsa Zylberstein). Follow-up msgid 1a0cddbd35ecb913.
A77: 2026-09-06 | B77: Taj Hotels (IHCL) | C77: Email | D77: meetings@ihcltata.com | F77: an AI film festival, Taj Hotels | G77: N | H77: N | J77: Y | K77: Y | L77: N | M77: N | O77: Sent | P77: Relevance: India's most recognized hospitality brand, dedicated events inbox | Day-11 follow-up sent 2026-09-23: sponsor-track template, updated Cannes facts (Apr 6-7 2027 Palais des Festivals; Agnes Jaoui jury president, Roger Avary, Elsa Zylberstein). Follow-up msgid 1a0cddbe58e09de2.
A78: 2026-09-06 | B78: ITC Hotels | C78: Email | D78: reservations@itchotels.com | F78: ITC Hotels — a Cannes-born festival lands in Mumbai | G78: N | H78: N | J78: Y | K78: Y | L78: N | M78: N | O78: Sent | P78: Relevance: Major Indian hospitality group with dedicated event infrastructure | Day-11 follow-up sent 2026-09-23: sponsor-track template, updated Cannes facts (Apr 6-7 2027 Palais des Festivals; Agnes Jaoui jury president, Roger Avary, Elsa Zylberstein). Follow-up msgid 1a0cddbf7497246a.
A79: 2026-09-06 | B79: Grand Hyatt Mumbai | C79: Email | D79: sales.ghmumbai@hyatt.com | E79: mumgh.snm@hyatt.com | F79: WAiFF's India launch — Grand Hyatt Mumbai fit? | G79: N | H79: N | J79: Y | K79: Y | L79: N | M79: N | O79: Sent | P79: Relevance: Premium Mumbai venue with two dedicated sales/events addresses | Day-11 follow-up sent 2026-09-23: sponsor-track template, updated Cannes facts (Apr 6-7 2027 Palais des Festivals; Agnes Jaoui jury president, Roger Avary, Elsa Zylberstein). Follow-up msgid 1a0cddc09a77e181.
A80: 2026-09-06 | B80: JW Marriott Mumbai Sahar | C80: Form | D80: https://www.marriott.com/en-us/hotels/bomsa-jw-marriott-mumbai-sahar/events/ | F80: WAiFF x JW Marriott Mumbai Sahar — India, this December | G80: N | H80: N | J80: N/A - form channel, no email to follow up | K80: N | L80: N | M80: N | O80: Excluded - already contacted by partner | P80: Relevance: Major Marriott property near the airport, active events business | DO NOT CONTACT. Aditya confirmed 6 Sep that his other partner has already reached out to JW Marriott Mumbai Sahar. Form deliberately NOT filled. Any future batch must exclude this company to avoid a duplicate approach from two people.
A81: 2026-09-06 | B81: Dabur India | C81: Email | D81: corpcomm@dabur.com | F81: an AI film festival, Dabur India | G81: N | H81: N | J81: Y | K81: Y | L81: N | M81: N | O81: Sent | P81: Relevance: One of India's largest FMCG houses with a long history of cultural sponsorships | Day-11 follow-up sent 2026-09-23: sponsor-track template, updated Cannes facts (Apr 6-7 2027 Palais des Festivals; Agnes Jaoui jury president, Roger Avary, Elsa Zylberstein). Follow-up msgid 1a0cddc1969e147a.
A82: 2026-09-06 | B82: Paper Boat (Hector Beverages) | C82: Email | D82: paperboat@hectorbeverages.com | F82: Paper Boat — a Cannes-born festival lands in Mumbai | G82: N | H82: N | J82: Y | K82: Y | L82: N | M82: N | O82: Sent | P82: Relevance: Experiential-marketing-native beverage brand, natural fit for a festival activation | Day-11 follow-up sent 2026-09-23: sponsor-track template, updated Cannes facts (Apr 6-7 2027 Palais des Festivals; Agnes Jaoui jury president, Roger Avary, Elsa Zylberstein). Follow-up msgid 1a0cddc2adc49ab8.
A83: 2026-09-06 | B83: PhonePe | C83: Email | D83: pr@phonepe.com | F83: WAiFF x PhonePe — India, this December | G83: N | H83: N | J83: Y | K83: Y | L83: N | M83: N | O83: Sent | P83: Relevance: India's largest UPI player, strong brand-visibility appetite | AUDIT FINDING (6 Sep Gmail check): this pitch was sent to PhonePe 3 times within ~15 min (14:06, 14:17, 14:22 IST) — a duplicate-send error, not 3 separate outreaches. Treat as ONE real send. | Day-11 follow-up sent 2026-09-23: sponsor-track template, updated Cannes facts (Apr 6-7 2027 Palais des Festivals; Agnes Jaoui jury president, Roger Avary, Elsa Zylberstein). Follow-up msgid 1a0cddc3b920a86c.
A84: 2026-09-06 | B84: SonyLIV (Culver Max Entertainment) | C84: Form | D84: https://advertisewithus.sonyliv.com/ | F84: WAiFF x SonyLIV — India, this December | G84: N | H84: N | J84: N/A - form channel, no email to follow up | K84: N | L84: N | M84: N | O84: Draft ready | P84: Relevance: Major Indian OTT platform, natural distribution/organizer angle
A85: 2026-09-06 | B85: hoichoi | C85: Email | D85: support@hoichoi.tv | F85: an AI film festival, hoichoi | G85: N | H85: N | J85: Y | K85: N | L85: N | M85: N | O85: Sent | P85: Relevance: Fast-growing regional OTT platform with a named partnerships routing | AUDIT FINDING (6 Sep Gmail check): this pitch was sent to hoichoi 3 times within ~15 min, and hoichoi auto-replied each time asking to email sayantan.guha@hoichoi.tv directly instead of support@hoichoi.tv. Wrong-channel — needs a fresh, single send to sayantan.guha@hoichoi.tv.
A86: 2026-09-06 | B86: IndiaAI Mission (MeitY) | C86: Email | D86: impactsummit-events@indiaai.gov.in | E86: impactsummit-comms@indiaai.gov.in | F86: IndiaAI Mission — a Cannes-born festival lands in Mumbai | G86: N | H86: N | J86: Y | K86: N | L86: N | M86: N | O86: Sent | P86: Relevance: India's flagship government AI initiative — direct institutional-partner analog for an AI film festival | AUDIT FINDING (6 Sep Gmail check): this pitch was sent to IndiaAI Mission 3 times within ~15 min (14:07, 14:18, 14:22 IST) — a duplicate-send error, not 3 separate outreaches. Treat as ONE real send.
A87: 2026-09-06 | B87: CBFC (Central Board of Film Certification) | C87: Email | D87: romum.cbfc@nic.in | E87: chairperson.cbfc@nic.in,ceo.cbfc@nic.in | F87: WAiFF's India launch — CBFC fit? | G87: N | H87: N | J87: Y | K87: N | L87: N | M87: N | O87: Sent | P87: Relevance: India's film certification authority — institutional legitimacy for an AI-generated-film festival | AUDIT FINDING (6 Sep Gmail check): this pitch was sent to CBFC 3 times within ~15 min (14:07, 14:18, 14:23 IST) — a duplicate-send error, not 3 separate outreaches. Treat as ONE real send.
A88: 2026-09-06 | B88: FTII (Film and Television Institute of India) | C88: Email | D88: registrar@ftii.ac.in | E88: vc@ftii.ac.in | F88: WAiFF x FTII — India, this December | G88: N | H88: N | J88: Y | K88: N | L88: N | M88: N | O88: Sent | P88: Relevance: India's premier film school — a natural jury/masterclass/academic-partner pipeline
A89: 2026-09-06 | B89: SRFTI (Satyajit Ray Film and Television Institute) | C89: Email | D89: contact@srfti.ac.in | E89: dean.edm@srfti.ac.in | F89: an AI film festival, SRFTI | G89: N | H89: N | J89: Y | K89: N | L89: N | M89: N | O89: Sent | P89: Relevance: Leading Indian film institute with a digital-media specialization closest to AI filmmaking
A90: 2026-09-06 | B90: Startup Mahakumbh (FICCI / DPIIT) | C90: Email | D90: akshay.jain@ficci.com | F90: Startup Mahakumbh — a Cannes-born festival lands in Mumbai | G90: N | H90: N | J90: Y | K90: N | L90: N | M90: N | O90: Sent | P90: Relevance: Government-linked flagship startup platform, real named contact
A91: 2026-09-06 | B91: Maharashtra Directorate of Tourism | C91: Email | D91: diot@maharashtratourism.gov.in | F91: WAiFF's India launch — Maharashtra Directorate of Tourism fit? | G91: N | H91: N | J91: Y | K91: N | L91: N | M91: N | O91: Sent | P91: Relevance: State-government culture/tourism channel for an India-launch story based in Mumbai
A92: 2026-09-06 | B92: Anthropic | C92: Email | D92: press@anthropic.com | F92: WAiFF x Anthropic — India, this December | G92: N | H92: Y | I92: 2026-09-14 | J92: Y | K92: N | L92: N | M92: N | O92: Replied - needs review | P92: Relevance: Leading AI lab, natural thought-leadership fit for an AI film festival || A reply arrived 2026-09-14 from patrick@150bond.com on this thread - unusual domain for Anthropic (150bond.com, not anthropic.com), possibly a PR/agency contact or a misdirected reply. FLAG: verify before treating as a genuine Anthropic response.
A93: 2026-09-06 | B93: Mistral AI | C93: Email | D93: press@mistral.ai | F93: an AI film festival, Mistral AI | G93: N | H93: N | J93: Y | K93: Y | L93: N | M93: N | O93: Sent | P93: Relevance: Major European AI lab with an events-scoped contact channel | Day-11 follow-up sent 2026-09-23: sponsor-track template, updated Cannes facts (Apr 6-7 2027 Palais des Festivals; Agnes Jaoui jury president, Roger Avary, Elsa Zylberstein). Follow-up msgid 1a0cddc4b6fac086.
A94: 2026-09-06 | B94: Hugging Face | C94: Email | D94: press@huggingface.co | F94: Hugging Face — a Cannes-born festival lands in Mumbai | G94: N | H94: N | J94: Y | K94: Y | L94: N | M94: N | O94: Sent | P94: Relevance: The hub many AI filmmaking tools are built on top of | Day-11 follow-up sent 2026-09-23: sponsor-track template, updated Cannes facts (Apr 6-7 2027 Palais des Festivals; Agnes Jaoui jury president, Roger Avary, Elsa Zylberstein). Follow-up msgid 1a0cddc5d518e008.
A95: 2026-09-06 | B95: Magnific AI (Freepik) | C95: Email | D95: pr@magnific.com | F95: WAiFF's India launch — Magnific AI fit? | G95: N | H95: N | J95: Y | K95: Y | L95: N | M95: N | O95: Sent | P95: Relevance: AI upscaling/creative tool with a formal, named partner program — the strongest-typed match in this batch | Day-11 follow-up sent 2026-09-23: sponsor-track template, updated Cannes facts (Apr 6-7 2027 Palais des Festivals; Agnes Jaoui jury president, Roger Avary, Elsa Zylberstein). Follow-up msgid 1a0cddc6cf8bb2dd.
A96: 2026-09-06 | B96: Deepgram | C96: Form | D96: https://deepgram.com/partners | F96: WAiFF x Deepgram — India, this December | G96: N | H96: N | J96: N/A - form channel, no email to follow up | K96: N | L96: N | M96: N | O96: Draft ready | P96: Relevance: Voice-AI infra vendor relevant to AI film sound/dubbing
A97: 2026-09-06 | B97: AssemblyAI | C97: Form | D97: https://www.assemblyai.com/contact/sales | F97: an AI film festival, AssemblyAI | G97: N | H97: N | J97: N/A - form channel, no email to follow up | K97: N | L97: N | M97: N | O97: Closed - company declined | P97: Relevance: Speech recognition/AI infra relevant to AI film production pipelines | Do NOT fill this form. AssemblyAI already declined by email on 5 Sep, twice, stating they do not evaluate festival, sponsorship or partnership proposals through any channel. Filling the sales form would be a re-approach after a firm no.
A98: 2026-09-06 | B98: Replicate | C98: Form | D98: https://replicate.com/enterprise | F98: Replicate — a Cannes-born festival lands in Mumbai | G98: N | H98: N | J98: N/A - form channel, no email to follow up | K98: N | L98: N | M98: N | O98: Draft ready | P98: Relevance: Infrastructure layer for AI creative tooling
A99: 2026-09-06 | B99: Leonardo AI | C99: Form | D99: https://leonardo.ai/contact-us | F99: WAiFF's India launch — Leonardo AI fit? | G99: N | H99: N | J99: N/A - form channel, no email to follow up | K99: N | L99: N | M99: N | O99: Draft ready | P99: Relevance: AI creative tool with growing enterprise reach
A100: 2026-09-06 | B100: Krikey AI | C100: Email | D100: support@krikey.com | F100: WAiFF x Krikey AI — India, this December | G100: N | H100: N | J100: Y | K100: Y | L100: N | M100: N | O100: Sent | P100: Relevance: AI animation/mocap tool, direct filmmaking-adjacent fit | Day-11 follow-up sent 2026-09-23: sponsor-track template, updated Cannes facts (Apr 6-7 2027 Palais des Festivals; Agnes Jaoui jury president, Roger Avary, Elsa Zylberstein). Follow-up msgid 1a0cddc7d10b107e.
...

Sheet Sponsor Follow-ups
A1: WAIFF India — Sponsor Follow-ups
A2: Sponsor track only. One row per company: contact, reply status, and the Day 4 / 11 / 25 follow-up cadence (brief section 10). Row 4 is an example — real rows start at row 5.
A3: # | B3: Company | C3: Contact Name | D3: Contact Title | E3: Channel | F3: Date First Contacted | G3: Reply Received? (Y/N) | H3: Reply Date | I3: What They Said | J3: Day 4 Follow-up (Y/N) | K3: Day 11 Follow-up (Y/N) | L3: Day 25 Follow-up (Y/N) | M3: Status | N3: Notes
A4: 0 | B4: Example Co | C4: Jane Doe | D4: Head of Partnerships | E4: Email | F4: 2026-09-03 | G4: N | J4: N | K4: N | L4: N | M4: Sent | N4: EXAMPLE ROW — edit or delete, do not count as real data
A5: 1 | B5: Radisson Blu | E5: Email | F5: 2026-09-01 | G5: Y | H5: 2026-09-03 | I5: Call held 3 Sep. Anuj is interested in the India edition but needs more lucrative/concrete details before he can move it forward internally — guest/talent finalization and similar specifics. He said he will push it to his internal team and MDs. Per Aditya: hold the reply until India-edition details are firmer; keep him warm, do not send a substantive reply yet. | J5: N | K5: N | L5: N | M5: Warm - awaiting more India-edition detail from Aditya before next reply | N5: Sent before this tracker existed — backfilled from Gmail search 3 Sep 2026. Anuj Kumar (Marketing Manager, South Asia) asked 3 specific questions before a call. Replied 3 Sep 2026: covered India edition (Dec 2026, Mumbai), JW Marriott Cannes as existing global sponsor, what Radisson gets (network-wide visibility, access, association) and what WAiFF needs (VIP accommodation/hosting, brand partner role, not just venue). No Canva/deck link sent per standing rule. Asked for a call after 2 PM IST. Awaiting reply.
A6: 2 | B6: EPAM Systems | E6: Email | F6: 2026-09-01 | G6: Y | H6: 2026-09-02 | I6: Suggested speaking after the 9th; looping in colleague Sameena Ali to help set something up. | J6: N | K6: N | L6: N | M6: Awaiting scheduling after 9th | N6: Sent before this tracker existed — backfilled from Gmail search 3 Sep 2026. Nandini Bhatnagar (Sr Director Marketing) wants to talk after Sept 9. Replied 3 Sep 2026 confirming availability anytime after 12:00 PM IST, around 4:00 PM IST or later. Awaiting her scheduling reply.
A7: 3 | B7: Adani Digital Labs | E7: Email | F7: 2026-09-02 | G7: N | J7: N | K7: N | L7: N | M7: Bounced | N7: Sent before this tracker existed — backfilled from Gmail search 3 Sep 2026. BOUNCE: 4 of 8 BCC addresses bounced (cgarg@adanidigitallabs.com, hrishik.jethi@adani.com, manishsingh.payal@adani.com, digitallabs@adani.com)
A8: 4 | B8: Adani AI Labs | E8: Email | F8: 2026-09-02 | G8: N | J8: N | K8: N | L8: N | M8: Bounced | N8: Sent before this tracker existed — backfilled from Gmail search 3 Sep 2026. BOUNCE: 1 of 4 BCC addresses bounced (tanushyam.chattopadhyay@adani.com); also sent separately to Shalini Singh direct
A9: 5 | B9: Freshworks | E9: Email | F9: 2026-09-02 | G9: N | J9: N | K9: N | L9: N | M9: Sent | N9: Sent before this tracker existed — backfilled from Gmail search 3 Sep 2026. Automated support-ticket confirmation only — not a personal reply, no action needed yet
A10: 6 | B10: Zoho | E10: Email | F10: 2026-09-02 | G10: Y | H10: 2026-09-03 | I10: Sales team gave generic product info; partner-operations team pointed to zoho.com/partners as the standard partner program, not a direct sponsorship conversation. | J10: N | K10: N | L10: N | M10: Low priority - generic partner program, not a real lead | N10: Sent before this tracker existed — backfilled from Gmail search 3 Sep 2026. Automated partner-ticket confirmation + generic sales-team reply — not personalized, no action needed yet
A11: 7 | B11: Myntra | E11: Email | F11: 2026-09-02 | G11: N | J11: N | K11: N | L11: N | M11: Bounced | N11: Sent before this tracker existed — backfilled from Gmail search 3 Sep 2026. BOUNCE: Address not found (bounced) — only address used, no BCC alternates
A12: 8 | B12: Tech Mahindra | E12: Email | F12: 2026-09-02 | G12: N | J12: N | K12: N | L12: N | M12: Sent | N12: Sent before this tracker existed — backfilled from Gmail search 3 Sep 2026.
A13: 9 | B13: BenQ India | E13: Email | F13: 2026-09-02 | G13: N | J13: N | K13: N | L13: N | M13: Sent | N13: Sent before this tracker existed — backfilled from Gmail search 3 Sep 2026.
A14: 10 | B14: Sennheiser | E14: Email | F14: 2026-09-02 | G14: N | J14: N | K14: N | L14: N | M14: Sent | N14: Sent before this tracker existed — backfilled from Gmail search 3 Sep 2026.
A15: 11 | B15: Runway | C15: Michelle Kwon | D15: Head of Operations and Partnerships | E15: Email | F15: 2026-09-03 | G15: N | J15: N | K15: N | L15: N | M15: Sent | N15: Sent 3 Sep 2026 — Batch 1 (60), Target Batch 2 research.
A16: 12 | B16: Genmo | C16: Paras Jain | D16: Genmo (title unconfirmed) | E16: Email | F16: 2026-09-03 | G16: N | J16: N | K16: N | L16: N | M16: Sent | N16: Sent 3 Sep 2026 — Batch 1 (60), Target Batch 2 research.
A17: 13 | B17: Shengshu Technology (Vidu) | E17: Email | F17: 2026-09-03 | G17: N | J17: N | K17: N | L17: N | M17: Sent | N17: Sent 3 Sep 2026 — Batch 1 (60), Target Batch 2 research.
A18: 14 | B18: ElevenLabs | E18: Email | F18: 2026-09-03 | G18: N | J18: N | K18: N | L18: N | M18: Sent | N18: Sent 3 Sep 2026 — Batch 1 (60), Target Batch 2 research.
A19: 15 | B19: Murf AI | E19: Email | F19: 2026-09-03 | G19: N | J19: N | K19: N | L19: N | M19: Sent | N19: Sent 3 Sep 2026 — Batch 1 (60), Target Batch 2 research.
A20: 16 | B20: NeuralGarage | E20: Email | F20: 2026-09-03 | G20: N | J20: N | K20: N | L20: N | M20: Sent | N20: Sent 3 Sep 2026 — Batch 1 (60), Target Batch 2 research.
A21: 17 | B21: Synthesia | E21: Email | F21: 2026-09-03 | G21: N | J21: N | K21: N | L21: N | M21: Sent | N21: Sent 3 Sep 2026 — Batch 1 (60), Target Batch 2 research.
A22: 18 | B22: OpusClip (Opus.pro) | E22: Email | F22: 2026-09-03 | G22: N | J22: N | K22: N | L22: N | M22: Sent | N22: Sent 3 Sep 2026 — Batch 1 (60), Target Batch 2 research.
A23: 19 | B23: Captions (Mirage) | E23: Email | F23: 2026-09-03 | G23: N | J23: N | K23: N | L23: N | M23: Sent | N23: Sent 3 Sep 2026 — Batch 1 (60), Target Batch 2 research.
A24: 20 | B24: Topaz Labs | C24: Ross Shain | D24: Principal Creative Technologist | E24: Email | F24: 2026-09-03 | G24: N | J24: N | K24: N | L24: N | M24: Sent | N24: Sent 3 Sep 2026 — Batch 1 (60), Target Batch 2 research.
A25: 21 | B25: Black Forest Labs | E25: Email | F25: 2026-09-03 | G25: N | J25: N | K25: N | L25: N | M25: Sent | N25: Sent 3 Sep 2026 — Batch 1 (60), Target Batch 2 research.
A26: 22 | B26: Stability AI | E26: Email | F26: 2026-09-03 | G26: N | J26: N | K26: N | L26: N | M26: Sent | N26: Sent 3 Sep 2026 — Batch 1 (60), Target Batch 2 research.
A27: 23 | B27: NVIDIA | C27: Parthajit Sar | D27: Marketing programs | E27: Email | F27: 2026-09-03 | G27: Y | H27: 2026-09-03 | I27: Asked for 2025 highlights and public data points before internal review. Replied with verified figures (6,000+ applications/100+ countries 2026, leadership names, global footprint, press coverage), all cross-checked against worldaifilmfestival.com and independent press. | J27: N | K27: N | L27: N | M27: Awaiting internal review, ~2 weeks | N27: Sent 3 Sep 2026 — Batch 1 (60), Target Batch 2 research.
A28: 24 | B28: Qualcomm | C28: Sumit Sonal | D28: Head of Marketing, Qualcomm India | E28: Email | F28: 2026-09-03 | G28: N | J28: N | K28: N | L28: N | M28: Sent | N28: Sent 3 Sep 2026 — Batch 1 (60), Target Batch 2 research.
A29: 25 | B29: Sony India | C29: Nimit Jain | D29: Marketing Communications Head | E29: Email | F29: 2026-09-03 | G29: N | J29: N | K29: N | L29: N | M29: Sent | N29: Sent 3 Sep 2026 — Batch 1 (60), Target Batch 2 research.
A30: 26 | B30: Harman International (JBL) | E30: Email | F30: 2026-09-03 | G30: N | J30: N | K30: N | L30: N | M30: Sent | N30: Sent 3 Sep 2026 — Batch 1 (60), Target Batch 2 research.
A31: 27 | B31: Zebronics | C31: Mansi Sharma | D31: Regional Marketing Manager | E31: Email | F31: 2026-09-03 | G31: N | J31: N | K31: N | L31: N | M31: Sent | N31: Sent 3 Sep 2026 — Batch 1 (60), Target Batch 2 research.
A32: 28 | B32: Dell Technologies India | E32: Email | F32: 2026-09-03 | G32: N | J32: N | K32: N | L32: N | M32: Sent | N32: Sent 3 Sep 2026 — Batch 1 (60), Target Batch 2 research.
A33: 29 | B33: ASUS India | E33: Email | F33: 2026-09-03 | G33: N | J33: N | K33: N | L33: N | M33: Sent | N33: Sent 3 Sep 2026 — Batch 1 (60), Target Batch 2 research.
A34: 30 | B34: Lenovo India | E34: Email | F34: 2026-09-03 | G34: N | J34: N | K34: N | L34: N | M34: Sent | N34: Sent 3 Sep 2026 — Batch 1 (60), Target Batch 2 research.
A35: 31 | B35: Western Digital (SanDisk Professional) | E35: Email | F35: 2026-09-03 | G35: N | J35: N | K35: N | L35: N | M35: Sent | N35: Sent 3 Sep 2026 — Batch 1 (60), Target Batch 2 research.
A36: 32 | B36: Samsung India | C36: Sumit Walia | D36: VP, Head of D2C & Corporate Marketing | E36: Email | F36: 2026-09-03 | G36: N | J36: N | K36: N | L36: N | M36: Sent | N36: Sent 3 Sep 2026 — Batch 1 (60), Target Batch 2 research.
A37: 33 | B37: Krutrim AI (Ola Krutrim) | E37: Email | F37: 2026-09-03 | G37: N | J37: N | K37: N | L37: N | M37: Sent | N37: Sent 3 Sep 2026 — Batch 1 (60), Target Batch 2 research.
A38: 34 | B38: Yotta Data Services | E38: Email | F38: 2026-09-03 | G38: N | J38: N | K38: N | L38: N | M38: Sent | N38: Sent 3 Sep 2026 — Batch 1 (60), Target Batch 2 research.
A39: 35 | B39: E2E Networks | C39: Ashish Dixit | D39: VP Marketing | E39: Email | F39: 2026-09-03 | G39: N | J39: N | K39: N | L39: N | M39: Sent | N39: Sent 3 Sep 2026 — Batch 1 (60), Target Batch 2 research.
A40: 36 | B40: Netweb Technologies | E40: Email | F40: 2026-09-03 | G40: N | J40: N | K40: N | L40: N | M40: Sent | N40: Sent 3 Sep 2026 — Batch 1 (60), Target Batch 2 research.
A41: 37 | B41: CtrlS Datacenters | E41: Email | F41: 2026-09-03 | G41: N | J41: N | K41: N | L41: N | M41: Sent | N41: Sent 3 Sep 2026 — Batch 1 (60), Target Batch 2 research.
A42: 38 | B42: Nikon India / RED Digital Cinema | E42: Email | F42: 2026-09-03 | G42: N | J42: N | K42: N | L42: N | M42: Sent | N42: Sent 3 Sep 2026 — Batch 1 (60), Target Batch 2 research.
A43: 39 | B43: Panasonic (Lumix) India | E43: Email | F43: 2026-09-03 | G43: N | J43: N | K43: N | L43: N | M43: Sent | N43: Sent 3 Sep 2026 — Batch 1 (60), Target Batch 2 research.
A44: 40 | B44: Fractal Analytics | C44: Shubhendra Kanade | D44: Head of Marketing | E44: Form | F44: 2026-09-03 | G44: N | J44: N | K44: N | L44: N | M44: Form submitted | N44: Business Opportunity form submitted 3 Sep 2026, reply-to adiup394@gmail.com. Note: message field had a stray phone-number prefix due to a form-fill glitch, rest of message intact. | Status normalised 6 Sep: this is a FORM row that read "Sent". Form was submitted 3 Sep. Do not re-fill.
A45: 41 | B45: AMD | C45: Vinay Sinha | D45: Managing Director, Sales, AMD India | E45: Email | F45: 2026-09-06 | G45: N | J45: N | K45: N | L45: N | M45: Sent | N45: Found via 6 Sep Gmail audit (not originally logged this session). Major AI compute/GPU vendor | MULTI-CHANNEL, not a duplicate: this is the AMD EMAIL send (6 Sep, found via Gmail audit). The AMD enquiry FORM attempt is logged separately at row 45 (3 Sep). Count AMD once when reporting company totals.
A46: 42 | B46: Avid Technology | C46: Raymond Thompson | D46: Senior Director, WW Partners and Alliances | E46: Email | F46: 2026-09-03 | G46: N | J46: N | K46: N | L46: N | M46: Sent | N46: Sent 3 Sep 2026 - Global enterprise/fresh candidate batch, sponsor track.
A47: 43 | B47: Foundry | C47: Jody Madden | D47: CEO | E47: Email | F47: 2026-09-03 | G47: N | J47: N | K47: N | L47: N | M47: Sent | N47: Sent 3 Sep 2026 - Global enterprise/fresh candidate batch, sponsor track.
A48: 44 | B48: Insta360 | C48: Fiona Leung | D48: Global Brand Marketing Director | E48: Email | F48: 2026-09-03 | G48: N | J48: N | K48: N | L48: N | M48: Sent | N48: Sent 3 Sep 2026 - Global enterprise/fresh candidate batch, sponsor track.
A49: 45 | B49: Envato | E49: Email | F49: 2026-09-03 | G49: N | J49: N | K49: N | L49: N | M49: Sent | N49: Elements/stock-content + AI creative tools company. Sent to business@envato.com (business inquiries address). Gmail id 1a0689153454235e.
A50: 46 | B50: Moonvalley AI | E50: Form | F50: 2026-09-03 | G50: N | J50: N | K50: N | L50: N | M50: Form submitted | N50: Genuine "Partner with us" form (studios/directors/filmmakers/agencies/advertisers/brands). Filled Name, Email, Organization, and message covering WAiFF scale + Moonvalley's licensed-data Marey model + CAA/Comcast Ventures funding. Confirmed "Thank you! You have successfully submitted." 3 Sep 2026. | Status normalised 6 Sep: this is a FORM row that read "Sent". Form was submitted 3 Sep. Do not re-fill.
A51: 47 | B51: GoPro | C51: Anne Reilly | D51: VP, Global Sales Operations | E51: Email | F51: 2026-09-03 | G51: N | J51: N | K51: N | L51: N | M51: Bounced | N51: Sponsor@gopro.com bounced 3 Sep — "address couldn't be found." The address was real (verified via GoPro's own X/Twitter reply) but appears defunct now. Not counted as a landed send. Needs a fresh channel if pursued again.
A52: 48 | B52: Christie Digital | E52: Email | F52: 2026-09-03 | G52: N | J52: N | K52: N | L52: N | M52: Sent | N52: Christie's own site explicitly labels this "Public Relations or sponsorship" contact — qualifies as sponsorship-typed. Cinema projection technology company, directly relevant to festival exhibition. Gmail id 1a068a58e2898876.
A53: 49 | B53: D-ID | C53: Susanne Ilemann | D53: SVP Marketing and Business Intelligence | E53: Email | F53: 2026-09-04 | G53: N | J53: N | K53: N | L53: N | M53: Sent
A54: 50 | B54: Krea AI | E54: Email | F54: 2026-09-04 | G54: N | J54: N | K54: N | L54: N | M54: Bounced | N54: press@krea.ai bounced despite being decoded from official press page — Cloudflare-obfuscated address decode may have been imperfect, or inbox retired.
A55: 51 | B55: Character.AI | E55: Email | F55: 2026-09-04 | G55: N | J55: N | K55: N | L55: N | M55: Sent
A56: 52 | B56: CoRover | E56: Email | F56: 2026-09-04 | G56: N | J56: N | K56: N | L56: N | M56: Sent
A57: 53 | B57: Haptik (Jio Haptik) | E57: Email | F57: 2026-09-04 | G57: N | J57: N | K57: N | L57: N | M57: Sent
A58: 54 | B58: FICCI (Media & Entertainment / FRAMES) | E58: Email | F58: 2026-09-04 | G58: N | J58: N | K58: N | L58: N | M58: Sent
A59: 55 | B59: NFDC (National Film Development Corporation) / WAVES Film Bazaar | E59: Email | F59: 2026-09-04 | G59: N | J59: N | K59: N | L59: N | M59: Sent | N59: Government/Institutional track
A60: 56 | B60: Maharashtra Film, Stage & Cultural Development Corporation (Film City Mumbai) | E60: Email | F60: 2026-09-04 | G60: N | J60: N | K60: N | L60: N | M60: Sent | N60: Government/Institutional track
A61: 57 | B61: Four Seasons Hotel Mumbai | E61: Email | F61: 2026-09-06 | G61: N | J61: N | K61: N | L61: N | M61: Sent | N61: Relevance: Premium venue with a luxury-events sales lead named directly on the hotel's own press page
A62: 58 | B62: Taj Hotels (IHCL) | E62: Email | F62: 2026-09-06 | G62: N | J62: N | K62: N | L62: N | M62: Sent | N62: Relevance: India's most recognized hospitality brand, dedicated events inbox
A63: 59 | B63: ITC Hotels | E63: Email | F63: 2026-09-06 | G63: N | J63: N | K63: N | L63: N | M63: Sent | N63: Relevance: Major Indian hospitality group with dedicated event infrastructure
A64: 60 | B64: Grand Hyatt Mumbai | E64: Email | F64: 2026-09-06 | G64: N | J64: N | K64: N | L64: N | M64: Sent | N64: Relevance: Premium Mumbai venue with two dedicated sales/events addresses
A65: 61 | B65: JW Marriott Mumbai Sahar | E65: Form | F65: 2026-09-06 | G65: N | J65: N | K65: N | L65: N | M65: Excluded - already contacted by partner | N65: Relevance: Major Marriott property near the airport, active events business | DO NOT CONTACT. Aditya confirmed 6 Sep that his other partner has already reached out to JW Marriott Mumbai Sahar. Form deliberately NOT filled. Any future batch must exclude this company to avoid a duplicate approach from two people.
A66: 62 | B66: Dabur India | E66: Email | F66: 2026-09-06 | G66: N | J66: N | K66: N | L66: N | M66: Sent | N66: Relevance: One of India's largest FMCG houses with a long history of cultural sponsorships
A67: 63 | B67: Paper Boat (Hector Beverages) | E67: Email | F67: 2026-09-06 | G67: N | J67: N | K67: N | L67: N | M67: Sent | N67: Relevance: Experiential-marketing-native beverage brand, natural fit for a festival activation
A68: 64 | B68: PhonePe | E68: Email | F68: 2026-09-06 | G68: N | J68: N | K68: N | L68: N | M68: Sent | N68: Relevance: India's largest UPI player, strong brand-visibility appetite | AUDIT FINDING (6 Sep Gmail check): this pitch was sent to PhonePe 3 times within ~15 min (14:06, 14:17, 14:22 IST) — a duplicate-send error, not 3 separate outreaches. Treat as ONE real send.
A69: 65 | B69: IndiaAI Mission (MeitY) | E69: Email | F69: 2026-09-06 | G69: N | J69: N | K69: N | L69: N | M69: Sent | N69: Relevance: India's flagship government AI initiative — direct institutional-partner analog for an AI film festival | AUDIT FINDING (6 Sep Gmail check): this pitch was sent to IndiaAI Mission 3 times within ~15 min (14:07, 14:18, 14:22 IST) — a duplicate-send error, not 3 separate outreaches. Treat as ONE real send.
A70: 66 | B70: CBFC (Central Board of Film Certification) | E70: Email | F70: 2026-09-06 | G70: N | J70: N | K70: N | L70: N | M70: Sent | N70: Relevance: India's film certification authority — institutional legitimacy for an AI-generated-film festival | AUDIT FINDING (6 Sep Gmail check): this pitch was sent to CBFC 3 times within ~15 min (14:07, 14:18, 14:23 IST) — a duplicate-send error, not 3 separate outreaches. Treat as ONE real send.
... A77: 73 | B77: Deepgram | E77: Form | F77: 2026-09-06 | G77: N | J77: N | K77: N | L77: N | M77: Draft ready | N77: Relevance: Voice-AI infra vendor relevant to AI film sound/dubbing
A78: 74 | B78: AssemblyAI | E78: Form | F78: 2026-09-06 | G78: Y | H78: 2026-09-05 | I78: AssemblyAI's support explicitly declined: "doesn't evaluate festival, sponsorship, or partnership proposals through this channel." Pushed twice (asked to route to founders/executives) and got a firm final no both times: "We don't have a partnership or sponsorship program that evaluates festival collaborations, so there isn't another team to route this to." | J78: N | K78: N | L78: N | M78: Closed - firm decline, do not re-pursue via this channel | N78: Relevance: Speech recognition/AI infra relevant to AI film production pipelines | Do NOT fill this form. AssemblyAI already declined by email on 5 Sep, twice, stating they do not evaluate festival, sponsorship or partnership proposals through any channel. Filling the sales form would be a re-approach after a firm no.
A79: 75 | B79: Replicate | E79: Form | F79: 2026-09-06 | G79: N | J79: N | K79: N | L79: N | M79: Draft ready | N79: Relevance: Infrastructure layer for AI creative tooling
A80: 76 | B80: Leonardo AI | E80: Form | F80: 2026-09-06 | G80: N | J80: N | K80: N | L80: N | M80: Draft ready | N80: Relevance: AI creative tool with growing enterprise reach
A81: 77 | B81: Krikey AI | E81: Email | F81: 2026-09-06 | G81: N | J81: N | K81: N | L81: N | M81: Sent | N81: Relevance: AI animation/mocap tool, direct filmmaking-adjacent fit
A82: 78 | B82: ServiceNow | E82: Email | F82: 2026-09-06 | G82: N | J82: N | K82: N | L82: N | M82: Sent | N82: Found via 6 Sep Gmail audit (not originally logged this session). Global enterprise AI platform; CC'd press@/emeapr@/APJmedia@servicenow.com
A83: 79 | B83: AMD | C83: Vinay Sinha | D83: Managing Director, Sales, AMD India | E83: Email | F83: 2026-09-06 | G83: N | J83: N | K83: N | L83: N | M83: Sent | N83: Found via 6 Sep Gmail audit (not originally logged this session). Major AI compute/GPU vendor | MULTI-CHANNEL, not a duplicate: this is the AMD EMAIL send (6 Sep, found via Gmail audit). The AMD enquiry FORM attempt is logged separately at row 45 (3 Sep). Count AMD once when reporting company totals.
A84: 80 | B84: Intel | C84: Apurva Jani | D84: Director of Marketing, India Region | E84: Email | F84: 2026-09-06 | G84: N | J84: N | K84: N | L84: N | M84: Bounced | N84: Found via 6 Sep Gmail audit (not originally logged this session). oneventseries@intel.com bounced - address not found; other BCC addresses may have landed
A85: 81 | B85: Supermicro | E85: Email | F85: 2026-09-06 | G85: N | J85: N | K85: N | L85: N | M85: Sent | N85: Found via 6 Sep Gmail audit (not originally logged this session). AI server/infra hardware vendor; CC marketing@supermicro.com
A86: 82 | B86: YuVerse | E86: Email | F86: 2026-09-06 | G86: N | J86: N | K86: N | L86: N | M86: Sent | N86: Found via 6 Sep Gmail audit (not originally logged this session). AI decision-infra company
A87: 83 | B87: IA-Meetings | E87: Email | F87: 2026-09-05 | G87: N | J87: N | K87: N | L87: N | M87: Sent | N87: Found via 6 Sep Gmail audit (not originally logged this session). Global event management company; one BCC domain bounced
A88: 84 | B88: Pictory | E88: Email | F88: 2026-09-05 | G88: N | J88: N | K88: N | L88: N | M88: Sent | N88: Found via 6 Sep Gmail audit (not originally logged this session). AI video creation platform (Pictory 2.0)
A89: 85 | B89: Hedra | E89: Email | F89: 2026-09-05 | G89: N | J89: N | K89: N | L89: N | M89: Sent | N89: Found via 6 Sep Gmail audit (not originally logged this session). AI avatar/generative media platform, $32M Series A
A90: 86 | B90: Ola | E90: Email | F90: 2026-09-05 | G90: N | J90: N | K90: N | L90: N | M90: Sent | N90: Found via 6 Sep Gmail audit (not originally logged this session). Major Indian mobility brand moving toward IPO (distinct from Ola Krutrim/Krutrim AI, already tracked separately)
A91: 87 | B91: Corsair | C91: Jack Peterson | D91: VP Marketing | E91: Email | F91: 2026-09-05 | G91: N | J91: N | K91: N | L91: N | M91: Sent | N91: Found via 6 Sep Gmail audit (not originally logged this session). AI hardware/workstation vendor (CORSAIR PRO line)
A92: 88 | B92: PixVerse | E92: Email | F92: 2026-09-05 | G92: N | J92: N | K92: N | L92: N | M92: Sent | N92: Found via 6 Sep Gmail audit (not originally logged this session). AI video unicorn, $300M round
A93: 89 | B93: Recraft | E93: Email | F93: 2026-09-05 | G93: N | J93: N | K93: N | L93: N | M93: Sent | N93: Found via 6 Sep Gmail audit (not originally logged this session). Generative AI design platform, $30M Series B
A94: 90 | B94: IndiGo | E94: Email | F94: 2026-09-05 | G94: N | J94: N | K94: N | L94: N | M94: Sent | N94: Found via 6 Sep Gmail audit (not originally logged this session). India's largest airline, international expansion story
A95: 91 | B95: Yashobhoomi IICC | E95: Email | F95: 2026-09-05 | G95: N | J95: N | K95: N | L95: N | M95: Sent | N95: Found via 6 Sep Gmail audit (not originally logged this session). Major convention/expo venue in Delhi
A96: 92 | B96: DLF | E96: Email | F96: 2026-09-05 | G96: N | J96: N | K96: N | L96: N | M96: Sent | N96: Found via 6 Sep Gmail audit (not originally logged this session). Major Indian real estate/retail group, new mall launches
A97: 93 | B97: The Park Hotels | E97: Email | F97: 2026-09-05 | G97: N | J97: N | K97: N | L97: N | M97: Bounced | N97: Found via 6 Sep Gmail audit (not originally logged this session). Address not found - bounced, needs fresh contact if repursued
A98: 94 | B98: Videndum | E98: Email | F98: 2026-09-05 | G98: N | J98: N | K98: N | L98: N | M98: Sent | N98: Found via 6 Sep Gmail audit (not originally logged this session). Parent of Vinten/Teradek/SmallHD/Manfrotto, film production equipment
A99: 95 | B99: Hollyland | E99: Email | F99: 2026-09-05 | G99: N | J99: N | K99: N | L99: N | M99: Sent | N99: Found via 6 Sep Gmail audit (not originally logged this session). Wireless video transmission systems, IBC 2026 exhibitor
A100: 96 | B100: Godox | E100: Email | F100: 2026-09-05 | G100: N | J100: N | K100: N | L100: N | M100: Sent | N100: Found via 6 Sep Gmail audit (not originally logged this session). Lighting/flash equipment for filmmakers
A101: 97 | B101: Micron | E101: Email | F101: 2026-09-05 | G101: N | J101: N | K101: N | L101: N | M101: Sent | N101: Found via 6 Sep Gmail audit (not originally logged this session). AI memory/semiconductor, $2.75B India facility
A102: 98 | B102: Seagate | E102: Email | F102: 2026-09-05 | G102: N | J102: N | K102: N | L102: N | M102: Sent | N102: Found via 6 Sep Gmail audit (not originally logged this session). Storage infra for AI/media, named contact
A103: 99 | B103: Sigma | E103: Email | F103: 2026-09-05 | G103: N | J103: N | K103: N | L103: N | M103: Sent | N103: Found via 6 Sep Gmail audit (not originally logged this session). Cinema lens manufacturer
A104: 100 | B104: ARRI | C104: David Bermbach | D104: Managing Director, ARRI Cinetechnik | E104: Email | F104: 2026-09-05 | G104: N | J104: N | K104: N | L104: N | M104: Sent | N104: Found via 6 Sep Gmail audit (not originally logged this session). Premier cinema camera/color science brand
A105: 101 | B105: DJI | C105: Christina Zhang | D105: VP, Sales & Marketing | E105: Email | F105: 2026-09-05 | G105: N | J105: N | K105: N | L105: N | M105: Sent | N105: Found via 6 Sep Gmail audit (not originally logged this session). Drone/handheld cinema camera brand, Osmo Pocket 4P debuted at Cannes
A106: 102 | B106: Adobe | C106: Lara Balazs | D106: CMO & EVP Global Marketing | E106: Email | F106: 2026-09-05 | G106: N | J106: N | K106: N | L106: N | M106: Sent | N106: Found via 6 Sep Gmail audit (not originally logged this session). Adobe on Main / Sundance creative-tools sponsorship team - close analog
...

Sheet Organizer Follow-ups
A1: WAIFF India — Organizer Follow-ups
A2: Organizer track only. One row per company: contact, reply status, and the Day 4 / 11 / 25 follow-up cadence (brief section 10). Row 4 is an example — real rows start at row 5.
A3: # | B3: Company | C3: Contact Name | D3: Contact Title | E3: Channel | F3: Date First Contacted | G3: Reply Received? (Y/N) | H3: Reply Date | I3: What They Said | J3: Day 4 Follow-up (Y/N) | K3: Day 11 Follow-up (Y/N) | L3: Day 25 Follow-up (Y/N) | M3: Status | N3: Notes
A4: 0 | B4: Example Co | C4: Jane Doe | D4: Head of Partnerships | E4: Email | F4: 2026-09-03 | G4: N | J4: N | K4: N | L4: N | M4: Sent | N4: EXAMPLE ROW — edit or delete, do not count as real data
A5: 1 | B5: DNEG India | E5: Email | F5: 2026-09-03 | G5: N | J5: N | K5: N | L5: N | M5: Sent | N5: Sent 3 Sep 2026 — Organizer track batch (media/VFX/exhibition pool).
A6: 2 | B6: Red Chillies Entertainment (Redchillies.vfx) | E6: Email | F6: 2026-09-03 | G6: N | J6: N | K6: N | L6: N | M6: Sent | N6: Sent 3 Sep 2026 — Organizer track batch (media/VFX/exhibition pool).
A7: 3 | B7: Applause Entertainment | C7: Prasoon Garg | D7: Chief Business Officer | E7: Email | F7: 2026-09-03 | G7: N | J7: N | K7: N | L7: N | M7: Sent | N7: Sent 3 Sep 2026 — Organizer track batch (media/VFX/exhibition pool).
A8: 4 | B8: Mythri Movie Makers | E8: Email | F8: 2026-09-03 | G8: N | J8: N | K8: N | L8: N | M8: Sent | N8: Sent 3 Sep 2026 — Organizer track batch (media/VFX/exhibition pool).
A9: 5 | B9: Wizcraft International Entertainment | C9: Pratik Shah | D9: Manager, Business Development | E9: Email | F9: 2026-09-03 | G9: N | J9: N | K9: N | L9: N | M9: Sent | N9: Sent 3 Sep 2026 — Organizer track batch (media/VFX/exhibition pool).
A10: 6 | B10: Ramoji Film City | C10: Mohit Chatwal | D10: Director, Sales, Marketing & Operations | E10: Email | F10: 2026-09-03 | G10: N | J10: N | K10: N | L10: N | M10: Sent | N10: Sent 3 Sep 2026 — Organizer track batch (media/VFX/exhibition pool).
A11: 7 | B11: Lyca Productions | E11: Email | F11: 2026-09-03 | G11: N | J11: N | K11: N | L11: N | M11: Sent | N11: Sent 3 Sep 2026 — Organizer track batch (media/VFX/exhibition pool).
A12: 8 | B12: Prime Focus Technologies | C12: T Shobhana | D12: SVP & Global Head of Marketing & Communications | E12: Email | F12: 2026-09-03 | G12: N | J12: N | K12: N | L12: N | M12: Sent | N12: Sent 3 Sep 2026 — Organizer track batch (media/VFX/exhibition pool).
A13: 9 | B13: NY VFXWAALA | C13: Naveen Paul | D13: Founder & Creative Head / Managing Director | E13: Email | F13: 2026-09-03 | G13: N | J13: N | K13: N | L13: N | M13: Sent | N13: Sent 3 Sep 2026 — Organizer track batch (media/VFX/exhibition pool).
A14: 10 | B14: Qube Cinema Technologies | C14: Harshit Thakkar | D14: Director, Products | E14: Email | F14: 2026-09-03 | G14: N | J14: N | K14: N | L14: N | M14: Sent | N14: Sent 3 Sep 2026 — Organizer track batch (media/VFX/exhibition pool).
A15: 11 | B15: Yash Raj Films | C15: Amit Dwivedi | D15: Marketing | E15: Form | F15: 2026-09-03 | G15: N | J15: N | K15: N | L15: N | M15: Draft ready | N15: Business Queries form filled 3 Sep 2026 (Purpose: Brand Partnerships/Talent Management, name, email, address, detailed message referencing Hemant Kundnani's Head of Marketing appointment). Form has a text CAPTCHA - left for Aditya to complete and submit manually, per the no-CAPTCHA-solving rule.
A16: 12 | B16: JioStar (Jio Studios/Reliance Entertainment) | E16: Email | F16: 2026-09-04 | G16: N | J16: N | K16: N | L16: N | M16: Sent
A17: 13 | B17: Zee Entertainment Enterprises | E17: Email | F17: 2026-09-04 | G17: N | J17: N | K17: N | L17: N | M17: Sent
A18: 14 | B18: Dharma Productions | E18: Email | F18: 2026-09-04 | G18: N | J18: N | K18: N | L18: N | M18: Sent
A19: 15 | B19: IIFA (International Indian Film Academy) | E19: Form | F19: 2026-09-04 | G19: N | J19: N | K19: N | L19: N | M19: Form submitted | N19: Confirmed: "Thank you. Your enquiry has been sent to the IIFA team." | Status normalised 6 Sep: this is a FORM row that read "Sent". Submission confirmed 4 Sep with an on-screen acknowledgement from the IIFA team. Do not re-fill.
A20: 16 | B20: SonyLIV (Culver Max Entertainment) | E20: Form | F20: 2026-09-06 | G20: N | J20: N | K20: N | L20: N | M20: Draft ready | N20: Relevance: Major Indian OTT platform, natural distribution/organizer angle
A21: 17 | B21: hoichoi | E21: Email | F21: 2026-09-06 | G21: Y | H21: 2026-09-06 | I21: Support inbox auto-replied 3x (once per duplicate send) asking for brand-partnership/collaboration enquiries to go directly to sayantan.guha@hoichoi.tv instead of support@hoichoi.tv. | J21: N | K21: N | L21: N | M21: Resolved - Aditya sent the follow-up to sayantan.guha@hoichoi.tv directly. | N21: Relevance: Fast-growing regional OTT platform with a named partnerships routing | AUDIT FINDING (6 Sep Gmail check): this pitch was sent to hoichoi 3 times within ~15 min, and hoichoi auto-replied each time asking to email sayantan.guha@hoichoi.tv directly instead of support@hoichoi.tv. Wrong-channel — needs a fresh, single send to sayantan.guha@hoichoi.tv.
A22: 18 | B22: FTII (Film and Television Institute of India) | E22: Email | F22: 2026-09-06 | G22: N | J22: N | K22: N | L22: N | M22: Sent | N22: Relevance: India's premier film school — a natural jury/masterclass/academic-partner pipeline
A23: 19 | B23: SRFTI (Satyajit Ray Film and Television Institute) | E23: Email | F23: 2026-09-06 | G23: N | J23: N | K23: N | L23: N | M23: Sent | N23: Relevance: Leading Indian film institute with a digital-media specialization closest to AI filmmaking
A24: 20 | B24: T-Hub | E24: Email | F24: 2026-09-06 | G24: N | J24: N | K24: N | L24: N | M24: Sent | N24: Found via 6 Sep Gmail audit (not originally logged this session). India's largest startup incubator/ecosystem body
A25: 21 | B25: Inc42 Media | E25: Email | F25: 2026-09-05 | G25: N | J25: N | K25: N | L25: N | M25: Sent | N25: Found via 6 Sep Gmail audit (not originally logged this session). India's largest tech/startup media platform - potential media partner
A26: 22 | B26: Digital Domain | C26: Sudhir Reddy | D26: President, Global VFX Business | E26: Email | F26: 2026-09-05 | G26: N | J26: N | K26: N | L26: N | M26: Sent | N26: Found via 6 Sep Gmail audit (not originally logged this session). Major VFX studio, new DDAI creative-AI infrastructure
A27: 23 | B27: Weta FX | C27: Daniel Seah | D27: CEO | E27: Email | F27: 2026-09-05 | G27: N | J27: N | K27: N | L27: N | M27: Sent | N27: Found via 6 Sep Gmail audit (not originally logged this session). Premier VFX studio, new AMD AI-rendering partnership
A28: 24 | B28: Framestore | C28: Mel Sullivan | D28: CEO | E28: Email | F28: 2026-09-05 | G28: N | J28: N | K28: N | L28: N | M28: Sent | N28: Found via 6 Sep Gmail audit (not originally logged this session). Major VFX studio, 15 VES Award nominations
A29: 25 | B29: Industrial Light & Magic (ILM) | E29: Email | F29: 2026-09-05 | G29: N | J29: N | K29: N | L29: N | M29: Sent | N29: Found via 6 Sep Gmail audit (not originally logged this session). Legendary VFX studio (Lucasfilm)
A30: 26 | B30: MPC (Moving Picture Company) | E30: Email | F30: 2026-09-05 | G30: N | J30: N | K30: N | L30: N | M30: Sent | N30: Found via 6 Sep Gmail audit (not originally logged this session). Major VFX studio, named contact
A31: 27 | B31: Excel Entertainment | C31: Vishal Ramchandani | D31: CEO | E31: Email | F31: 2026-09-05 | G31: N | J31: N | K31: N | L31: N | M31: Sent | N31: Found via 6 Sep Gmail audit (not originally logged this session). Major Bollywood production house, new-talent-backing mission (Excel Origins)
A32: 28 | B32: Miraj Entertainment (Cinemas) | E32: Email | F32: 2026-09-05 | G32: N | J32: N | K32: N | L32: N | M32: Sent | N32: Found via 6 Sep Gmail audit (not originally logged this session). Fast-expanding Indian multiplex chain
A33: 29 | B33: Anibrain | C33: Jesh Krishna Murthy | D33: Founder & CEO | E33: Email | F33: 2026-09-05 | G33: N | J33: N | K33: N | L33: N | M33: Sent | N33: Found via 6 Sep Gmail audit (not originally logged this session). Indian VFX/animation studio with international credits
A34: 30 | B34: Cinepolis India | C34: Amit Garg | D34: Head of Business Development | E34: Email | F34: 2026-09-05 | G34: N | J34: N | K34: N | L34: N | M34: Sent | N34: Found via 6 Sep Gmail audit (not originally logged this session). Major multiplex chain, 489 screens/41 cities
A35: 31 | B35: Abundantia Entertainment | E35: Email | F35: 2026-09-03 | G35: N | J35: N | K35: N | L35: N | M35: Sent | N35: Found via 6 Sep Gmail audit (not originally logged this session). LinkedIn-sourced contact (Vikram Malhotra) - connected on LinkedIn first, then emailed. Major Indian production house.
A36: 32 | B36: Bombay Exhibition Centre (NESCO) | E36: Email | F36: 2026-09-06 | G36: N | J36: N | K36: N | L36: N | M36: Sent | N36: 6 Sep quality batch (v3, individually written). Hook source: BEC/NESCO hosts large-format national shows in Mumbai including PAMEX 2026 (venue event calendars). 197 words. Meeting ask + IST offered. Website link only, no deck.
A37: 33 | B37: JSW Group / JSW Sports | E37: Email | F37: 2026-09-22 | G37: N | J37: N | K37: N | L37: N
A38: 34 | B38: Mahindra Group | C38: Jay Shah | D38: VP & Head of Cultural Outreach | E38: Email | F38: 2026-09-22 | G38: N | J38: N | K38: N | L38: N
A39: 35 | B39: IFP (India's Culture Company) | E39: Email | F39: 2026-09-22 | G39: N | J39: N | K39: N | L39: N
A40: 36 | B40: Sunburn / Spacebound Web Labs | E40: Email | F40: 2026-09-22 | G40: N | J40: N | K40: N | L40: N
A41: 37 | B41: Kyoorius | E41: Email | F41: 2026-09-22 | G41: N | J41: N | K41: N | L41: N
A42: 38 | B42: Adgully | E42: Email | F42: 2026-09-22 | G42: N | J42: N | K42: N | L42: N
A43: 39 | B43: Pocket Aces | E43: Email | F43: 2026-09-22 | G43: N | J43: N | K43: N | L43: N
A44: 40 | B44: exchange4media | E44: Email | F44: 2026-09-22 | G44: N | J44: N | K44: N | L44: N
A45: 41 | B45: Tech Entrepreneurs Association of Mumbai (TEAM) | E45: Email | F45: 2026-09-22 | G45: N | J45: N | K45: N | L45: N
A46: 42 | B46: AAAI / Goafest | E46: Email | F46: 2026-09-22 | G46: N | J46: N | K46: N | L46: N
A47: 43 | B47: Delta Corp Limited | E47: Email | F47: 2026-09-22 | G47: N | J47: N | K47: N | L47: N
A48: 44 | B48: JK Tyre & Industries | E48: Email | F48: 2026-09-22 | G48: N | J48: N | K48: N | L48: N
A49: 45 | B49: GMR Group | E49: Email | F49: 2026-09-22 | G49: N | J49: N | K49: N | L49: N
A50: 46 | B50: Sula Vineyards | E50: Email | F50: 2026-09-22 | G50: N | J50: N | K50: N | L50: N
... A52: 48 | B52: Sun TV Network Limited | E52: Email | F52: 2026-09-22 | G52: N | J52: N | K52: N | L52: N
A53: 50 | B53: Tata Steel | E53: Email | F53: 2026-09-23 | G53: N | J53: N | K53: N | L53: N | M53: Sent | N53: Apollo-CSV batch 23 Sep 2026
A54: 51 | B54: RX India | E54: Email | F54: 2026-09-23 | G54: N | J54: N | K54: N | L54: N | M54: Sent | N54: Apollo-CSV batch 23 Sep 2026
A55: 52 | B55: Messe Frankfurt India | E55: Email | F55: 2026-09-23 | G55: N | J55: N | K55: N | L55: N | M55: Sent | N55: Apollo-CSV batch 23 Sep 2026
A56: 53 | B56: India Today Group | E56: Email | F56: 2026-09-23 | G56: N | J56: N | K56: N | L56: N | M56: Sent | N56: Apollo-CSV batch 23 Sep 2026
A57: 54 | B57: RPSG Ventures | E57: Email | F57: 2026-09-23 | G57: N | J57: N | K57: N | L57: N | M57: Sent | N57: Apollo-CSV batch 23 Sep 2026
A58: 55 | B58: Torrent Group | E58: Email | F58: 2026-09-23 | G58: N | J58: N | K58: N | L58: N | M58: Sent | N58: Apollo-CSV batch 23 Sep 2026
A59: 56 | B59: EY India | E59: Email | F59: 2026-09-23 | G59: N | J59: N | K59: N | L59: N | M59: Sent | N59: Apollo-CSV batch 23 Sep 2026
A60: 57 | B60: MRF | E60: Email | F60: 2026-09-23 | G60: N | J60: N | K60: N | L60: N | M60: Sent | N60: Apollo-CSV batch 23 Sep 2026
A61: 58 | B61: Bennett Coleman & Co (Times Group) | E61: Email | F61: 2026-09-23 | G61: N | J61: N | K61: N | L61: N | M61: Sent | N61: Apollo-CSV batch 23 Sep 2026 — RETARGET, supersedes earlier guessed-address send
A62: 59 | B62: Conde Nast | E62: Email | F62: 2026-09-23 | G62: N | J62: N | K62: N | L62: N | M62: Sent | N62: Apollo-CSV batch wave 2, 23 Sep 2026
A63: 60 | B63: Mahindra Group | E63: Email | F63: 2026-09-23 | G63: N | J63: N | K63: N | L63: N | M63: Sent | N63: Apollo-CSV batch wave 2, 23 Sep 2026
A64: 61 | B64: Informa Markets India | E64: Email | F64: 2026-09-23 | G64: N | J64: N | K64: N | L64: N | M64: Sent | N64: Apollo-CSV batch wave 2, 23 Sep 2026

Sheet Replies Tracker
A1: WAIFF India — Replies Tracker
A2: Only real, relevant replies go here (not auto-acknowledgements). One row per reply. Track: name of person, company, track, what they said, and what's needed next.
A3: Date | B3: Company | C3: Person Name | D3: Track (Sponsor/Organizer/Existing) | E3: Reply Type | F3: What they said | G3: Follow-up needed | H3: Follow-up sent date | I3: Status
A4: 2026-09-03 | B4: Radisson Blu | C4: Anuj Kumar | D4: Existing (live client) | E4: Real reply - call held | F4: Call held 3 Sep. Anuj is interested in the India edition but needs more lucrative/concrete details before he can move it forward internally — guest/talent finalization and similar specifics. He said he will push it to his internal team and MDs. Per Aditya: hold the reply until India-edition details are firmer; keep him warm, do not send a substantive reply yet. | G4: N (holding per Aditya) | H4: 2026-09-03 | I4: Warm - awaiting more India-edition detail from Aditya before next reply
A5: 2026-09-02 | B5: EPAM Systems | C5: Nandini Bhatnagar (Sr. Director Marketing) | D5: Existing (live client) | E5: Real reply | F5: Suggested speaking after the 9th; looping in colleague Sameena Ali to help set something up. | G5: Y | H5: 2026-09-03 | I5: Awaiting scheduling after 9th
A6: 2026-09-03 | B6: NVIDIA | C6: Shristi Mahnot (India Enterprise PR Manager) | D6: Sponsor | E6: Real reply - decline then referral | F6: Declined sponsorship directly (PR does not handle it), then looped in colleague Kavita Aroor for ecosystem/developer-relations angle. | G6: Y | H6: 2026-09-03 | I6: Awaiting Kavita's reply
A7: 2026-09-03 | B7: Zoho | C7: Partner Operations team | D7: Sponsor | E7: Auto-routed to partner program | F7: Sales team gave generic product info; partner-operations team pointed to zoho.com/partners as the standard partner program, not a direct sponsorship conversation. | G7: N | I7: Low priority - generic partner program, not a real lead
A8: 2026-09-03 | B8: Vidu (Shengshu Technology) | C8: support team | D8: Sponsor | E8: Automated acknowledgement | F8: Generic thank-you, said team will follow up if there's a collaboration opportunity. | G8: N | I8: Wait and see
A9: 2026-09-03 | B9: Nikon (RED Digital Cinema) | C9: NIND Support | D9: Sponsor | E9: Automated acknowledgement | F9: Said details shared with the respective team for review. | G9: N | I9: Wait and see
A10: 2026-09-03 | B10: NVIDIA | C10: Kavita Aroor (Head Enterprise & Developer Marketing, South Asia) | D10: Sponsor | E10: Real reply - data request | F10: Asked for 2025 highlights and public data points before internal review. Replied with verified figures (6,000+ applications/100+ countries 2026, leadership names, global footprint, press coverage), all cross-checked against worldaifilmfestival.com and independent press. | G10: Y | H10: 2026-09-03 | I10: Awaiting internal review, ~2 weeks
A11: 2026-09-04 | B11: Leela (hotel group) | C11: Aparna Singh (Sales Manager - Catering) | D11: Sponsor | E11: Real reply - venue quote received | F11: Note: this is venue/catering RFQ, not sponsorship — Aditya requested a quote to host the WAIFF India event AT The Leela Mumbai. Sent a full waitlisted proposal for 15 Dec 2026, 800 guests: Grand Ballroom (11,742 sq ft), buffet lunch INR 3,300+18% GST/person, buffet dinner INR 3,600+18% GST/person, minimum revenue INR 55,20,000+taxes/day. Includes banquet floor plan, AV list, beverage list, ballroom layout deck as attachments. Space is on WAITLIST basis, and the quote is explicitly valid only 48 hours from send (received 2026-09-04 ~11:01 IST). | G11: Y - time-sensitive, Aditya to decide | I11: ACTION NEEDED: quote expires ~2026-09-06 11:00 IST. Aditya to review pricing/decide whether to hold the space, negotiate, or pass — this is a venue decision, not a sponsor pitch, so Claude is not acting on it without Aditya.
A12: 2026-09-05 | B12: AssemblyAI | C12: Joey (AI support agent) | D12: Sponsor | E12: Real reply - firm decline | F12: AssemblyAI's support explicitly declined: "doesn't evaluate festival, sponsorship, or partnership proposals through this channel." Pushed twice (asked to route to founders/executives) and got a firm final no both times: "We don't have a partnership or sponsorship program that evaluates festival collaborations, so there isn't another team to route this to." | G12: N | I12: Closed - firm decline, do not re-pursue via this channel
A13: 2026-09-05 | B13: boAt (Imagine Marketing) | C13: Team boAt (support) | D13: Sponsor | E13: Real reply - acknowledgement | F13: "Thanks for showing interest. We have forwarded your request to the concerned team. They will get in touch with you post reviewing the requirements." | G13: N | I13: Wait and see - forwarded internally
A14: 2026-09-06 | B14: hoichoi | C14: support team (auto) | D14: Organizer | E14: Wrong channel - redirect given | F14: Support inbox auto-replied 3x (once per duplicate send) asking for brand-partnership/collaboration enquiries to go directly to sayantan.guha@hoichoi.tv instead of support@hoichoi.tv. | G14: Y - done | H14: 2026-09-06 | I14: Resolved - Aditya sent the follow-up to sayantan.guha@hoichoi.tv directly.
A15: 2026-09-07 | B15: Grand Hyatt Mumbai | C15: Rupal Mathur (Sales, MUMGH) | D15: Sponsor | E15: Real reply - asked for contact/time | F15: "Thank you for writing to us. Kindly share your direct contact number and a suitable time to connect so that we can discuss the details as mentioned in the trail email." Aditya replied with his number and proposed around 5 PM today (7 Sep), asked her to WhatsApp given call volume. | G15: Y | H15: 2026-09-07 | I15: On Meetings Log - today 5 PM, awaiting her confirmation
A16: 2026-09-07 | B16: MG Motor India | C16: MG Pulse Hub (support) | D16: Sponsor | E16: Real reply - acknowledgement, routed internally | F16: "Thank you for showing interest in MG Motor India. We have shared your proposal with the department concerned. The team will connect with you if they wish to take this forward." Ticket ref 7015150. | G16: N | I16: Wait and see - forwarded internally, no time proposed
A17: 2026-09-07 | B17: Yashobhoomi IICC | C17: Prabhjot Singh Bedi (Head, Convention Sales & Marketing) | D17: Sponsor / venue | E17: Real reply - wants a time | F17: "Thank you for expressing your interest in Yashobhoomi ... Kindly let us know a convenient time for a call this week. It would also be helpful if you could share your contact details." Mobile: 9971148820. | G17: N | I17: DROPPED 7 Sep at Adityas instruction. Not being pursued. Delhi venue, Mumbai event.
A18: 2026-09-07 | B18: IA-Meetings | C18: Pooja Menon (Sr. Manager, International Sales, Singapore) | D18: Organizer | E18: Real reply - wants a time | F18: "Thank you for your email. We can fix up a meeting sometime today or tomorrow. I would like to hear more about this." | G18: Y - done | H18: 2026-09-07 | I18: Times offered: 7 PM IST today or 3-5 PM IST tomorrow. Awaiting her pick.
A19: 2026-09-07 | B19: YuVerse | C19: Ajay Arvind Bhanushali (Sales) | D19: Sponsor | E19: Real reply - asked for details, offered to push internally | F19: Connected with Aditya directly and asked for written detail on WAiFF so he can take it to his team, and push it to marketing if it lands. Aditya shared the WAiFF website over WhatsApp. Reply came through WhatsApp/phone, not Gmail. | G19: Y - done | H19: 2026-09-07 | I19: Detail pack sent 7 Sep to Ajayarvind.bhanushali@yuverse.ai. Awaiting internal routing to their marketing team.
A20: 2026-09-07 | B20: Trident BKC (Oberoi Group) | C20: Puja Singh, Sales Supervisor - Banquet | D20: Sponsor / venue | E20: Real reply - asked for event details to build a proposal | F20: Sent a nine-point checklist (company name, address, purpose, guest nationality, billing, date, timing, headcount, meal preference) to enable a proposal. Cc'd Tarang Kaur at oberoigroup.com. Treated it as a banquet booking rather than a partnership. | G20: Y - done | H20: 2026-09-07 | I20: Replied 7 Sep. Answered honestly what is known (company, purpose, international guests, December 2026) and declined to invent headcount, timings, catering or billing. Reframed the ask as a host-hotel partnership using the JW Marriott Cannes precedent and asked her to route it to marketing / brand partnerships. BCC'd Silki Sehgal, the Oberoi Group's published media contact.
A21: 2026-09-07 | B21: Grand Hyatt Mumbai | C21: Rupal Mathur (Sales, MUMGH) | D21: Sponsor | E21: Update - sales desk, needs marketing routing | F21: Rupal is sales, not marketing. Aditya asked her to connect him to the relevant marketing team or share the data. Today's 5 PM call is cancelled as a result. | G21: Y - done | H21: 2026-09-07 | I21: Full WAiFF picture emailed 7 Sep, reframed from booking to host-hotel partnership. Nikhil Dalvi cc'd, Deepa Krishnan (Hyatt Communications, South West Asia) BCC'd. Awaiting a marketing introduction before rebooking.
A22: 2026-09-07 | B22: Hayat | C22: (name TBD - identity unconfirmed) | D22: Unclassified | E22: Real reply - call booked (reported by Aditya) | F22: Aditya reported a reply and a quick call scheduled for 8 Sep, 1 PM. No matching send exists in Gmail Tracker - not a Claude-originated lead. | G22: Y - confirm identity before call | H22: 2026-09-07 | I22: Logged verbally 7 Sep. Flagged to Aditya: please confirm full company name/role so a proper brief can be built before the call.
A23: 2026-09-07 | B23: Balaji Telefilms | C23: (name TBD) | D23: Organizer | E23: Real reply - meeting booked (reported by Aditya) | F23: Aditya reported a reply and a meeting booked for 9 Sep, 3 PM. No matching send exists in Gmail Tracker. | G23: N - meeting already booked | H23: 2026-09-07 | I23: Logged verbally 7 Sep. Major Indian TV/OTT production house (Ekta Kapoor). Meeting Context block added for the 9 Sep meeting.
A24: 2026-09-07 | B24: Laqshya Live Experiences | C24: (name TBD) | D24: Organizer | E24: Call expected (reported by Aditya) | F24: Aditya expects a call tomorrow (8 Sep). No matching send exists in Gmail Tracker. | G24: N - awaiting call | I24: Logged verbally 7 Sep. Corrected transcription from "Lakshya Life Experiences" - real entity is Laqshya Live Experiences, Mumbai experiential/events company under Laqshya Media Group.
A25: 2026-09-14 | B25: ShareChat & Moj (Mohalla Tech) | C25: Soumitra Maity (Head - PR & Communications) | D25: Sponsor | E25: Real reply - inbound interest, contact details requested | F25: Soumitra Maity (Head - PR & Communications, ShareChat & Moj) replied to the 13 Sep cold email: "Could you pls share your contact details to discuss this in detail?" Aditya replied with his number (+91 76899 06665) the same morning. Soumitra's stated blocker was that there was not enough material on the WAiFF website to understand the offer. | G25: Y - done same day | H25: 2026-09-14 | I25: Decks and material sent by Aditya direct. Next step is a call. Aditya to schedule.

Sheet Daily Log
A1: WAIFF India — Daily Outreach Log
A2: Date-wise breakdown, pulled live from the Gmail Tracker tab (COUNTIFS formulas — recalculates automatically as new rows are added). Fill in the "Notes / milestones" column by hand.
A4: Date | B4: Companies contacted | C4: Emails sent (clean) | D4: Bounced | E4: Forms submitted | F4: Replies received (as of today) | G4: Meetings booked (as of today) | H4: Notes / milestones
A5: 2026-09-01 | B5: =COUNTIF('Gmail Tracker'!$A$4:$A$500,$A5) | C5: =COUNTIFS('Gmail Tracker'!$A$4:$A$500,$A5,'Gmail Tracker'!$C$4:$C$500,"Email",'Gmail Tracker'!$G$4:$G$500,"<>Y") | D5: =COUNTIFS('Gmail Tracker'!$A$4:$A$500,$A5,'Gmail Tracker'!$G$4:$G$500,"Y") | E5: =COUNTIFS('Gmail Tracker'!$A$4:$A$500,$A5,'Gmail Tracker'!$C$4:$C$500,"Form") | F5: =COUNTIFS('Gmail Tracker'!$A$4:$A$500,$A5,'Gmail Tracker'!$H$4:$H$500,"Y") | G5: =COUNTIFS('Gmail Tracker'!$A$4:$A$500,$A5,'Gmail Tracker'!$M$4:$M$500,"Y") | H5: Campaign start.
A6: 2026-09-02 | B6: =COUNTIF('Gmail Tracker'!$A$4:$A$500,$A6) | C6: =COUNTIFS('Gmail Tracker'!$A$4:$A$500,$A6,'Gmail Tracker'!$C$4:$C$500,"Email",'Gmail Tracker'!$G$4:$G$500,"<>Y") | D6: =COUNTIFS('Gmail Tracker'!$A$4:$A$500,$A6,'Gmail Tracker'!$G$4:$G$500,"Y") | E6: =COUNTIFS('Gmail Tracker'!$A$4:$A$500,$A6,'Gmail Tracker'!$C$4:$C$500,"Form") | F6: =COUNTIFS('Gmail Tracker'!$A$4:$A$500,$A6,'Gmail Tracker'!$H$4:$H$500,"Y") | G6: =COUNTIFS('Gmail Tracker'!$A$4:$A$500,$A6,'Gmail Tracker'!$M$4:$M$500,"Y") | H6: Ramp continues — AI/media sponsor batch.
A7: 2026-09-03 | B7: =COUNTIF('Gmail Tracker'!$A$4:$A$500,$A7) | C7: =COUNTIFS('Gmail Tracker'!$A$4:$A$500,$A7,'Gmail Tracker'!$C$4:$C$500,"Email",'Gmail Tracker'!$G$4:$G$500,"<>Y") | D7: =COUNTIFS('Gmail Tracker'!$A$4:$A$500,$A7,'Gmail Tracker'!$G$4:$G$500,"Y") | E7: =COUNTIFS('Gmail Tracker'!$A$4:$A$500,$A7,'Gmail Tracker'!$C$4:$C$500,"Form") | F7: =COUNTIFS('Gmail Tracker'!$A$4:$A$500,$A7,'Gmail Tracker'!$H$4:$H$500,"Y") | G7: =COUNTIFS('Gmail Tracker'!$A$4:$A$500,$A7,'Gmail Tracker'!$M$4:$M$500,"Y") | H7: Largest single-day batch — full sponsor + organizer sweep across VFX, hardware, cloud, and production-house targets.
A8: 2026-09-04 | B8: =COUNTIF('Gmail Tracker'!$A$4:$A$500,$A8) | C8: =COUNTIFS('Gmail Tracker'!$A$4:$A$500,$A8,'Gmail Tracker'!$C$4:$C$500,"Email",'Gmail Tracker'!$G$4:$G$500,"<>Y") | D8: =COUNTIFS('Gmail Tracker'!$A$4:$A$500,$A8,'Gmail Tracker'!$G$4:$G$500,"Y") | E8: =COUNTIFS('Gmail Tracker'!$A$4:$A$500,$A8,'Gmail Tracker'!$C$4:$C$500,"Form") | F8: =COUNTIFS('Gmail Tracker'!$A$4:$A$500,$A8,'Gmail Tracker'!$H$4:$H$500,"Y") | G8: =COUNTIFS('Gmail Tracker'!$A$4:$A$500,$A8,'Gmail Tracker'!$M$4:$M$500,"Y") | H8: Government/institutional track added (NFDC, Maharashtra Film Corp) + new copywriting standards drafted (brief section 16) + IIFA form landed.
A9: TOTAL | B9: =SUM(B5:B8) | C9: =SUM(C5:C8) | D9: =SUM(D5:D8) | E9: =SUM(E5:E8) | F9: =SUM(F5:F8) | G9: =SUM(G5:G8)

Sheet LinkedIn Profiles To Connect
A1: LinkedIn profiles sourced 12 Sep 2026 - Aditya sends the connection requests himself
A2: Seniority column flags who is a real decision-maker. Claude never accesses LinkedIn directly; these came from public web search listings.
A4: Name | B4: Title | C4: Company | D4: LinkedIn URL | E4: Seniority | F4: Outreach status | G4: Notes
A5: Fei-Fei Li | B5: Cofounder & CEO | C5: World Labs | D5: linkedin.com/in/fei-fei-li-4541247 | E5: SENIOR - CEO | F5: Emailed 12 Sep
A6: Alex (Oleksandr) Serdiuk | B6: CEO & Co-founder | C6: Respeecher | D6: linkedin.com/in/oleksandrserdiuk | E6: SENIOR - CEO | F6: Form pending | G6: Respeecher has a real partnership-offer form
A7: Ivan Kuzin | B7: Business Development / GTM | C7: Deepdub | D7: il.linkedin.com/in/ikuzin | E7: Mid - BD | F7: Emailed 12 Sep
A8: Gal Machnay | B8: Business Development | C8: Deepdub | D8: il.linkedin.com/in/gal-machnay-8a50bb247 | E8: Mid - BD | F8: Emailed 12 Sep
A9: Ofir Krakowski | B9: Co-founder | C9: Deepdub | D9: linkedin.com/in/ofir-krakowski | E9: SENIOR - Founder | F9: Emailed 12 Sep
A10: Akshat Prakash | B10: Co-founder | C10: CAMB.AI | D10: linkedin.com/in/akshat-prakash | E10: SENIOR - Founder | F10: No email channel | G10: LinkedIn is the only route in
A11: Hammad Syed | B11: Co-Founder & COO | C11: PlayAI (play.ht) | D11: linkedin.com/in/syed-hammad-ahmed | E11: SENIOR - Founder | F11: No email channel | G11: Reportedly acquired by Meta
A12: Marton Nagy | B12: MCP Apps | C12: VEED.IO | D12: linkedin.com/in/tonmarton | E12: Junior - skip | F12: Form pending
A13: Ilan Bass | B13: Team | C13: Flawless AI | D13: linkedin.com/in/ilan-bass-25a4037 | E13: Unknown | F13: Form pending
A14: Chris Orozco | B14: Team | C14: Flawless AI | D14: linkedin.com/in/chris-orozco-385157a8 | E14: Unknown | F14: Form pending
A15: Weili Zhang | B15: Growth, NA/EU/LATAM | C15: Meshy AI | D15: linkedin.com/in/weili-zhang-39b273157 | E15: Mid - Growth | F15: Form pending
A16: Ariel Zhang | B16: Team | C16: Meshy AI | D16: linkedin.com/in/arielzhangdw | E16: Unknown | F16: Form pending
A17: Anu Sharma | B17: Marketing Manager | C17: Fujifilm India | D17: in.linkedin.com/in/anu-sharma-743469107 | E17: Mid - Marketing | F17: No email channel | G17: Fujifilm India publishes no email - LinkedIn is the route
A18: Shaiphali Galhotra | B18: Head of Digital Marketing & Content, Instax | C18: Fujifilm India | D18: in.linkedin.com/in/shaiphali-galhotra | E18: SENIOR - Head | F18: No email channel | G18: Fujifilm India dead end by email
A19: Amrita Pandey | B19: CEO | C19: Junglee Pictures | D19: linkedin.com/in/amrita-pandey-35b6b3119 | E19: SENIOR - CEO | F19: No email channel | G19: Junglee site unreachable - LinkedIn is the only route
A20: Ajit Andhare | B20: Head of combined Studio business | C20: JioStar | D20: linkedin.com/in/ajit-andhare-1931372 | E20: SENIOR - Head | F20: Company already contacted
A21: Guneet Monga Kapoor | B21: Founder & CEO | C21: Sikhya Entertainment | D21: in.linkedin.com/in/guneetmonga | E21: SENIOR - CEO | F21: Form pending | G21: Oscar winner, Jio Studios took a stake
A22: Kumar Mangat Pathak | B22: Founder Emmay / Chairman Panorama | C22: Emmay & Panorama Studios | D22: in.linkedin.com/in/kumar-mangat-pathak | E22: SENIOR - Chairman | F22: Emailed 12 Sep | G22: Covers two companies
A23: Abhishek Pathak | B23: Managing Director | C23: Panorama Studios | D23: in.linkedin.com/in/abhishek-pathak-b9999380 | E23: SENIOR - MD | F23: Emailed 12 Sep
A24: Hiren Gada | B24: CEO | C24: Shemaroo Entertainment | D24: in.linkedin.com/in/hiren-gada-4a98805 | E24: SENIOR - CEO | F24: No email channel | G24: Shemaroo publishes no business email
A25: Puneet Das | B25: Chief Marketing Officer | C25: Britannia Industries | D25: in.linkedin.com/in/puneet-das-6a52917 | E25: SENIOR - CMO | F25: Emailed 12 Sep | G25: Appointed Feb 2026
A26: Kalpana Singh | B26: Chief Marketing Officer | C26: Raymond Lifestyle | D26: linkedin.com/in/kalpanasinghmarketingleader | E26: SENIOR - CMO | F26: Emailed 12 Sep
A27: Ashwin Moorthy | B27: Chief Marketing Officer | C27: Godrej Consumer Products | D27: linkedin.com/in/ashwinmoorthy | E27: SENIOR - CMO | F27: No email channel | G27: GCPL dead end by email - LinkedIn is the route
A28: Suruchi Kore | B28: Head, Digital & Social Strategies | C28: Bajaj Electricals | D28: linkedin.com/in/suruchi-digital-pr-marketing-strategist | E28: SENIOR - Head | F28: Emailed 12 Sep
A29: Ramkrishna Naik | B29: Chief Marketing Officer | C29: Kansai Nerolac | D29: linkedin.com/in/ramkrishna-naik-7704298 | E29: SENIOR - CMO | F29: Emailed 12 Sep
A30: Pragya Bijalwan | B30: Business Head, Home Comfort (ex-CMO) | C30: Voltas | D30: linkedin.com/in/pragyabijalwan | E30: SENIOR - Business Head | F30: Emailed 12 Sep
A31: Girish Hingorani | B31: VP Marketing & Corporate Communications | C31: Blue Star | D31: linkedin.com/in/girishhingorani | E31: SENIOR - VP | F31: Emailed 12 Sep | G31: Emailed him directly by name
A32: Goldy Goel | B32: Marketing Manager | C32: Blue Star | D32: linkedin.com/in/goldygoel | E32: Mid - Marketing | F32: Company emailed
A33: Sameer Wanchoo | B33: Chief Marketing Officer | C33: VIP Industries | D33: linkedin.com/in/sameer-wanchoo-a505134 | E33: SENIOR - CMO | F33: Emailed 12 Sep | G33: Appointed Dec 2025
A34: Arindam Roy | B34: Head of Marketing Comms, Caprese | C34: VIP Industries | D34: linkedin.com/in/arindamroymumbai | E34: SENIOR - Head | F34: Company emailed
A35: Adwaita Nayar | B35: Co-founder & CEO, Nykaa Fashion | C35: Nykaa | D35: linkedin.com/in/adwaita-nayar-b5027532 | E35: SENIOR - CEO | F35: Emailed 12 Sep
A36: Anchit Nayar | B36: Executive Director | C36: Nykaa | D36: linkedin.com/in/anchit-nayar-168aa320 | E36: SENIOR - ED | F36: Emailed 12 Sep
A37: Neha Gupta | B37: Head of Marketing India | C37: Lenskart | D37: linkedin.com/in/nehagupta2511 | E37: SENIOR - Head | F37: Emailed 12 Sep
A38: Gaurav Khatri | B38: CEO & Co-Founder | C38: Noise | D38: linkedin.com/in/gauravkhatrigonoise | E38: SENIOR - CEO | F38: Emailed 12 Sep
A39: Varun Gupta | B39: Founder & CEO | C39: Boult Audio | D39: linkedin.com/in/boultervarun | E39: SENIOR - CEO | F39: Emailed 12 Sep
A40: Tarun Gupta | B40: Co-Founder | C40: Boult Audio | D40: linkedin.com/in/boultertarun | E40: SENIOR - Founder | F40: Emailed 12 Sep
A41: Anoop Manohar | B41: Chief Marketing Officer | C41: Axis Bank | D41: linkedin.com/in/anoop-manohar-05933810 | E41: SENIOR - CMO | F41: No email channel | G41: Axis Bank dead end by email - LinkedIn is the route
A42: Gourav Sharma | B42: Chief Marketing Officer | C42: Bajaj Finserv | D42: in.linkedin.com/in/gourav-sharma-48ab911a0 | E42: SENIOR - CMO | F42: Emailed 12 Sep
A43: Jester Paul | B43: Marketing Head | C43: Paytm | D43: in.linkedin.com/in/jester-paul-449123203 | E43: SENIOR - Head | F43: Emailed 12 Sep
A44: Rohit Agarwala | B44: Content & Media | C44: Zerodha | D44: in.linkedin.com/in/rohitagarwala98 | E44: Mid - Media | F44: Emailed 12 Sep
A45: Pradheep Manivel | B45: Head of Marketing & Growth | C45: Groww | D45: in.linkedin.com/in/pradheep-manivel | E45: SENIOR - Head | F45: Emailed 12 Sep
A46: Zameer Kochar | B46: Chief Marketing Officer | C46: Angel One | D46: linkedin.com/in/zameer-kochar-61140732 | E46: SENIOR - CMO | F46: Emailed 12 Sep | G46: Named him in the email
A47: Joaquin Cuenca Abela | B47: CEO & Co-founder | C47: Freepik / Magnific | D47: linkedin.com/in/joaquin-cuenca-abela-905717a | E47: SENIOR - CEO | F47: Company already contacted
A48: Peng Zhang | B48: CEO | C48: Zhipu AI (Z.ai) | D48: linkedin.com/in/peng-zhang-771b94212 | E48: SENIOR - CEO | F48: Emailed 12 Sep
A49: Jakob Balslev | B49: CEO & Founder | C49: Rokoko | D49: dk.linkedin.com/in/jakob-balslev | E49: SENIOR - CEO | F49: Emailed 12 Sep
A50: Tino Millar | B50: Founder & CEO | C50: Move AI | D50: uk.linkedin.com/in/tino-millar-7b2a8b329 | E50: SENIOR - CEO | F50: Emailed 12 Sep
A51: Phil Salesses | B51: Team | C51: Move AI | D51: linkedin.com/in/philsalesses | E51: Unknown | F51: Company emailed
A52: Nikola Todorovic | B52: Co-Founder | C52: Wonder Dynamics (Autodesk) | D52: linkedin.com/in/nikola-todorovic3 | E52: SENIOR - Founder | F52: Autodesk already contacted
A53: Pinar Demirdag | B53: Co-Founder & CEO | C53: Cuebric | D53: linkedin.com/in/pinar-demirdag-a6429a311 | E53: SENIOR - CEO | F53: Emailed 12 Sep | G53: Named her in the email
A54: Kunal Shanker | B54: General Manager | C54: Novotel Mumbai Juhu Beach | D54: linkedin.com/in/kunalshanker | E54: SENIOR - GM | F54: Emailed 12 Sep | G54: Named him in the email
A55: Anitha Krishnanchettiyar | B55: Director, Human Resources | C55: The Westin Mumbai Powai Lake | D55: linkedin.com/in/anitha-krishnanchettiyar-572aa011 | E55: SENIOR - Director | F55: Form pending | G55: Westin is form-only
A56: Joel Steinfeld | B56: Director of Corporate Communications | C56: Salesforce | D56: linkedin.com/in/joel-steinfeld-9292317 | E56: SENIOR - Director | F56: Form pending | G56: Role not re-verified as current

Sheet AI Festival Sponsors
A1: Companies that ALREADY sponsor AI film festivals - researched 12 Sep 2026
A2: These have already proven they will pay for exactly this association. Highest-conversion target pool.
A4: Company | B4: Festival(s) sponsored | C4: India presence | D4: Our status | E4: Evidence
A5: Adobe | B5: Runway AIFF (presenting partner); Sundance $20m Film & TV Fund | C5: Yes - Noida, Bengaluru | D5: Already contacted | E5: aif.runwayml.com; news.adobe.com
A6: NVIDIA | B6: Runway AIFF (presenting partner) | C6: Yes - major India ops | D6: Already contacted, follow-up due | E6: aif.runwayml.com
A7: Lionsgate | B7: Runway AIFF (presenting partner) | C7: Yes - Lionsgate Play India | D7: EMAILED 12 Sep | E7: aif.runwayml.com
A8: Roku | B8: Runway AIFF (presenting partner) | C8: Limited | D8: EMAILED 12 Sep | E8: aif.runwayml.com
A9: Monks | B9: Runway AIFF (presenting partner) | C9: Yes - India delivery offices | D9: Form only - pending | E9: aif.runwayml.com; monks.com/connect
